Workbook
Name IQ_CH: 110000
Name IQ_CQ: 5000
Name IQ_CY: 10000
Name IQ_DAILY: 500000
Name IQ_FH: 100000
Name IQ_FQ: 500
Name IQ_FY: 1000
Name IQ_LTM: 2000
Name IQ_MONTH: 15000
Name IQ_NTM: 6000
Name IQ_WEEK: 50000
Name IQ_YTD: 3000

Sheet README
A1: This model is an interactive model. Text in blue are hardcoded values and their origin is stated with a website link. All black text are formulas. Do not change the formulas. All worksheets are interconnected.
A2: Note: Saves of the model goes through a iterative process of updated tables so wait for the end of the save to complete before looking at IRR
A3: Glossary of Worksheets
A4: # | B4: Worksheet Name | C4: Type | D4: Description
A5: 1 | B5: graphs | C5: Summary | D5: provides various graphs based on the calculated data
A6: =SUM(A5+1) -> 2 | B6: Summary | C6: Summary | D6: Provides the summary of the calculations to include the IRR.
A7: =SUM(A6+1) -> 3 | B7: Data Sources | C7: Financial | D7: All inputs to the model are located on this worksheet. This is where you change items.
A8: =SUM(A7+1) -> 4 | B8: Inputs | C8: Financial | D8: Reads the Data sources values and calculates the yearly and monthly values
A9: =SUM(A8+1) -> 5 | B9: Project Equity | C9: Financial | D9: Assumes the CREC ownership and other partners equity then shows the equity flows out of the project
A10: =SUM(A9+1) -> 6 | B10: CapEx | C10: Financial | D10: Provides the equipment and engineering costs plus management reserve for the project. It also shows country origins of the equipment
A11: =SUM(A10+1) -> 7 | B11: Financials Yearly | C11: Financial | D11: Takes the monthly calculations in Financial worksheet and rolls it up to yearly values.
A12: =SUM(A11+1) -> 8 | B12: Quarterly | C12: Financial | D12: Takes the monthly calculations in Financial worksheet and rolls it up to quarterly values.
A13: =SUM(A12+1) -> 9 | B13: Financials | C13: Financial | D13: Calculates the monthly revenue and expenses for the project over 25 years
A14: =SUM(A13+1) -> 10 | B14: Capital Contributions | C14: Financial | D14: Shows the loans and interest rates and then does the draw downs and repayments back calculations
A15: =SUM(A14+1) -> 11 | B15: Insurance | C15: Financial | D15: Covers insuarnce costs for MIGA and technical Risk insurance
A16: =SUM(A15+1) -> 12 | B16: Cash Draw Down Schedule | C16: Financial | D16: Shows the drawdown schedule for the project on engineering and also the equipment ordering
A17: =SUM(A16+1) -> 13 | B17: NPV IRR | C17: Financial | D17: Net Present Value worksheet
... A29: =SUM(A28+1) -> 25 | B29: Job Descriptions | C29: Financial | D29: Description of each job type

Sheet graphs
B1: ='Financials Yearly'!C2 -> 2026 | C1: ='Financials Yearly'!D2 -> 2027 | D1: ='Financials Yearly'!E2 -> 2028 | E1: ='Financials Yearly'!F2 -> 2029 | F1: ='Financials Yearly'!G2 -> 2030 | G1: ='Financials Yearly'!H2 -> 2031 | H1: ='Financials Yearly'!I2 -> 2032 | I1: ='Financials Yearly'!J2 -> 2033 | ... X1: ='Financials Yearly'!Y2 -> 2048
A2: ='Financials Yearly'!B30 -> Total Revenue | B2: ='Financials Yearly'!C30 -> 0 | C2: ='Financials Yearly'!D30 -> 42079158 | D2: ='Financials Yearly'!E30 -> 73261683 | E2: ='Financials Yearly'!F30 -> 79804722 | F2: ='Financials Yearly'!G30 -> 81225242 | G2: ='Financials Yearly'!H30 -> 82228620 | H2: ='Financials Yearly'!I30 -> 83477384 | ... X2: ='Financials Yearly'!Y30 -> 1.072573e+08
A3: ='Financials Yearly'!B49 -> Total Expenses | B3: ='Financials Yearly'!C49 -> 4213882 | C3: ='Financials Yearly'!D49 -> 14503585 | D3: ='Financials Yearly'!E49 -> 16601801 | E3: ='Financials Yearly'!F49 -> 14831084 | F3: ='Financials Yearly'!G49 -> 14043197 | G3: ='Financials Yearly'!H49 -> 13700323 | H3: ='Financials Yearly'!I49 -> 13326671 | ... X3: ='Financials Yearly'!Y49 -> 11376319
A4: ='Financials Yearly'!B63 -> Interest Expense | B4: ='Financials Yearly'!C63 -> 9254241.3 | C4: ='Financials Yearly'!D63 -> 14539844 | D4: ='Financials Yearly'!E63 -> 12846521 | E4: ='Financials Yearly'!F63 -> 11888300 | F4: ='Financials Yearly'!G63 -> 11002521 | G4: ='Financials Yearly'!H63 -> 10052709 | H4: ='Financials Yearly'!I63 -> 9034234.5 | ... X4: ='Financials Yearly'!Y63 -> 0
A5: ='Financials Yearly'!B94 -> Debt Amortization Payments | B5: ='Financials Yearly'!C94 -> 0 | C5: ='Financials Yearly'!D94 -> 8061833.3 | D5: ='Financials Yearly'!E94 -> 11427056 | E5: ='Financials Yearly'!F94 -> 12253119 | F5: ='Financials Yearly'!G94 -> 13138898 | G5: ='Financials Yearly'!H94 -> 14088710 | H5: ='Financials Yearly'!I94 -> 15107184 | ... X5: ='Financials Yearly'!Y94 -> 0
A7: ='Financials Yearly'!B87 -> Cashflow Statement
B8: =B1 -> 2026 | C8: =C1 -> 2027 | D8: =D1 -> 2028 | E8: =E1 -> 2029 | F8: =F1 -> 2030 | G8: =G1 -> 2031 | H8: =H1 -> 2032 | I8: =I1 -> 2033 | ... X8: =X1 -> 2048
A9: ='Financials Yearly'!B88 -> Net Income | B9: ='Financials Yearly'!C88 -> -13468123 | C9: ='Financials Yearly'!D88 -> -16090608 | D9: ='Financials Yearly'!E88 -> 7219852.4 | E9: ='Financials Yearly'!F88 -> 16491830 | F9: ='Financials Yearly'!G88 -> 19586016 | G9: ='Financials Yearly'!H88 -> 21882079 | H9: ='Financials Yearly'!I88 -> 24522970 | ... X9: ='Financials Yearly'!Y88 -> 75741761
A10: ='Financials Yearly'!B89 -> Depreciation | B10: ='Financials Yearly'!C89 -> 0 | C10: ='Financials Yearly'!D89 -> 27292295 | D10: ='Financials Yearly'!E89 -> 36389726 | E10: ='Financials Yearly'!F89 -> 36389726 | F10: ='Financials Yearly'!G89 -> 36389726 | G10: ='Financials Yearly'!H89 -> 36389726 | H10: ='Financials Yearly'!I89 -> 36389726 | ... X10: ='Financials Yearly'!Y89 -> 1000000
A11: ='Financials Yearly'!B90 -> Amortization | B11: ='Financials Yearly'!C90 -> 0 | C11: ='Financials Yearly'!D90 -> 1834042.2 | D11: ='Financials Yearly'!E90 -> 203782.47 | E11: ='Financials Yearly'!F90 -> 203782.47 | F11: ='Financials Yearly'!G90 -> 203782.47 | G11: ='Financials Yearly'!H90 -> 203782.47 | H11: ='Financials Yearly'!I90 -> 203782.47 | ... X11: ='Financials Yearly'!Y90 -> 203782.47
A12: ='Financials Yearly'!B91 -> Net Cashflow from Operating Activities | B12: ='Financials Yearly'!C91 -> -13468123 | C12: ='Financials Yearly'!D91 -> 13035729 | D12: ='Financials Yearly'!E91 -> 43813361 | E12: ='Financials Yearly'!F91 -> 53085338 | F12: ='Financials Yearly'!G91 -> 56179524 | G12: ='Financials Yearly'!H91 -> 58475588 | H12: ='Financials Yearly'!I91 -> 61116479 | ... X12: ='Financials Yearly'!Y91 -> 76945544
A14: Revenue / Expense and Mortgage
B15: =B8 -> 2026 | C15: =C8 -> 2027 | D15: =D8 -> 2028 | E15: =E8 -> 2029 | F15: =F8 -> 2030 | G15: =G8 -> 2031 | H15: =H8 -> 2032 | I15: =I8 -> 2033 | ... X15: =X8 -> 2048
A16: =A2 -> Total Revenue | B16: =B2 -> 0 | C16: =C2 -> 42079158 | D16: =D2 -> 73261683 | E16: =E2 -> 79804722 | F16: =F2 -> 81225242 | G16: =G2 -> 82228620 | H16: =H2 -> 83477384 | ... X16: =X2 -> 1.072573e+08
A17: Expense and Mortgage | B17: =SUM(B3+B4+B5) -> 13468123 | C17: =SUM(C3+C4+C5) -> 37105262 | D17: =SUM(D3+D4+D5) -> 40875378 | E17: =SUM(E3+E4+E5) -> 38972502 | F17: =SUM(F3+F4+F5) -> 38184615 | G17: =SUM(G3+G4+G5) -> 37841742 | H17: =SUM(H3+H4+H5) -> 37468089 | I17: =SUM(I3+I4+I5) -> 37061343 | ... X17: =SUM(X3+X4+X5) -> 11376319
A18: Mortgage line 1.3 times | B18: =SUM(B17*1.3) -> 17508560 | C18: =SUM(C17*1.3) -> 48236841 | D18: =SUM(D17*1.3) -> 53137991 | E18: =SUM(E17*1.3) -> 50664253 | F18: =SUM(F17*1.3) -> 49640000 | G18: =SUM(G17*1.3) -> 49194265 | H18: =SUM(H17*1.3) -> 48708516 | I18: =SUM(I17*1.3) -> 48179745 | ... X18: =SUM(X17*1.3) -> 14789214
A20: Total Revenue and Expense | B20: =B1 -> 2026 | C20: =C1 -> 2027 | D20: =D1 -> 2028 | E20: =E1 -> 2029 | F20: =F1 -> 2030 | G20: =G1 -> 2031 | H20: =H1 -> 2032 | I20: =I1 -> 2033 | ... X20: =X1 -> 2048
A21: =A2 -> Total Revenue | B21: =B2 -> 0 | C21: =C2 -> 42079158 | D21: =D2 -> 73261683 | E21: =E2 -> 79804722 | F21: =F2 -> 81225242 | G21: =G2 -> 82228620 | H21: =H2 -> 83477384 | ... X21: =X2 -> 1.072573e+08
A22: Total Expense | B22: =SUM(B3:B5) -> 13468123 | C22: =SUM(C3:C5) -> 37105262 | D22: =SUM(D3:D5) -> 40875378 | E22: =SUM(E3:E5) -> 38972502 | F22: =SUM(F3:F5) -> 38184615 | G22: =SUM(G3:G5) -> 37841742 | H22: =SUM(H3:H5) -> 37468089 | I22: =SUM(I3:I5) -> 37061343 | ... X22: =SUM(X3:X5) -> 11376319
A23: Loan Ratio | B23: =SUM(B22 * 1.3) -> 17508560 | C23: =SUM(C22 * 1.3) -> 48236841 | D23: =SUM(D22 * 1.3) -> 53137991 | E23: =SUM(E22 * 1.3) -> 50664253 | F23: =SUM(F22 * 1.3) -> 49640000 | G23: =SUM(G22 * 1.3) -> 49194265 | H23: =SUM(H22 * 1.3) -> 48708516 | I23: =SUM(I22 * 1.3) -> 48179745 | ... X23: =SUM(X22 * 1.3) -> 14789214
A26: Revenue breakout | B26: =B20 -> 2026 | C26: =C20 -> 2027 | D26: =D20 -> 2028 | E26: =E20 -> 2029 | F26: =F20 -> 2030 | G26: =G20 -> 2031 | H26: =H20 -> 2032 | I26: =I20 -> 2033 | ... X26: =X20 -> 2048
A27: Core Revenue (Electrical and Fuel) | B27: =SUM('Financials Yearly'!C5+'Financials Yearly'!C16+'Financials Yearly'!C17+'Financials Yearly'!C18+'Financials Yearly'!C19+'Financials Yearly'!C20) -> 0 | C27: =SUM('Financials Yearly'!D5+'Financials Yearly'!D16+'Financials Yearly'!D17+'Financials Yearly'!D18+'Financials Yearly'!D19+'Financials Yearly'!D20) -> 0 | D27: =SUM('Financials Yearly'!E5+'Financials Yearly'!E16+'Financials Yearly'!E17+'Financials Yearly'!E18+'Financials Yearly'!E19+'Financials Yearly'!E20) -> 16398976 | E27: =SUM('Financials Yearly'!F5+'Financials Yearly'!F16+'Financials Yearly'!F17+'Financials Yearly'!F18+'Financials Yearly'!F19+'Financials Yearly'!F20) -> 21765914 | F27: =SUM('Financials Yearly'!G5+'Financials Yearly'!G16+'Financials Yearly'!G17+'Financials Yearly'!G18+'Financials Yearly'!G19+'Financials Yearly'!G20) -> 21825546 | G27: =SUM('Financials Yearly'!H5+'Financials Yearly'!H16+'Financials Yearly'!H17+'Financials Yearly'!H18+'Financials Yearly'!H19+'Financials Yearly'!H20) -> 21765914 | H27: =SUM('Financials Yearly'!I5+'Financials Yearly'!I16+'Financials Yearly'!I17+'Financials Yearly'!I18+'Financials Yearly'!I19+'Financials Yearly'!I20) -> 21765914 | I27: =SUM('Financials Yearly'!J5+'Financials Yearly'!J16+'Financials Yearly'!J17+'Financials Yearly'!J18+'Financials Yearly'!J19+'Financials Yearly'!J20) -> 21765914 | ... X27: =SUM('Financials Yearly'!Y5+'Financials Yearly'!Y16+'Financials Yearly'!Y17+'Financials Yearly'!Y18+'Financials Yearly'!Y19+'Financials Yearly'!Y20) -> 21765914
A28: Commodities (adjusted at 75% of value) | B28: =SUM('Financials Yearly'!C7+'Financials Yearly'!C8+'Financials Yearly'!C9+'Financials Yearly'!C10+'Financials Yearly'!C11+'Financials Yearly'!C12+'Financials Yearly'!C13) * 0.75 -> 0 | C28: =SUM('Financials Yearly'!D7+'Financials Yearly'!D8+'Financials Yearly'!D9+'Financials Yearly'!D10+'Financials Yearly'!D11+'Financials Yearly'!D12+'Financials Yearly'!D13) * 0.75 -> 21774744 | D28: =SUM('Financials Yearly'!E7+'Financials Yearly'!E8+'Financials Yearly'!E9+'Financials Yearly'!E10+'Financials Yearly'!E11+'Financials Yearly'!E12+'Financials Yearly'!E13) * 0.75 -> 29411946 | E28: =SUM('Financials Yearly'!F7+'Financials Yearly'!F8+'Financials Yearly'!F9+'Financials Yearly'!F10+'Financials Yearly'!F11+'Financials Yearly'!F12+'Financials Yearly'!F13) * 0.75 -> 30005607 | F28: =SUM('Financials Yearly'!G7+'Financials Yearly'!G8+'Financials Yearly'!G9+'Financials Yearly'!G10+'Financials Yearly'!G11+'Financials Yearly'!G12+'Financials Yearly'!G13) * 0.75 -> 30694486 | G28: =SUM('Financials Yearly'!H7+'Financials Yearly'!H8+'Financials Yearly'!H9+'Financials Yearly'!H10+'Financials Yearly'!H11+'Financials Yearly'!H12+'Financials Yearly'!H13) * 0.75 -> 31229120 | H28: =SUM('Financials Yearly'!I7+'Financials Yearly'!I8+'Financials Yearly'!I9+'Financials Yearly'!I10+'Financials Yearly'!I11+'Financials Yearly'!I12+'Financials Yearly'!I13) * 0.75 -> 31859459 | I28: =SUM('Financials Yearly'!J7+'Financials Yearly'!J8+'Financials Yearly'!J9+'Financials Yearly'!J10+'Financials Yearly'!J11+'Financials Yearly'!J12+'Financials Yearly'!J13) * 0.75 -> 32502522 | ... X28: =SUM('Financials Yearly'!Y7+'Financials Yearly'!Y8+'Financials Yearly'!Y9+'Financials Yearly'!Y10+'Financials Yearly'!Y11+'Financials Yearly'!Y12+'Financials Yearly'!Y13) * 0.75 -> 43862860
A30: =A27 -> Core Revenue (Electrical and Fuel) | B30: =SUM(B27:X27) -> 4.5177688e+08
A31: =A28 -> Commodities (adjusted at 75% of value) | B31: =SUM(B28:X28) -> 7.8166712e+08
A33: Core Revenue to Expense | B33: =B26 -> 2026 | C33: =C26 -> 2027 | D33: =D26 -> 2028 | E33: =E26 -> 2029 | F33: =F26 -> 2030 | G33: =G26 -> 2031 | H33: =H26 -> 2032 | I33: =I26 -> 2033 | ... X33: =X26 -> 2048
A34: =A27 -> Core Revenue (Electrical and Fuel) | B34: =B27 -> 0 | C34: =C27 -> 0 | D34: =D27 -> 16398976 | E34: =E27 -> 21765914 | F34: =F27 -> 21825546 | G34: =G27 -> 21765914 | H34: =H27 -> 21765914 | ... X34: =X27 -> 21765914
A35: =A22 -> Total Expense | B35: =B17 -> 13468123 | C35: =C17 -> 37105262 | D35: =D17 -> 40875378 | E35: =E17 -> 38972502 | F35: =F17 -> 38184615 | G35: =G17 -> 37841742 | H35: =H17 -> 37468089 | I35: =I17 -> 37061343 | ... X35: =X17 -> 11376319
A36: =A23 -> Loan Ratio | B36: =SUM(B35 * 1.3) -> 17508560 | C36: =SUM(C35 * 1.3) -> 48236841 | D36: =SUM(D35 * 1.3) -> 53137991 | E36: =SUM(E35 * 1.3) -> 50664253 | F36: =SUM(F35 * 1.3) -> 49640000 | G36: =SUM(G35 * 1.3) -> 49194265 | H36: =SUM(H35 * 1.3) -> 48708516 | I36: =SUM(I35 * 1.3) -> 48179745 | ... X36: =SUM(X35 * 1.3) -> 14789214
B38: =B33 -> 2026 | C38: =C33 -> 2027 | D38: =D33 -> 2028 | E38: =E33 -> 2029 | F38: =F33 -> 2030 | G38: =G33 -> 2031 | H38: =H33 -> 2032 | I38: =I33 -> 2033 | ... X38: =X33 -> 2048
A39: Revenue | B39: =B2 -> 0 | C39: =C2 -> 42079158 | D39: =D2 -> 73261683 | E39: =E2 -> 79804722 | F39: =F2 -> 81225242 | G39: =G2 -> 82228620 | H39: =H2 -> 83477384 | I39: =I2 -> 84751355 | ... X39: =X2 -> 1.072573e+08
A40: ='Financials Yearly'!B51 -> EBITDA | B40: ='Financials Yearly'!C51 -> -4213882 | C40: ='Financials Yearly'!D51 -> 27575573 | D40: ='Financials Yearly'!E51 -> 56659882 | E40: ='Financials Yearly'!F51 -> 64973638 | F40: ='Financials Yearly'!G51 -> 67182045 | G40: ='Financials Yearly'!H51 -> 68528296 | H40: ='Financials Yearly'!I51 -> 70150714 | ... X40: ='Financials Yearly'!Y51 -> 95880984
A42: These graphs are based on the full 25 year projections
A44: Revenue Stream Breakout | J44: =A45 -> Income Power | K44: =B45 -> 21765914
A45: ='Financials Yearly'!B5 -> Income Power | B45: ='Financials Yearly'!O5 -> 21765914 | J45: ='Financials Yearly'!B7 -> Activated Carbon Ash | K45: ='Financials Yearly'!F7 -> 16233629
A46: ='Financials Yearly'!B7 -> Activated Carbon Ash | B46: ='Financials Yearly'!O7 -> 19432271 | J46: =A52 -> Carbon Black | K46: =B52 -> 10340590
A47: ='Financials Yearly'!B8 -> Aluminum | B47: ='Financials Yearly'!O8 -> 4333307.1 | J47: =A53 -> Graphene | K47: =B53 -> 23266327
A48: ='Financials Yearly'!B9 -> Ferrous Metals | B48: ='Financials Yearly'!O9 -> 560594.76 | J48: Ferrous and non-ferrous metals | K48: =SUM('Financials Yearly'!F8:F10) -> 13775733
A49: ='Financials Yearly'!B10 -> Non-Ferrous Metals | B49: ='Financials Yearly'!O10 -> 11596174 | J49: Steel | K49: =SUM('Financials Yearly'!F11:F12) -> 1359633.7
A50: ='Financials Yearly'!B11 -> Steel from Tires | B50: ='Financials Yearly'!O11 -> 1627533.2
A51: ='Financials Yearly'!B12 -> Steel, OTR Tires | B51: ='Financials Yearly'!O12 -> 0
A52: ='Financials Yearly'!B13 -> Carbon Black | B52: ='Financials Yearly'!O13 -> 10340590
A53: ='Financials Yearly'!B14 -> Graphene | B53: ='Financials Yearly'!O14 -> 23266327
A54: ='Financials Yearly'!B15 -> Light Oil Sale | B54: ='Financials Yearly'!O15 -> 0
A55: ='Financials Yearly'!B16 -> Diesel | B55: ='Financials Yearly'!O16 -> 0
A56: ='Financials Yearly'!B17 -> JP | B56: ='Financials Yearly'!O17 -> 0
A57: ='Financials Yearly'!B18 -> Gas | B57: ='Financials Yearly'!O18 -> 0
A58: ='Financials Yearly'!B19 -> Lube oil | B58: ='Financials Yearly'!O19 -> 0
A59: ='Financials Yearly'!B20 -> Petroleum Coke | B59: ='Financials Yearly'!O20 -> 0
A60: ='Financials Yearly'!B6 -> RNG Sale price | B60: ='Financials Yearly'!O6 -> 0
A61: ='Financials Yearly'!B21 -> Total Commodity Revenue | B61: ='Financials Yearly'!O21 -> 92922709
S64: Revnue Composition
T65: 2024 | U65: =SUM(T65+1) -> 2025 | V65: =SUM(U65+1) -> 2026 | W65: =SUM(V65+1) -> 2027 | X65: =SUM(W65+1) -> 2028 | Y65: =SUM(X65+1) -> 2029 | Z65: =SUM(Y65+1) -> 2030 | AA65: =SUM(Z65+1) -> 2031 | AB65: =SUM(AA65+1) -> 2032 | AC65: =SUM(AB65+1) -> 2033
S66: Electricty | T66: ='Financials Yearly'!C5 -> 0 | U66: ='Financials Yearly'!D5 -> 0 | V66: ='Financials Yearly'!E5 -> 16398976 | W66: ='Financials Yearly'!F5 -> 21765914 | X66: ='Financials Yearly'!G5 -> 21825546 | Y66: ='Financials Yearly'!H5 -> 21765914 | Z66: ='Financials Yearly'!I5 -> 21765914 | AA66: ='Financials Yearly'!J5 -> 21765914 | ... AC66: ='Financials Yearly'!L5 -> 21765914
S67: Activated Carbon | T67: ='Financials Yearly'!C7 -> 0 | U67: ='Financials Yearly'!D7 -> 11780568 | V67: ='Financials Yearly'!E7 -> 15912447 | W67: ='Financials Yearly'!F7 -> 16233629 | X67: ='Financials Yearly'!G7 -> 16606326 | Y67: ='Financials Yearly'!H7 -> 16895573 | Z67: ='Financials Yearly'!I7 -> 17236600 | AA67: ='Financials Yearly'!J7 -> 17584509 | ... AC67: ='Financials Yearly'!L7 -> 18301537
S68: Carbon Black | T68: ='Financials Yearly'!C13 -> 0 | U68: ='Financials Yearly'!D13 -> 6268851.7 | V68: ='Financials Yearly'!E13 -> 8467568.3 | W68: ='Financials Yearly'!F13 -> 8638480.7 | X68: ='Financials Yearly'!G13 -> 8836805.9 | Y68: ='Financials Yearly'!H13 -> 8990724.4 | Z68: ='Financials Yearly'!I13 -> 9172196.4 | AA68: ='Financials Yearly'!J13 -> 9357331.2 | ... AC68: ='Financials Yearly'!L13 -> 9738886.9
S69: Graphene | T69: ='Financials Yearly'!C14 -> 0 | U69: ='Financials Yearly'!D14 -> 14104916 | V69: ='Financials Yearly'!E14 -> 19052029 | W69: ='Financials Yearly'!F14 -> 19436581 | X69: ='Financials Yearly'!G14 -> 19882813 | Y69: ='Financials Yearly'!H14 -> 20229130 | Z69: ='Financials Yearly'!I14 -> 20637442 | AA69: ='Financials Yearly'!J14 -> 21053995 | ... AC69: ='Financials Yearly'!L14 -> 21912496
S70: Ferrous | T70: ='Financials Yearly'!C9 -> 0 | U70: ='Financials Yearly'!D9 -> 339853.48 | V70: ='Financials Yearly'!E9 -> 459052.59 | W70: ='Financials Yearly'!F9 -> 468318.27 | X70: ='Financials Yearly'!G9 -> 479070.08 | Y70: ='Financials Yearly'!H9 -> 487414.47 | Z70: ='Financials Yearly'!I9 -> 497252.62 | AA70: ='Financials Yearly'!J9 -> 507289.34 | ... AC70: ='Financials Yearly'!L9 -> 527974.63
S71: Non-ferrous | T71: =SUM('Financials Yearly'!C10+'Financials Yearly'!C8) -> 0 | U71: =SUM('Financials Yearly'!D10+'Financials Yearly'!D8) -> 9657046.4 | V71: =SUM('Financials Yearly'!E10+'Financials Yearly'!E8) -> 13044127 | W71: =SUM('Financials Yearly'!F10+'Financials Yearly'!F8) -> 13307415 | X71: =SUM('Financials Yearly'!G10+'Financials Yearly'!G8) -> 13612931 | Y71: =SUM('Financials Yearly'!H10+'Financials Yearly'!H8) -> 13850039 | Z71: =SUM('Financials Yearly'!I10+'Financials Yearly'!I8) -> 14129594 | AA71: =SUM('Financials Yearly'!J10+'Financials Yearly'!J8) -> 14414790 | ... AC71: =SUM('Financials Yearly'!L10+'Financials Yearly'!L8) -> 15002569
S72: Tire Steel | T72: =SUM('Financials Yearly'!C11) -> 0 | U72: =SUM('Financials Yearly'!D11) -> 986671.41 | V72: =SUM('Financials Yearly'!E11) -> 1332733.3 | W72: =SUM('Financials Yearly'!F11) -> 1359633.7 | X72: =SUM('Financials Yearly'!G11) -> 1390848.6 | Y72: =SUM('Financials Yearly'!H11) -> 1415074.3 | Z72: =SUM('Financials Yearly'!I11) -> 1443636.6 | AA72: =SUM('Financials Yearly'!J11) -> 1472775.5 | ... AC72: =SUM('Financials Yearly'!L11) -> 1532829.6
S94: OpEX
T95: =T65 -> 2024 | U95: =U65 -> 2025 | V95: =V65 -> 2026 | W95: =W65 -> 2027 | X95: =X65 -> 2028 | Y95: =Y65 -> 2029 | Z95: =Z65 -> 2030 | AA95: =AA65 -> 2031 | ... AC95: =AC65 -> 2033
S96: Employee | T96: ='Financials Yearly'!C33 -> 601983.15 | U96: ='Financials Yearly'!D33 -> 3603546.1 | V96: ='Financials Yearly'!E33 -> 4846945.1 | W96: ='Financials Yearly'!F33 -> 4895637.3 | X96: ='Financials Yearly'!G33 -> 4944818.7 | Y96: ='Financials Yearly'!H33 -> 4994494.1 | Z96: ='Financials Yearly'!I33 -> 5044668.6 | AA96: ='Financials Yearly'!J33 -> 5095347.2 | ... AC96: ='Financials Yearly'!L33 -> 5198236.7
S97: Insurance | T97: ='Financials Yearly'!C37 -> 601983.15 | U97: ='Financials Yearly'!D37 -> 7511416.3 | V97: ='Financials Yearly'!E37 -> 7147871.2 | W97: ='Financials Yearly'!F37 -> 6758045.3 | X97: ='Financials Yearly'!G37 -> 6340039 | Y97: ='Financials Yearly'!H37 -> 5891814.9 | Z97: ='Financials Yearly'!I37 -> 5411188.6 | AA97: ='Financials Yearly'!J37 -> 4895817.9 | ... AC97: ='Financials Yearly'!L37 -> 3750614.5
S98: O&M | T98: ='Financials Yearly'!C34+'Financials Yearly'!C35+'Financials Yearly'!C36 -> 3009915.7 | U98: ='Financials Yearly'!D34+'Financials Yearly'!D35+'Financials Yearly'!D36 -> 2791307.1 | V98: ='Financials Yearly'!E34+'Financials Yearly'!E35+'Financials Yearly'!E36 -> 3787418.9 | W98: ='Financials Yearly'!F34+'Financials Yearly'!F35+'Financials Yearly'!F36 -> 2341292.7 | X98: ='Financials Yearly'!G34+'Financials Yearly'!G35+'Financials Yearly'!G36 -> 1905354.4 | Y98: ='Financials Yearly'!H34+'Financials Yearly'!H35+'Financials Yearly'!H36 -> 1943812.7 | Z98: ='Financials Yearly'!I34+'Financials Yearly'!I35+'Financials Yearly'!I36 -> 1983047.3 | AA98: ='Financials Yearly'!J34+'Financials Yearly'!J35+'Financials Yearly'!J36 -> 2023073.9 | ... AC98: ='Financials Yearly'!L34+'Financials Yearly'!L35+'Financials Yearly'!L36 -> 2105567
S99: Other | T99: =SUM('Financials Yearly'!C48+'Financials Yearly'!C47+'Financials Yearly'!C46+'Financials Yearly'!C45+'Financials Yearly'!C44+'Financials Yearly'!C43+'Financials Yearly'!C42+'Financials Yearly'!C40+'Financials Yearly'!C39+'Financials Yearly'!C38) -> 0 | U99: =SUM('Financials Yearly'!D48+'Financials Yearly'!D47+'Financials Yearly'!D46+'Financials Yearly'!D45+'Financials Yearly'!D44+'Financials Yearly'!D43+'Financials Yearly'!D42+'Financials Yearly'!D40+'Financials Yearly'!D39+'Financials Yearly'!D38) -> 597315.54 | V99: =SUM('Financials Yearly'!E48+'Financials Yearly'!E47+'Financials Yearly'!E46+'Financials Yearly'!E45+'Financials Yearly'!E44+'Financials Yearly'!E43+'Financials Yearly'!E42+'Financials Yearly'!E40+'Financials Yearly'!E39+'Financials Yearly'!E38) -> 819565.89 | W99: =SUM('Financials Yearly'!F48+'Financials Yearly'!F47+'Financials Yearly'!F46+'Financials Yearly'!F45+'Financials Yearly'!F44+'Financials Yearly'!F43+'Financials Yearly'!F42+'Financials Yearly'!F40+'Financials Yearly'!F39+'Financials Yearly'!F38) -> 836108.3 | X99: =SUM('Financials Yearly'!G48+'Financials Yearly'!G47+'Financials Yearly'!G46+'Financials Yearly'!G45+'Financials Yearly'!G44+'Financials Yearly'!G43+'Financials Yearly'!G42+'Financials Yearly'!G40+'Financials Yearly'!G39+'Financials Yearly'!G38) -> 852984.61 | Y99: =SUM('Financials Yearly'!H48+'Financials Yearly'!H47+'Financials Yearly'!H46+'Financials Yearly'!H45+'Financials Yearly'!H44+'Financials Yearly'!H43+'Financials Yearly'!H42+'Financials Yearly'!H40+'Financials Yearly'!H39+'Financials Yearly'!H38) -> 870201.55 | Z99: =SUM('Financials Yearly'!I48+'Financials Yearly'!I47+'Financials Yearly'!I46+'Financials Yearly'!I45+'Financials Yearly'!I44+'Financials Yearly'!I43+'Financials Yearly'!I42+'Financials Yearly'!I40+'Financials Yearly'!I39+'Financials Yearly'!I38) -> 887766.01 | AA99: =SUM('Financials Yearly'!J48+'Financials Yearly'!J47+'Financials Yearly'!J46+'Financials Yearly'!J45+'Financials Yearly'!J44+'Financials Yearly'!J43+'Financials Yearly'!J42+'Financials Yearly'!J40+'Financials Yearly'!J39+'Financials Yearly'!J38) -> 905685 | ... AC99: =SUM('Financials Yearly'!L48+'Financials Yearly'!L47+'Financials Yearly'!L46+'Financials Yearly'!L45+'Financials Yearly'!L44+'Financials Yearly'!L43+'Financials Yearly'!L42+'Financials Yearly'!L40+'Financials Yearly'!L39+'Financials Yearly'!L38) -> 942615.32
G107: Revenue vs EBITDA
H109: Byproducts Volume per Year in MT
H110: =Inputs!B27 -> Activated Carbon Ash | I110: =SUM(Inputs!D27*365) -> 24653.791
H111: =Inputs!B28 -> Aluminum | I111: =SUM(Inputs!D28*365) -> 1806.75
H112: =Inputs!B29 -> Ferrous Metals | I112: =SUM(Inputs!D29*365) -> 2489.3
H113: =Inputs!B30 -> Non-Ferrous Metals | I113: =SUM(Inputs!D30*365) -> 1204.5
H114: Steel | I114: =SUM(Inputs!D31*365) -> 5475
H115: =Inputs!B33 -> Carbon Black | I115: =SUM(Inputs!D33*365) -> 9183.4
H116: =Inputs!B34 -> Graphene | I116: =SUM(Inputs!D34*365) -> 2066.265
H117: Total | I117: =SUM(I110:I116) -> 46879.006
T120: =T95 -> 2024 | U120: =U95 -> 2025 | V120: =V95 -> 2026 | W120: =W95 -> 2027 | X120: =X95 -> 2028 | Y120: =Y95 -> 2029 | Z120: =Z95 -> 2030 | AA120: =AA95 -> 2031 | ... AC120: =AC95 -> 2033
S121: ='Financials Yearly'!B91 -> Net Cashflow from Operating Activities | T121: ='Financials Yearly'!C91 -> -13468123 | U121: ='Financials Yearly'!D91 -> 13035729 | V121: ='Financials Yearly'!E91 -> 43813361 | W121: ='Financials Yearly'!F91 -> 53085338 | X121: ='Financials Yearly'!G91 -> 56179524 | Y121: ='Financials Yearly'!H91 -> 58475588 | Z121: ='Financials Yearly'!I91 -> 61116479 | ... AC121: ='Financials Yearly'!L91 -> 68663172
A126: Expenses | B126: ='Financials Yearly'!C2 -> 2026 | C126: ='Financials Yearly'!D2 -> 2027 | D126: ='Financials Yearly'!E2 -> 2028 | E126: ='Financials Yearly'!F2 -> 2029 | F126: ='Financials Yearly'!G2 -> 2030 | G126: ='Financials Yearly'!H2 -> 2031 | H126: ='Financials Yearly'!I2 -> 2032 | I126: ='Financials Yearly'!J2 -> 2033 | ... X126: ='Financials Yearly'!Y2 -> 2048
A127: ='Financials Yearly'!B33 -> Employee Cost | B127: ='Financials Yearly'!C33 -> 601983.15 | C127: ='Financials Yearly'!D33 -> 3603546.1 | D127: ='Financials Yearly'!E33 -> 4846945.1 | E127: ='Financials Yearly'!F33 -> 4895637.3 | F127: ='Financials Yearly'!G33 -> 4944818.7 | G127: ='Financials Yearly'!H33 -> 4994494.1 | H127: ='Financials Yearly'!I33 -> 5044668.6 | ... X127: ='Financials Yearly'!Y33 -> 5919579.1
A128: ='Financials Yearly'!B34 -> Turbine LTMA Cost 5 year term | B128: ='Financials Yearly'!C34 -> 1203966.3 | C128: ='Financials Yearly'!D34 -> 1630842.1 | D128: ='Financials Yearly'!E34 -> 2212827.9 | E128: ='Financials Yearly'!F34 -> 560150.9 | F128: ='Financials Yearly'!G34 -> 0 | G128: ='Financials Yearly'!H34 -> 0 | H128: ='Financials Yearly'!I34 -> 0 | ... X128: ='Financials Yearly'!Y34 -> 0
A129: ='Financials Yearly'!B35 -> Pyrolysis LTMA Cost yrs. 3+ | B129: ='Financials Yearly'!C35 -> 1203966.3 | C129: ='Financials Yearly'!D35 -> 0 | D129: ='Financials Yearly'!E35 -> 0 | E129: ='Financials Yearly'!F35 -> 174768.73 | F129: ='Financials Yearly'!G35 -> 266557.69 | G129: ='Financials Yearly'!H35 -> 271937.99 | H129: ='Financials Yearly'!I35 -> 277426.88 | ... X129: ='Financials Yearly'!Y35 -> 381950.5
A130: ='Financials Yearly'!B36 -> Total O&M | B130: ='Financials Yearly'!C36 -> 601983.15 | C130: ='Financials Yearly'!D36 -> 1160465 | D130: ='Financials Yearly'!E36 -> 1574591 | E130: ='Financials Yearly'!F36 -> 1606373.1 | F130: ='Financials Yearly'!G36 -> 1638796.7 | G130: ='Financials Yearly'!H36 -> 1671874.7 | H130: ='Financials Yearly'!I36 -> 1705620.5 | ... X130: ='Financials Yearly'!Y36 -> 2348231.7
A131: ='Financials Yearly'!B37 -> All insurance for the plant and risks | B131: ='Financials Yearly'!C37 -> 601983.15 | C131: ='Financials Yearly'!D37 -> 7511416.3 | D131: ='Financials Yearly'!E37 -> 7147871.2 | E131: ='Financials Yearly'!F37 -> 6758045.3 | F131: ='Financials Yearly'!G37 -> 6340039 | G131: ='Financials Yearly'!H37 -> 5891814.9 | H131: ='Financials Yearly'!I37 -> 5411188.6 | ... X131: ='Financials Yearly'!Y37 -> 1504315.7
A132: ='Financials Yearly'!B38 -> Land Rental | B132: ='Financials Yearly'!C38 -> 0 | C132: ='Financials Yearly'!D38 -> 75501.949 | D132: ='Financials Yearly'!E38 -> 102445.74 | E132: ='Financials Yearly'!F38 -> 104513.54 | F132: ='Financials Yearly'!G38 -> 106623.08 | G132: ='Financials Yearly'!H38 -> 108775.19 | H132: ='Financials Yearly'!I38 -> 110970.75 | ... X132: ='Financials Yearly'!Y38 -> 152780.2
A133: ='Financials Yearly'!B39 -> IT outsourced | B133: ='Financials Yearly'!C39 -> 0 | C133: ='Financials Yearly'!D39 -> 53701.504 | D133: ='Financials Yearly'!E39 -> 81956.589 | E133: ='Financials Yearly'!F39 -> 83610.83 | F133: ='Financials Yearly'!G39 -> 85298.461 | G133: ='Financials Yearly'!H39 -> 87020.155 | H133: ='Financials Yearly'!I39 -> 88776.601 | ... X133: ='Financials Yearly'!Y39 -> 122224.16
A134: ='Financials Yearly'!B40 -> Utilities | B134: ='Financials Yearly'!C40 -> 0 | C134: ='Financials Yearly'!D40 -> 151003.9 | D134: ='Financials Yearly'!E40 -> 204891.47 | E134: ='Financials Yearly'!F40 -> 209027.08 | F134: ='Financials Yearly'!G40 -> 213246.15 | G134: ='Financials Yearly'!H40 -> 217550.39 | H134: ='Financials Yearly'!I40 -> 221941.5 | ... X134: ='Financials Yearly'!Y40 -> 305560.4
A135: ='Financials Yearly'!B41 -> OVD Fee for exporting | B135: ='Financials Yearly'!C41 -> 0 | C135: ='Financials Yearly'!D41 -> 0 | D135: ='Financials Yearly'!E41 -> 0 | E135: ='Financials Yearly'!F41 -> 0 | F135: ='Financials Yearly'!G41 -> 0 | G135: ='Financials Yearly'!H41 -> 0 | H135: ='Financials Yearly'!I41 -> 0 | ... X135: ='Financials Yearly'!Y41 -> 0
A136: ='Financials Yearly'!B42 -> Electricity | B136: ='Financials Yearly'!C42 -> 0 | C136: ='Financials Yearly'!D42 -> 0 | D136: ='Financials Yearly'!E42 -> 0 | E136: ='Financials Yearly'!F42 -> 0 | F136: ='Financials Yearly'!G42 -> 0 | G136: ='Financials Yearly'!H42 -> 0 | H136: ='Financials Yearly'!I42 -> 0 | ... X136: ='Financials Yearly'!Y42 -> 0
A137: ='Financials Yearly'!B43 -> Accounting & Auditing | B137: ='Financials Yearly'!C43 -> 0 | C137: ='Financials Yearly'!D43 -> 64176.657 | D137: ='Financials Yearly'!E43 -> 87078.876 | E137: ='Financials Yearly'!F43 -> 88836.507 | F137: ='Financials Yearly'!G43 -> 90629.615 | G137: ='Financials Yearly'!H43 -> 92458.915 | H137: ='Financials Yearly'!I43 -> 94325.139 | ... X137: ='Financials Yearly'!Y43 -> 129863.17
A138: ='Financials Yearly'!B44 -> Office Supplies | B138: ='Financials Yearly'!C44 -> 0 | C138: ='Financials Yearly'!D44 -> 56626.462 | D138: ='Financials Yearly'!E44 -> 76834.302 | E138: ='Financials Yearly'!F44 -> 78385.153 | F138: ='Financials Yearly'!G44 -> 79967.307 | G138: ='Financials Yearly'!H44 -> 81581.396 | H138: ='Financials Yearly'!I44 -> 83228.064 | ... X138: ='Financials Yearly'!Y44 -> 114585.15
... A143: ='Financials Yearly'!B49 -> Total Expenses | B143: ='Financials Yearly'!C49 -> 4213882 | C143: ='Financials Yearly'!D49 -> 14503585 | D143: ='Financials Yearly'!E49 -> 16601801 | E143: ='Financials Yearly'!F49 -> 14831084 | F143: ='Financials Yearly'!G49 -> 14043197 | G143: ='Financials Yearly'!H49 -> 13700323 | H143: ='Financials Yearly'!I49 -> 13326671 | ... X143: ='Financials Yearly'!Y49 -> 11376319
M145: =A127 -> Employee Cost | N145: =E127 -> 4895637.3
M146: =A128 -> Turbine LTMA Cost 5 year term | N146: =E128 -> 560150.9
M147: =A129 -> Pyrolysis LTMA Cost yrs. 3+ | N147: =E129 -> 174768.73
M148: =A130 -> Total O&M | N148: =E130 -> 1606373.1
M149: =A131 -> All insurance for the plant and risks | N149: =E131 -> 6758045.3
M150: =A132 -> Land Rental | N150: =E132 -> 104513.54
M151: =A133 -> IT outsourced | N151: =E133 -> 83610.83
M152: =A134 -> Utilities | N152: =E134 -> 209027.08
...

Sheet Summary
B2: Sources | D2: $USD | E2: % | G2: Uses | I2: $USD | J2: % | M2: ='Data Sources'!C1 -> 2026 | N2: =M2+1 -> 2027 | O2: =N2+1 -> 2028 | P2: =O2+1 -> 2029 | Q2: =P2+1 -> 2030 | R2: =Q2+1 -> 2031 | S2: =R2+1 -> 2032 | T2: =S2+1 -> 2033 | U2: =T2+1 -> 2034 | ... AI2: =AH2+1 -> 2048
B3: Equity | D3: =D8-SUM(D4:D5) -> 64955662 | E3: =D3/$D$8 -> 0.23774314 | G3: Capital Expenditures | I3: =CapEx!$D$113 -> 2.5472808e+08 | J3: =I3/$I$7 -> 0.93232606 | L3: Revenue | M3: =SUMIF(Financials!$C$6:$JR$6,Summary!M$2,Financials!$C$37:$JR$37) -> 0 | N3: =SUMIF(Financials!$C$6:$JR$6,Summary!N$2,Financials!$C$37:$JR$37) -> 42079158 | O3: =SUMIF(Financials!$C$6:$JR$6,Summary!O$2,Financials!$C$37:$JR$37) -> 73261683 | P3: =SUMIF(Financials!$C$6:$JR$6,Summary!P$2,Financials!$C$37:$JR$37) -> 79804722 | Q3: =SUMIF(Financials!$C$6:$JR$6,Summary!Q$2,Financials!$C$37:$JR$37) -> 81225242 | R3: =SUMIF(Financials!$C$6:$JR$6,Summary!R$2,Financials!$C$37:$JR$37) -> 82228620 | S3: =SUMIF(Financials!$C$6:$JR$6,Summary!S$2,Financials!$C$37:$JR$37) -> 83477384 | T3: =SUMIF(Financials!$C$6:$JR$6,Summary!T$2,Financials!$C$37:$JR$37) -> 84751355 | ... AI3: =SUMIF(Financials!$C$6:$JR$6,Summary!AI$2,Financials!$C$37:$JR$37) -> 1.072573e+08
B4: DSRA | D4: =$I$6 -> 13395165 | E4: =D4/$D$8 -> 0.049027421 | G4: CREC Engineering Oversight | H4: 0.01 | I4: =H4*$I$3 -> 2547280.8 | J4: =I4/$I$7 -> 0.0093232606 | L4: Expenses | M4: =SUMIF(Financials!$C$6:$JR$6,Summary!M$2,Financials!$C$56:$JR$56) -> 7223797.8 | N4: =SUMIF(Financials!$C$6:$JR$6,Summary!N$2,Financials!$C$56:$JR$56) -> 14503585 | O4: =SUMIF(Financials!$C$6:$JR$6,Summary!O$2,Financials!$C$56:$JR$56) -> 16601801 | P4: =SUMIF(Financials!$C$6:$JR$6,Summary!P$2,Financials!$C$56:$JR$56) -> 14831084 | Q4: =SUMIF(Financials!$C$6:$JR$6,Summary!Q$2,Financials!$C$56:$JR$56) -> 14043197 | R4: =SUMIF(Financials!$C$6:$JR$6,Summary!R$2,Financials!$C$56:$JR$56) -> 13700323 | S4: =SUMIF(Financials!$C$6:$JR$6,Summary!S$2,Financials!$C$56:$JR$56) -> 13326671 | T4: =SUMIF(Financials!$C$6:$JR$6,Summary!T$2,Financials!$C$56:$JR$56) -> 12919924 | ... AI4: =SUMIF(Financials!$C$6:$JR$6,Summary!AI$2,Financials!$C$56:$JR$56) -> 11376319
B5: Debt | C5: 0.75 | D5: =SUM($I$3:$I$5)*$C$5 -> 1.9486698e+08 | E5: =D5/$D$8 -> 0.71322943 | G5: Transaction Expenses | H5: 0.01 | I5: =H5*SUM($I$3) -> 2547280.8 | J5: =I5/$I$7 -> 0.0093232606 | L5: EBITDA | M5: =SUMIF(Financials!$C$6:$JR$6,Summary!M$2,Financials!$C$58:$JR$58) -> -7223797.8 | N5: =SUMIF(Financials!$C$6:$JR$6,Summary!N$2,Financials!$C$58:$JR$58) -> 27575573 | O5: =SUMIF(Financials!$C$6:$JR$6,Summary!O$2,Financials!$C$58:$JR$58) -> 56659882 | P5: =SUMIF(Financials!$C$6:$JR$6,Summary!P$2,Financials!$C$58:$JR$58) -> 64973638 | Q5: =SUMIF(Financials!$C$6:$JR$6,Summary!Q$2,Financials!$C$58:$JR$58) -> 67182045 | R5: =SUMIF(Financials!$C$6:$JR$6,Summary!R$2,Financials!$C$58:$JR$58) -> 68528296 | S5: =SUMIF(Financials!$C$6:$JR$6,Summary!S$2,Financials!$C$58:$JR$58) -> 70150714 | T5: =SUMIF(Financials!$C$6:$JR$6,Summary!T$2,Financials!$C$58:$JR$58) -> 71831431 | ... AI5: =SUMIF(Financials!$C$6:$JR$6,Summary!AI$2,Financials!$C$58:$JR$58) -> 95880984
G6: {='Capital Contributions'!A6:B6} -> Construction Loan | H6: 0 | I6: =SUM('Capital Contributions'!$E$10:$JT$10) -> 13395165 | J6: =I6/$I$7 -> 0.049027421
G7: Total | I7: =SUM(I3:I6) -> 2.7321781e+08 | J7: =SUM(J3:J6) -> 1 | L7: Interest Expense | M7: =-SUMIF(Financials!$C$6:$JR$6,Summary!M$2,Financials!$C$70:$JR$70) -> -9254241.3 | N7: =-SUMIF(Financials!$C$6:$JR$6,Summary!N$2,Financials!$C$70:$JR$70) -> -14185154 | O7: =-SUMIF(Financials!$C$6:$JR$6,Summary!O$2,Financials!$C$70:$JR$70) -> -12714362 | P7: =-SUMIF(Financials!$C$6:$JR$6,Summary!P$2,Financials!$C$70:$JR$70) -> -11888300 | Q7: =-SUMIF(Financials!$C$6:$JR$6,Summary!Q$2,Financials!$C$70:$JR$70) -> -11002521 | R7: =-SUMIF(Financials!$C$6:$JR$6,Summary!R$2,Financials!$C$70:$JR$70) -> -10052709 | S7: =-SUMIF(Financials!$C$6:$JR$6,Summary!S$2,Financials!$C$70:$JR$70) -> -9034234.5 | T7: =-SUMIF(Financials!$C$6:$JR$6,Summary!T$2,Financials!$C$70:$JR$70) -> -7942135 | ... AI7: =-SUMIF(Financials!$C$6:$JR$6,Summary!AI$2,Financials!$C$70:$JR$70) -> 0
B8: Total | D8: =I7 -> 2.7321781e+08 | E8: =SUM(E3:E7) -> 1 | L8: Depreciation & Amortization | M8: =-SUMIF(Financials!$C$6:$JR$6,Summary!M$2,Financials!$C$66:$JR$66) -> 0 | N8: =-SUMIF(Financials!$C$6:$JR$6,Summary!N$2,Financials!$C$66:$JR$66) -> -29126337 | O8: =-SUMIF(Financials!$C$6:$JR$6,Summary!O$2,Financials!$C$66:$JR$66) -> -36593509 | P8: =-SUMIF(Financials!$C$6:$JR$6,Summary!P$2,Financials!$C$66:$JR$66) -> -36593509 | Q8: =-SUMIF(Financials!$C$6:$JR$6,Summary!Q$2,Financials!$C$66:$JR$66) -> -36593509 | R8: =-SUMIF(Financials!$C$6:$JR$6,Summary!R$2,Financials!$C$66:$JR$66) -> -36593509 | S8: =-SUMIF(Financials!$C$6:$JR$6,Summary!S$2,Financials!$C$66:$JR$66) -> -36593509 | T8: =-SUMIF(Financials!$C$6:$JR$6,Summary!T$2,Financials!$C$66:$JR$66) -> -36736366 | ... AI8: =-SUMIF(Financials!$C$6:$JR$6,Summary!AI$2,Financials!$C$66:$JR$66) -> -1203782.5
L9: Taxes | M9: =-SUMIF(Financials!$C$6:$JR$6,Summary!M$2,Financials!$C$89:$JR$89) -> 0 | N9: =-SUMIF(Financials!$C$6:$JR$6,Summary!N$2,Financials!$C$89:$JR$89) -> 0 | O9: =-SUMIF(Financials!$C$6:$JR$6,Summary!O$2,Financials!$C$89:$JR$89) -> 0 | P9: =-SUMIF(Financials!$C$6:$JR$6,Summary!P$2,Financials!$C$89:$JR$89) -> 0 | Q9: =-SUMIF(Financials!$C$6:$JR$6,Summary!Q$2,Financials!$C$89:$JR$89) -> 0 | R9: =-SUMIF(Financials!$C$6:$JR$6,Summary!R$2,Financials!$C$89:$JR$89) -> 0 | S9: =-SUMIF(Financials!$C$6:$JR$6,Summary!S$2,Financials!$C$89:$JR$89) -> 0 | T9: =-SUMIF(Financials!$C$6:$JR$6,Summary!T$2,Financials!$C$89:$JR$89) -> 0 | ... AI9: =-SUMIF(Financials!$C$6:$JR$6,Summary!AI$2,Financials!$C$89:$JR$89) -> -18935440
G10: Total Equity Contributed | H10: =-SUM('NPV IRR'!C5:JR5) -> 78350826 | L10: Net Income | M10: =SUM(M5:M9) -> -16478039 | N10: =SUM(N5:N9) -> -15735918 | O10: =SUM(O5:O9) -> 7352010.6 | P10: =SUM(P5:P9) -> 16491830 | Q10: =SUM(Q5:Q9) -> 19586016 | R10: =SUM(R5:R9) -> 21882079 | S10: =SUM(S5:S9) -> 24522970 | T10: =SUM(T5:T9) -> 27152930 | ... AI10: =SUM(AI5:AI9) -> 75741761
B11: Initial Construction Interest-Only Loan | G11: Total Project Cash Flow | H11: =SUM('NPV IRR'!C6:JR6) -> 1.1293807e+09
B12: Loan-to-Value | C12: ='Capital Contributions'!B7 -> 0.71322943 | G12: Total Project Equity IRR % | H12: ='NPV IRR'!$B$10 -> 0.39179596 | M12: =M2 -> 2026 | N12: =M12+1 -> 2027 | O12: =N12+1 -> 2028 | P12: =O12+1 -> 2029 | Q12: =P12+1 -> 2030 | R12: =Q12+1 -> 2031 | S12: =R12+1 -> 2032 | T12: =S12+1 -> 2033 | U12: =T12+1 -> 2034 | ... AI12: =AH12+1 -> 2048
B13: Amount | C13: ='Capital Contributions'!B8 -> 1.9486698e+08 | G13: Net Present Value | H13: ='NPV IRR'!$B$22 -> 2.3306971e+08 | L13: Equity Contributions | M13: =SUMIF('NPV IRR'!$C$3:$JR$3,Summary!M$12,'NPV IRR'!$C$5:$JR$5) -> -74209903 | N13: =SUMIF('NPV IRR'!$C$3:$JR$3,Summary!N$12,'NPV IRR'!$C$5:$JR$5) -> -4140923.4 | O13: =SUMIF('NPV IRR'!$C$3:$JR$3,Summary!O$12,'NPV IRR'!$C$5:$JR$5) -> 0 | P13: =SUMIF('NPV IRR'!$C$3:$JR$3,Summary!P$12,'NPV IRR'!$C$5:$JR$5) -> 0 | Q13: =SUMIF('NPV IRR'!$C$3:$JR$3,Summary!Q$12,'NPV IRR'!$C$5:$JR$5) -> 0 | R13: =SUMIF('NPV IRR'!$C$3:$JR$3,Summary!R$12,'NPV IRR'!$C$5:$JR$5) -> 0 | S13: =SUMIF('NPV IRR'!$C$3:$JR$3,Summary!S$12,'NPV IRR'!$C$5:$JR$5) -> 0 | T13: =SUMIF('NPV IRR'!$C$3:$JR$3,Summary!T$12,'NPV IRR'!$C$5:$JR$5) -> 0 | ... AI13: =SUMIF('NPV IRR'!$C$3:$JR$3,Summary!AI$12,'NPV IRR'!$C$5:$JR$5) -> 0
B14: Interest Rate | C14: ='Capital Contributions'!B9 -> 0.085 | G14: Total Project IRR % | H14: ='NPV IRR'!$B$36 -> 0.205466 | L14: Debt Amortization Payment | M14: =SUMIF(Financials!$C$6:$JR$6,Summary!M$12,Financials!$C$101:$JR$101) -> 0 | N14: =SUMIF(Financials!$C$6:$JR$6,Summary!N$12,Financials!$C$101:$JR$101) -> 8061833.3 | O14: =SUMIF(Financials!$C$6:$JR$6,Summary!O$12,Financials!$C$101:$JR$101) -> 11427056 | P14: =SUMIF(Financials!$C$6:$JR$6,Summary!P$12,Financials!$C$101:$JR$101) -> 12253119 | Q14: =SUMIF(Financials!$C$6:$JR$6,Summary!Q$12,Financials!$C$101:$JR$101) -> 13138898 | R14: =SUMIF(Financials!$C$6:$JR$6,Summary!R$12,Financials!$C$101:$JR$101) -> 14088710 | S14: =SUMIF(Financials!$C$6:$JR$6,Summary!S$12,Financials!$C$101:$JR$101) -> 15107184 | T14: =SUMIF(Financials!$C$6:$JR$6,Summary!T$12,Financials!$C$101:$JR$101) -> 16199284 | ... AI14: =SUMIF(Financials!$C$6:$JR$6,Summary!AI$12,Financials!$C$101:$JR$101) -> 0
B15: Term | C15: ='Capital Contributions'!B10 -> COD | L15: Capital Expenditures | M15: =SUMIF(Financials!$C$6:$JR$6,Summary!M2,Financials!$C$100:$JR$100) -> 0 | N15: =SUMIF(Financials!$C$6:$JR$6,Summary!N2,Financials!$C$100:$JR$100) -> 0 | O15: =SUMIF(Financials!$C$6:$JR$6,Summary!O2,Financials!$C$100:$JR$100) -> 0 | P15: =SUMIF(Financials!$C$6:$JR$6,Summary!P2,Financials!$C$100:$JR$100) -> 0 | Q15: =SUMIF(Financials!$C$6:$JR$6,Summary!Q2,Financials!$C$100:$JR$100) -> 0 | R15: =SUMIF(Financials!$C$6:$JR$6,Summary!R2,Financials!$C$100:$JR$100) -> 0 | S15: =SUMIF(Financials!$C$6:$JR$6,Summary!S2,Financials!$C$100:$JR$100) -> 0 | T15: =SUMIF(Financials!$C$6:$JR$6,Summary!T2,Financials!$C$100:$JR$100) -> 1000000 | ... AI15: =SUMIF(Financials!$C$6:$JR$6,Summary!AI2,Financials!$C$100:$JR$100) -> 1000000
B16: Interest-Only | C16: ='Capital Contributions'!B11 -> Yes | L16: Project Cash Flow | M16: =SUMIF('NPV IRR'!$C$3:$JR$3,Summary!M$12,'NPV IRR'!$C$6:$JR$6) -> 0 | N16: =SUMIF('NPV IRR'!$C$3:$JR$3,Summary!N$12,'NPV IRR'!$C$6:$JR$6) -> 10779995 | O16: =SUMIF('NPV IRR'!$C$3:$JR$3,Summary!O$12,'NPV IRR'!$C$6:$JR$6) -> 30892540 | P16: =SUMIF('NPV IRR'!$C$3:$JR$3,Summary!P$12,'NPV IRR'!$C$6:$JR$6) -> 38790608 | Q16: =SUMIF('NPV IRR'!$C$3:$JR$3,Summary!Q$12,'NPV IRR'!$C$6:$JR$6) -> 40888595 | R16: =SUMIF('NPV IRR'!$C$3:$JR$3,Summary!R$12,'NPV IRR'!$C$6:$JR$6) -> 42167534 | S16: =SUMIF('NPV IRR'!$C$3:$JR$3,Summary!S$12,'NPV IRR'!$C$6:$JR$6) -> 43708830 | T16: =SUMIF('NPV IRR'!$C$3:$JR$3,Summary!T$12,'NPV IRR'!$C$6:$JR$6) -> 44355512 | ... AI16: =SUMIF('NPV IRR'!$C$3:$JR$3,Summary!AI$12,'NPV IRR'!$C$6:$JR$6) -> 75945544
B18: Refinance - Term Loan
B19: Month | C19: ='Capital Contributions'!B14 -> 16
B20: Loan-to-Value | C20: ='Capital Contributions'!B15 -> 0.35
B21: Amount | C21: ='Capital Contributions'!B16 -> 95626234
B22: Interest Rate | C22: ='Capital Contributions'!B17 -> 0.07 | L22: 20 Year Cash Flow $mm
B23: Term | C23: ='Capital Contributions'!B18 -> 15 | L23: EBITDA | M23: =SUM($M$5:$AI$5) -> 1.6952971e+09
B24: Final Month | C24: ='Capital Contributions'!B19 -> 196 | L24: Project Cash Flow | M24: =SUM($M$16:$AI$16) -> 1.1293807e+09
B26: Refinance - High Yield Loan | L26: ($USD in millions) | M26: =M2+2 -> 2028 | N26: =M26+1 -> 2029 | O26: =N26+1 -> 2030 | P26: =O26+1 -> 2031 | Q26: =P26+1 -> 2032 | R26: =Q26+1 -> 2033 | S26: =R26+1 -> 2034 | T26: =S26+1 -> 2035 | U26: =T26+1 -> 2036 | ... AG26: =AF26+1 -> 2048
B27: Month | C27: ='Capital Contributions'!B22 -> 16 | L27: Revenue
B28: Loan-to-Value | C28: ='Capital Contributions'!B23 -> 0.36322943 | L28: Power Sales | M28: =SUMIF(Financials!$C$6:$JR$6,Summary!M$26,Financials!$C$12:$JR$12) -> 16398976 | N28: =SUMIF(Financials!$C$6:$JR$6,Summary!N$26,Financials!$C$12:$JR$12) -> 21765914 | O28: =SUMIF(Financials!$C$6:$JR$6,Summary!O$26,Financials!$C$12:$JR$12) -> 21825546 | P28: =SUMIF(Financials!$C$6:$JR$6,Summary!P$26,Financials!$C$12:$JR$12) -> 21765914 | Q28: =SUMIF(Financials!$C$6:$JR$6,Summary!Q$26,Financials!$C$12:$JR$12) -> 21765914 | R28: =SUMIF(Financials!$C$6:$JR$6,Summary!R$26,Financials!$C$12:$JR$12) -> 21765914 | S28: =SUMIF(Financials!$C$6:$JR$6,Summary!S$26,Financials!$C$12:$JR$12) -> 21765914 | T28: =SUMIF(Financials!$C$6:$JR$6,Summary!T$26,Financials!$C$12:$JR$12) -> 21765914 | ... AG28: =SUMIF(Financials!$C$6:$JR$6,Summary!AG$26,Financials!$C$12:$JR$12) -> 21765914
B29: Amount | C29: ='Capital Contributions'!B24 -> 99240751 | L29: Commodity Sales | M29: =SUMIF(Financials!$C$6:$JR$6,Summary!M$26,Financials!$C$28:$JR$28)-M28 -> 58267957 | N29: =SUMIF(Financials!$C$6:$JR$6,Summary!N$26,Financials!$C$28:$JR$28)-N28 -> 59444058 | O29: =SUMIF(Financials!$C$6:$JR$6,Summary!O$26,Financials!$C$28:$JR$28)-O28 -> 60808795 | P29: =SUMIF(Financials!$C$6:$JR$6,Summary!P$26,Financials!$C$28:$JR$28)-P28 -> 61867956 | Q29: =SUMIF(Financials!$C$6:$JR$6,Summary!Q$26,Financials!$C$28:$JR$28)-Q28 -> 63116721 | R29: =SUMIF(Financials!$C$6:$JR$6,Summary!R$26,Financials!$C$28:$JR$28)-R28 -> 64390691 | S29: =SUMIF(Financials!$C$6:$JR$6,Summary!S$26,Financials!$C$28:$JR$28)-S28 -> 65690376 | T29: =SUMIF(Financials!$C$6:$JR$6,Summary!T$26,Financials!$C$28:$JR$28)-T28 -> 67016294 | ... AG29: =SUMIF(Financials!$C$6:$JR$6,Summary!AG$26,Financials!$C$28:$JR$28)-AG28 -> 86896639
B30: Interest Rate | C30: ='Capital Contributions'!B25 -> 0.07 | L30: Byproduct Sales | M30: =SUMIF(Financials!$C$6:$JR$6,Summary!M$26,Financials!$C$35:$JR$35) -> -1405250 | N30: =SUMIF(Financials!$C$6:$JR$6,Summary!N$26,Financials!$C$35:$JR$35) -> -1405250 | O30: =SUMIF(Financials!$C$6:$JR$6,Summary!O$26,Financials!$C$35:$JR$35) -> -1409100 | P30: =SUMIF(Financials!$C$6:$JR$6,Summary!P$26,Financials!$C$35:$JR$35) -> -1405250 | Q30: =SUMIF(Financials!$C$6:$JR$6,Summary!Q$26,Financials!$C$35:$JR$35) -> -1405250 | R30: =SUMIF(Financials!$C$6:$JR$6,Summary!R$26,Financials!$C$35:$JR$35) -> -1405250 | S30: =SUMIF(Financials!$C$6:$JR$6,Summary!S$26,Financials!$C$35:$JR$35) -> -1405250 | T30: =SUMIF(Financials!$C$6:$JR$6,Summary!T$26,Financials!$C$35:$JR$35) -> -1405250 | ... AG30: =SUMIF(Financials!$C$6:$JR$6,Summary!AG$26,Financials!$C$35:$JR$35) -> -1405250
B31: Term | C31: ='Capital Contributions'!B26 -> 10 | L31: Total Revenue | M31: =SUM(M28:M30) -> 73261683 | N31: =SUM(N28:N30) -> 79804722 | O31: =SUM(O28:O30) -> 81225242 | P31: =SUM(P28:P30) -> 82228620 | Q31: =SUM(Q28:Q30) -> 83477384 | R31: =SUM(R28:R30) -> 84751355 | S31: =SUM(S28:S30) -> 86051039 | T31: =SUM(T28:T30) -> 87376957 | ... AG31: =SUM(AG28:AG30) -> 1.072573e+08
B32: Final Month | C32: ='Capital Contributions'!B27 -> 136
L33: Total Expenses | M33: =SUMIF(Financials!$C$6:$JR$6,Summary!M$26,Financials!$C$56:$JR$56) -> 16601801 | N33: =SUMIF(Financials!$C$6:$JR$6,Summary!N$26,Financials!$C$56:$JR$56) -> 14831084 | O33: =SUMIF(Financials!$C$6:$JR$6,Summary!O$26,Financials!$C$56:$JR$56) -> 14043197 | P33: =SUMIF(Financials!$C$6:$JR$6,Summary!P$26,Financials!$C$56:$JR$56) -> 13700323 | Q33: =SUMIF(Financials!$C$6:$JR$6,Summary!Q$26,Financials!$C$56:$JR$56) -> 13326671 | R33: =SUMIF(Financials!$C$6:$JR$6,Summary!R$26,Financials!$C$56:$JR$56) -> 12919924 | S33: =SUMIF(Financials!$C$6:$JR$6,Summary!S$26,Financials!$C$56:$JR$56) -> 12477600 | T33: =SUMIF(Financials!$C$6:$JR$6,Summary!T$26,Financials!$C$56:$JR$56) -> 11997034 | ... AG33: =SUMIF(Financials!$C$6:$JR$6,Summary!AG$26,Financials!$C$56:$JR$56) -> 11376319
L34: % of Revenue | M34: =M33/M$31 -> 0.22660961 | N34: =N33/N$31 -> 0.18584218 | O34: =O33/O$31 -> 0.17289203 | P34: =P33/P$31 -> 0.16661259 | Q34: =Q33/Q$31 -> 0.15964408 | R34: =R33/R$31 -> 0.15244504 | S34: =S33/S$31 -> 0.14500231 | T34: =T33/T$31 -> 0.13730203 | ... AG34: =AG33/AG$31 -> 0.10606568
L36: EBITDA | M36: =HLOOKUP(M$26,$M$2:$AI$16,4,0) -> 56659882 | N36: =HLOOKUP(N$26,$M$2:$AI$16,4,0) -> 64973638 | O36: =HLOOKUP(O$26,$M$2:$AI$16,4,0) -> 67182045 | P36: =HLOOKUP(P$26,$M$2:$AI$16,4,0) -> 68528296 | Q36: =HLOOKUP(Q$26,$M$2:$AI$16,4,0) -> 70150714 | R36: =HLOOKUP(R$26,$M$2:$AI$16,4,0) -> 71831431 | S36: =HLOOKUP(S$26,$M$2:$AI$16,4,0) -> 73573440 | T36: =HLOOKUP(T$26,$M$2:$AI$16,4,0) -> 75379924 | ... AG36: =HLOOKUP(AG$26,$M$2:$AI$16,4,0) -> 95880984
L37: % Margin | M37: =M36/M31 -> 0.77339039 | N37: =N36/N31 -> 0.81415782 | O37: =O36/O31 -> 0.82710797 | P37: =P36/P31 -> 0.83338741 | Q37: =Q36/Q31 -> 0.84035592 | R37: =R36/R31 -> 0.84755496 | S37: =S36/S31 -> 0.85499769 | T37: =T36/T31 -> 0.86269797 | ... AG37: =AG36/AG31 -> 0.89393432
B39: Revenue Graphs | L39: Project Cash Flow | M39: =HLOOKUP(M$26,$M$2:$AI$16,15,0) -> 30892540 | N39: =HLOOKUP(N$26,$M$2:$AI$16,15,0) -> 38790608 | O39: =HLOOKUP(O$26,$M$2:$AI$16,15,0) -> 40888595 | P39: =HLOOKUP(P$26,$M$2:$AI$16,15,0) -> 42167534 | Q39: =HLOOKUP(Q$26,$M$2:$AI$16,15,0) -> 43708830 | R39: =HLOOKUP(R$26,$M$2:$AI$16,15,0) -> 44355512 | S39: =HLOOKUP(S$26,$M$2:$AI$16,15,0) -> 46010420 | T39: =HLOOKUP(T$26,$M$2:$AI$16,15,0) -> 46585282 | ... AG39: =HLOOKUP(AG$26,$M$2:$AI$16,15,0) -> 75945544
L40: % Margin | M40: =M39/M31 -> 0.42167391 | N40: =N39/N31 -> 0.48606909 | O40: =O39/O31 -> 0.50339764 | P40: =P39/P31 -> 0.51280848 | Q40: =Q39/Q31 -> 0.52360086 | R40: =R39/R31 -> 0.5233605 | S40: =S39/S31 -> 0.53468756 | T40: =T39/T31 -> 0.53315294 | ... AG40: =AG39/AG31 -> 0.70806875
B41: =Financials!B12 -> Income Power | C41: =Financials!AG12 -> 1848611.9
B42: =Financials!B13 -> RNG Sale price | C42: =Financials!AG13 -> 0
B43: =Financials!B14 -> Activated Carbon Ash | C43: =Financials!AG14 -> 1352512.9 | L43: Net Income | M43: =HLOOKUP(M$26,$M$2:$AI$10,9,0) -> 7352010.6 | N43: =HLOOKUP(N$26,$M$2:$AI$10,9,0) -> 16491830 | O43: =HLOOKUP(O$26,$M$2:$AI$10,9,0) -> 19586016 | P43: =HLOOKUP(P$26,$M$2:$AI$10,9,0) -> 21882079 | Q43: =HLOOKUP(Q$26,$M$2:$AI$10,9,0) -> 24522970 | R43: =HLOOKUP(R$26,$M$2:$AI$10,9,0) -> 27152930 | S43: =HLOOKUP(S$26,$M$2:$AI$10,9,0) -> 57215424 | T43: =HLOOKUP(T$26,$M$2:$AI$10,9,0) -> 68030818 | ... AG43: =HLOOKUP(AG$26,$M$2:$AI$10,9,0) -> 75741761
B44: =Financials!B15 -> Aluminum | C44: =Financials!AG15 -> 301604.16 | L44: % Margin | M44: =M43/M31 -> 0.10035274 | N44: =N43/N31 -> 0.2066523 | O44: =O43/O31 -> 0.24113213 | P44: =P43/P31 -> 0.26611269 | Q44: =Q43/Q31 -> 0.29376783 | R44: =R43/R31 -> 0.32038343 | S44: =S43/S31 -> 0.66490102 | T44: =T43/T31 -> 0.77858992 | ... AG44: =AG43/AG31 -> 0.70616881
B45: =Financials!B16 -> Ferrous Metals | C45: =Financials!AG16 -> 39018.17
B46: =Financials!B17 -> Non-Ferrous Metals | C46: =Financials!AG17 -> 807109.73
B47: =Financials!B18 -> Steel from Tires | C47: =Financials!AG18 -> 113278.56
B48: =Financials!B19 -> Steel, OTR Tires | C48: =Financials!AG19 -> 0
B49: =Financials!B20 -> Carbon Black | C49: =Financials!AG20 -> 719719.33
B50: =Financials!B22 -> Light Oil Sale | C50: =Financials!AG22 -> 0
B51: =Financials!B23 -> Diesel | C51: =Financials!AG23 -> 0
B52: =Financials!B24 -> JP | C52: =Financials!AG24 -> 0
B53: =Financials!B25 -> Gas | C53: =Financials!AG25 -> 0
B54: =Financials!B26 -> Lube oil | C54: =Financials!AG26 -> 0
B55: =Financials!B27 -> Petroleum Coke | C55: =Financials!AG27 -> 0
B56: =Financials!B28 -> Total Commodity Revenue | C56: =Financials!AG28 -> 6801223.2
B60: =SUM(C41+C51+C52+C53+C54+C55) / C56 -> 0.27180579
B74: Income / Expense
B75: =Financials!B37 -> Total Revenue | C75: =Financials!AH37 -> 6690127.5
B76: =Financials!B56 -> Total Expenses | C76: =Financials!AH56 -> 1384940.6
B77: =Financials!B58 -> EBITDA | C77: =Financials!AH58 -> 5305187
B78: Debt Repayment | C78: =SUM('Capital Contributions'!AJ31) -> 2011784.9

Sheet Data Sources
A1: Year Financial Model starts | C1: 2026
A2: Month | C2: 1
A3: Day | C3: 30
A4: Month to get online | C4: 16 | E4: How long from start of construction to operations
A5: Metric Ton | C5: 2204.62
A6: Days in a year | C6: 365
A7: Technical Risk insurance | C7: 0.01 | E7: Technical risk policy guarantying the loan
A8: MIGA Debt insurance | C8: 0.022 | E8: Political risk policy guarantying the loan
A9: MIGA Equity insurance | C9: 0.02 | E9: Political risk policy guarantying the loan
A10: Days in year MSW received | B10: days | C10: 365 | E10: OVD delivers every day even on holidays
A11: Days in year tires received | B11: days | C11: 365 | E11: OVD delivers every day even on holidays
A12: 1 KiloCalorie = | B12: BTU | C12: 3.96567
A13: Stage 1 processing hours per day | B13: hours | C13: 19 | E13: The remaining hours are for maintenance on the stage 1 equipment
A14: Days for onsite storage | B14: days | C14: 7 | E14: for feedstock and byproducts
A15: Altitude of the REP | B15: feet | C15: 55 | E15: Altitudes of the Renewable Energy Park
A16: Percent Loss to conditioning gas | C16: 0.1
A17: Conditioning cost per MMBTU in USD | C17: 5
A18: Percent Aluminum in non ferrous metals | B18: % | C18: 0.6 | E18: Average in USA waste stream
A19: Desired Mwe goal | B19: Mwe | C19: 44 | E19: How much electricity do you desire
A20: Maintenance fund contribution | C20: 0.05 | E20: set aside for plant maintenance and equipment repair
A21: Max maintenance fund value | C21: 45000000 | E21: Cap on fund limit
A22: Confidence Factor | C22: 0.9 | E22: Take the market price and reduce the value by this for market fluctuations. Ex 100% but we assume 85% in case of price changes
A23: Turbine Delivery Estimate | C23: 28 | E23: Months to deliver turbine after order placed
A24: Graphene Switch | C24: Y | E24: Y says we will produce graphene
A25: Graphene reduction in Carbon Black | C25: 0.8 | E25: If we produce graphene we lose some of our carbon black yield. This value reflects what we will retain
A26: RNG Switch | C26: N | E26: N says we will produce electric Y says we will produce RNG
A27: Tires Only Switch | C27: N | E27: N says we will process both tires and MSW and Y means only tires and no MSW is processed for the entire facility
A29: Item | B29: Units | C29: Our price for confidence | D29: Wholesale Price | E29: Source
A30: Electrical price | B30: $/MWh | C30: =IF(C26="N",D30,(0)) -> 66.55 | D30: 66.55 | E30: No power production would be at this plant
A31: Power Production Year 4 - 25 | B31: MWh | C31: ='Power Production'!E30 -> 37.335738 | E31: Based on Power Production Worksheet. Parasitic load will fluctuate so assumed the highest parasitic load value
A32: Power Production Year 1 - 3 | B32: MWh | C32: =SUM(C31-10) -> 27.335738 | E32: Bitcoin HW power usage reduces output by 10 MWh
A33: Activated Carbon Ash | B33: $/MT | C33: =SUM(D33 * $C$22) -> 630 | D33: 700 | E33: https://www.engr.psu.edu/ce/courses/ce584/concrete/library/materials/Altmaterials/Class%20C%20Fly%20Ash.htm activated carbon pricing is over $1,100 a MT https://www.procurementresource.com/resource-center/activated-carbon-price-trends
A34: Carbon Black | B34: $/MT | C34: =SUM(D34 * $C$22) -> 900 | D34: 1000 | E34: https://bohanchem.en.made-in-china.com/product/tqOEBzJPJbYL/China-Carbon-Black-N339-for-Rubber-Industry.html
A35: Graphene | B35: $/MT | C35: =SUM(D35 * $C$22) -> 9000 | D35: 10000 | E35: https://www.alibaba.com/product-detail/High-Quality-Graphene-Powder-Nanoscale-Graphene_1600768680095.html?spm=a2700.7735675.0.0.4a7d0voQ0voQof&s=p
A36: Aluminum | B36: $/MT | C36: =SUM(D36 * $C$22) -> 1917 | D36: 2130 | E36: https://www.barchart.com/futures/european/major-commodities Took lowest price over 52 week range
A37: Ferrous Metals | B37: $/MT | C37: =SUM(D37 * $C$22) -> 180 | D37: 200 | E37: https://www.lme.com/Metals/Ferrous/Steel-Scrap#tabIndex=0; Current contract is at $200 MT
A38: Non-Ferrous Metals | B38: $/MT | C38: =SUM(D38 * $C$22) -> 7695 | D38: 8550 | E38: https://www.lme.com/Metals/Non-ferrous#tabIndex=0 (copper, aluminium, zinc, Nickel, lead
A39: Steel from Tires | B39: $/MT | C39: =SUM(D39 * $C$22) -> 237.6 | D39: 264 | E39: https://www.barchart.com/futures/european/major-commodities Took lowest price over 52 week range
A40: Steel, OTR Tires | B40: $/MT | C40: =SUM(D40 * $C$22) -> 270 | D40: 300 | E40: https://www.lme.com/Metals/Ferrous/Steel-Scrap#tabIndex=0
A41: MSW tipping fees | B41: $/MT | C41: -7 | D41: 70 | E41: Estimated tip fee received is $70 MT with 20% reduction
A42: Tire tipping fees | B42: $/MT | C42: 0 | D42: 22 | E42: Estimated tip fee received with 20% reduction
A43: Renewable Energy Credits | B43: $/MWh | C43: 0 | D43: 0 | E43: REC are given to EDD per the PPA agreement
A44: Carbon Credits | B44: $/ST | C44: 0 | D44: 0 | E44: Carbon Credits are given to EDD per the PPA agreement
A45: Light Oil Sale | B45: $/barrel | C45: 0 | D45: 70 | E45: oil price per barrel https://oilprice.com/ Mexican basket
A46: Diesel | B46: $/gallon | C46: 0 | E46: https://www.indexmundi.com/commodities/?commodity=diesel Price used is 45% normal market price
A47: JP | B47: $/gallon | C47: 0 | E47: https://www.iata.org/en/publications/economics/fuel-monitor Price used is 45% normal market price
A48: Gas | B48: $/gallon | C48: 0 | E48: https://www.indexmundi.com/commodities/?commodity=rbob-gasoline Price used in 60% of normal market price
A49: Lube oil | B49: $/gallon | C49: =SUM(D49/42) -> 0 | D49: 0 | E49: https://pubs.lubesngreases.com/lubereport-americas/u-s-base-oil-price-report-54/ price per barrel has dropped off considerably
A50: Petroleum Coke | B50: $/gallon | C50: 0 | E50: https://www.eia.gov/electricity/monthly/epm_table_grapher.php?t=epmt_4_12_a down 25% for normal price
A51: RNG Sale price | B51: $/MMBTU | C51: =IF(C26="N",0,(D51*C22)) -> 0 | D51: 8 | E51: Based on Latvia open source document
A52: VOLUME Calculations | C52: Reduced Value for confidence factor | D52: Baseline Values
A53: MSW Received per day | B53: MT / day | C53: 550 | E53: Waste stream delivery which includes the MRFs.
A54: Gross Tires Received | B54: MT / day | C54: 100 | E54: Tires sourced in Djibouti and other countries
A55: Ferrous material | B55: % | C55: 0.031 | E55: Average in waste stream
A56: Non-Ferrous Metals | B56: % | C56: 0.015 | E56: Average in waste stream
A57: #3 Plastics | B57: % | C57: 0.0005 | E57: Average in waste stream
A58: Final Moisture Content | B58: % | C58: 0.15 | E58: Percent moisture needed in the RDF Pellets
A59: =A33 -> Activated Carbon Ash | B59: MT/day | C59: ='Calc Summary'!B15 -> 67.544634 | E59: Values are calculated based on Mass Balance model. Percent of trash makeup was pulled from the Larimer County two season study, DOE waste stream study, three personal inspections on the Djibouti landfill and the Japanese study of Djibouti trash stream.
A60: =A36 -> Aluminum | B60: MT/day | C60: =SUM('Calc Summary'!B18 * C18) -> 4.95
A61: =A37 -> Ferrous Metals | B61: MT/day | C61: =SUM('Calc Summary'!B17 * (1-C18)) -> 6.82
A62: =A38 -> Non-Ferrous Metals | B62: MT/day | C62: =SUM('Calc Summary'!B18 * (100% - C18)) -> 3.3
A63: =A34 -> Carbon Black | B63: MT/day | C63: =IF(C24 ="N",D63,(D63*C25)) -> 25.16 | D63: ='Calc Summary'!B16 -> 31.45
A64: =A35 -> Graphene | B64: MT/day | C64: =SUM(D63-C63) * C22 -> 5.661 | E64: percent of graphene produced from the carbon black less some loss in production
A65: Oil Production | B65: % oil | C65: 0.25 | D65: 0.25 | E65: ARTI pyrolysis units Phase A test results at our temperature yields 20%. Example Calculation is 110 metric tons of tires in 15% of that is steel so 110*.15= 16.5 metric tons steel leaving 93.5 for tire fuel. 93.5 * .2 makes 18.7 metric tons of oil. The material has a density of 52.27 lbs. per cubic foot so now 18.7metric tons * 2204/52.27 = 788.50 cubic feet of oil which has is 7.48 gals in a cubic foot. So 788.5*7.48=5,897.97 gals/day.
B66: Gallons | C66: =SUM((((C54- (C54* 15%)) * C65) * (C5/52.27)) * 7.48) -> 6704.1199
A67: =A46 -> Diesel | B67: % of oil | C67: 0.2 | E67: Based on Phase A testing
A68: =A47 -> JP | B68: % of oil | C68: 0.2
A69: =A48 -> Gas | B69: % of oil | C69: 0.2
A70: =A49 -> Lube oil | B70: % of oil | C70: 0.2
A71: =A50 -> Petroleum Coke | B71: % of oil | C71: 0.2
A72: Liter conversion factor | C72: 3.78541 | E72: # of liters in a gallon
A73: Liters in a Fluid barrel | C73: 119.24047 | E73: 42 gallons in a barrel
A74: Steel in a tire | B74: % | C74: 0.15 | E74: The range is 10% to 20% so we use 15%. http://www.europeanrecycle.com/it/steelwire/steel-tire-wire/
A75: RNG Production | B75: MMBTU | C75: ='Stage 3 Gas Opt'!B7 -> 7539.0971 | E75: MMBTU per day
A76: Average Weight of a tire | B76: lbs | C76: 22
A79: Plant Operational Cost
C80: Yearly Cost
A81: Turbine LTMA Cost 5 year term | C81: 2160000 | E81: No turbines would be at this factory
A82: Pyrolysis LTMA Cost yrs. 3+ | C82: 250000 | E82: Support from the owners
A83: Total O&M | C83: =SUM(D84:D90) -> 1537000 | E83: Total of the below item estimates
D84: 1200000 | E84: Stage 1 maintenance for MSW and tire equipment and pelletizer maintenance with knife sharpening being the highest cost. Dryer maintenance is cost is $12,000 a year based on quote from ventilex. Captured in the overall stage 1 estimate already.
D85: 0 | E85: Cost per Year to condition the gas
D86: 170000 | E86: Stage 2 maintenance on the pyrolysis units to include replacing sulfur cleanup materials etc.
D87: 0 | E87: Stage 3 turbine Maintenance which includes the oil changes. Quoted by Solar Turbines covered under 5 year LTMA
E88: Stage 3 emission skid Maintenance which includes the ammonia cleanups
D89: 82000 | E89: Stage 4 mobile equipment repair and propane gas for the forklifts and crane support
D90: 85000 | E90: Stage 5 grounds maintenance expenses and supplies
A91: All insurance for the plant and risks | C91: =Insurance!E12 -> 7511416.3 | E91: Summation of Techincal and Political Risks and also Keyman, fire, liability etc.
A92: RNG Gas conditioning | C92: 19088.49 | E92: Cost per day to condition the gas based on MMBTU value
A93: IT outsourced | C93: 80000 | E93: Cost of internet plus cost of storage in the cloud etc.
A94: Utilities | C94: 200000 | E94: Will be on sewer, water bill an natural gas
A95: Electricity | C95: =SUM('Power Production'!D28*'Data Sources'!D95) *365 -> 0 | D95: 0 | E95: Quote from BHE per MWH hour Economic Development rate
A96: OVD Fee for exporting | C96: 0 | E96: DJB Law requires OVD to approve all sjhipments of metals we have signed contract at 30% for right to ship out of the country.
A97: Accounting & Auditing | C97: 85000 | E97: Accounting support both in country and in the USA from Plante Moran
A98: Office Supplies | C98: 75000 | E98: General office supplies of printer ink, paper, computer upgrades etc.
A99: Gas Transmission Costs | C99: 0 | E99: There is no transmission costs
A100: Permit Renewals | C100: 75000 | E100: Renewal of operating permits and business licenses
A101: Property Taxes | C101: 85000 | E101: Property taxes for the county
A102: Miscellaneous | C102: 100000 | E102: General expense catchall account. Estimate is based on assumptions from other facilities
A103: Land Rental | C103: 100000 | E103: We rent the land

Sheet Inputs
P1: Aluminum ($/ST)
B2: Byproduct prices | C2: Unit | D2: $ | F2: Costs | G2: Annual Costs ($) | H2: Monthly Costs ($) | J2: Escalation | K2: Annual | L2: Monthly | O2: =Summary!$H$12 -> 0.39179596 | P2: 750 | Q2: 760 | R2: 770 | S2: 780 | T2: 790 | U2: 800 | V2: 810 | W2: 820 | X2: 830 | Y2: 840 | Z2: 850
B3: ='Data Sources'!A33 -> Activated Carbon Ash | C3: $/MT | D3: ='Data Sources'!C33 -> 630 | F3: I-ERP | J3: Inflation | K3: 0.02 | L3: =K3/12 -> 0.0016666667 | N3: ST / day | O3: 2.5 | P3: 0.36696042 | Q3: 0.36704172 | R3: 0.36712303 | S3: 0.36720433 | T3: 0.36728563 | U3: 0.36736694 | V3: 0.36744824 | W3: 0.36752955 | X3: 0.36761087 | Y3: 0.36769218 | Z3: 0.36777349
B4: ='Data Sources'!A36 -> Aluminum | C4: $/MT | D4: ='Data Sources'!C36 -> 1917 | F4: =Financials!B40 -> Employee Cost | G4: ='Emp Labor Cost'!Z117 -> 4788734.6 | H4: =G4/12 -> 399061.21 | J4: PPA or RNG | K4: 0 | L4: =K4/12 -> 0 | O4: 2.75 | P4: 0.3675702 | Q4: 0.36765965 | R4: 0.36774909 | S4: 0.36783854 | T4: 0.36792799 | U4: 0.36801744 | V4: 0.36810688 | W4: 0.36819634 | X4: 0.36828579 | Y4: 0.36837525 | Z4: 0.3684647
B5: ='Data Sources'!A37 -> Ferrous Metals | C5: $/MT | D5: ='Data Sources'!C37 -> 180 | F5: =Financials!B41 -> Turbine LTMA Cost 5 year term | G5: ='Data Sources'!C81 -> 2160000 | H5: =G5/12 -> 180000 | J5: Tip Fee MSW | K5: 0 | L5: =K5/12 -> 0 | O5: 3 | P5: 0.36818008 | Q5: 0.36827766 | R5: 0.36837525 | S5: 0.36847283 | T5: 0.36857043 | U5: 0.36866801 | V5: 0.36876561 | W5: 0.36886321 | X5: 0.3689608 | Y5: 0.36905841 | Z5: 0.36915601
B6: ='Data Sources'!A38 -> Non-Ferrous Metals | C6: $/MT | D6: ='Data Sources'!C38 -> 7695 | F6: =Financials!B42 -> Pyrolysis LTMA Cost yrs. 3+ | G6: ='Data Sources'!C82 -> 250000 | H6: =G6/12 -> 20833.333 | J6: Tip Fee Tire | K6: 0 | L6: =K6/12 -> 0 | O6: 3.25 | P6: 0.36879001 | Q6: 0.36889574 | R6: 0.36900148 | S6: 0.3691072 | T6: 0.36921294 | U6: 0.36931868 | V6: 0.36942669 | W6: 0.36953244 | X6: 0.36963817 | Y6: 0.36974393 | Z6: 0.36984966
B7: ='Data Sources'!A39 -> Steel from Tires | C7: $/MT | D7: ='Data Sources'!C39 -> 237.6 | F7: =Financials!B43 -> Total O&M | G7: ='Data Sources'!C83 -> 1537000 | H7: =G7/12 -> 128083.33 | J7: Sugar Beet Pulp Tipping Fee | K7: 0 | L7: =K7/12 -> 0 | O7: 3.37 | P7: 0.36908281 | Q7: 0.36919245 | R7: 0.36930209 | S7: 0.369414 | T7: 0.36952365 | U7: 0.3696333 | V7: 0.36974295 | W7: 0.3698526 | X7: 0.36996225 | Y7: 0.37007191 | Z7: 0.37018157
B8: ='Data Sources'!A40 -> Steel, OTR Tires | C8: $/MT | D8: ='Data Sources'!C40 -> 270 | F8: =Financials!B44 -> All insurance for the plant and risks | G8: ='Data Sources'!C91 -> 7511416.3 | H8: =G8/12 -> 625951.36 | J8: Cargill Grass Tip Fee | K8: 0 | L8: =K8/12 -> 0 | O8: 3.5 | P8: 0.36940228 | Q8: 0.36951616 | R8: 0.36963004 | S8: 0.36974393 | T8: 0.36985781 | U8: 0.36997169 | V8: 0.37008558 | W8: 0.37019946 | X8: 0.37031335 | Y8: 0.37042726 | Z8: 0.37054115
B9: ='Data Sources'!A34 -> Carbon Black | C9: $/MT | D9: ='Data Sources'!C34 -> 900 | F9: =Financials!B46 -> IT outsourced | G9: ='Data Sources'!C93 -> 80000 | H9: =G9/12 -> 6666.6667 | J9: Commodity price | K9: 0.02 | L9: =K9/12 -> 0.0016666667 | O9: 3.75 | P9: 0.37001236 | Q9: 0.37013438 | R9: 0.37025641 | S9: 0.37037844 | T9: 0.37050048 | U9: 0.37062251 | V9: 0.37074454 | W9: 0.37086659 | X9: 0.37098863 | Y9: 0.37111067 | Z9: 0.37123273
B10: ='Data Sources'!A35 -> Graphene | C10: $/MT | D10: ='Data Sources'!C35 -> 9000 | F10: =Financials!B47 -> Utilities | G10: ='Data Sources'!C94 -> 200000 | H10: =G10/12 -> 16666.667 | J10: OPEX | K10: 0.02 | L10: =K10/12 -> 0.0016666667 | O10: 4 | P10: 0.37062251 | Q10: 0.37075269 | R10: 0.37088286 | S10: 0.37101304 | T10: 0.37114323 | U10: 0.3712734 | V10: 0.3714036 | W10: 0.37153379 | X10: 0.37166399 | Y10: 0.37179419 | Z10: 0.37192439
B11: ='Data Sources'!A41 -> MSW tipping fees | C11: $/MT | D11: ='Data Sources'!C41 -> -7 | F11: =Financials!B49 -> Electricity | G11: ='Data Sources'!C95 -> 0 | H11: =G11/12 -> 0 | J11: Tax benefit | K11: 0.02 | L11: =K11/12 -> 0.0016666667
B12: ='Data Sources'!A42 -> Tire tipping fees | C12: $/MT | D12: ='Data Sources'!C42 -> 0 | F12: =Financials!B50 -> Accounting & Auditing | G12: ='Data Sources'!C97 -> 85000 | H12: =G12/12 -> 7083.3333 | J12: Property Tax | K12: 0 | L12: =K12/12 -> 0 | P12: Ferrous Metals ($/ST)
B13: ='Data Sources'!A43 -> Renewable Energy Credits | C13: $/MWh | D13: ='Data Sources'!C43 -> 0 | F13: =Financials!B51 -> Office Supplies | G13: ='Data Sources'!C98 -> 75000 | H13: =G13/12 -> 6250 | J13: Testing Fraction | K13: 1 | L13: =K13 -> 1 | O13: =Summary!$H$12 -> 0.39179596 | P13: 105 | Q13: 110 | R13: 115 | S13: 120 | T13: 125 | U13: 135.17 | V13: =U13+5 -> 140.17 | W13: =V13+5 -> 145.17 | X13: =W13+5 -> 150.17 | Y13: =X13+5 -> 155.17 | Z13: =Y13+5 -> 160.17
B14: ='Data Sources'!A44 -> Carbon Credits | C14: $/ST | D14: ='Data Sources'!C44 -> 0 | F14: =Financials!B52 -> Gas Transmission Costs | G14: ='Data Sources'!C99 -> 0 | H14: =G14/12 -> 0 | J14: Employee Labor Escalation | K14: 0.01 | L14: =K14/12 -> 0.00083333333 | N14: ST / day | O14: 8.5 | P14: 0.39069952 | Q14: 0.39083828 | R14: 0.39097704 | S14: 0.39111809 | T14: 0.39125686 | U14: 0.39153913 | V14: 0.3916779 | W14: 0.39181668 | X14: 0.39195547 | Y14: 0.39209425 | Z14: 0.39223303
B15: ='Data Sources'!A45 -> Light Oil Sale | C15: ='Data Sources'!B45 -> $/barrel | D15: ='Data Sources'!C45 -> 0 | F15: =Financials!B53 -> Permit Renewals | G15: ='Data Sources'!C100 -> 75000 | H15: =G15/12 -> 6250 | O15: 8.75 | P15: 0.39078522 | Q15: 0.39092807 | R15: 0.3910732 | S15: 0.39121605 | T15: 0.39135889 | U15: 0.39164947 | V15: 0.39179233 | W15: 0.39193519 | X15: 0.39207806 | Y15: 0.39222092 | Z15: 0.39236379
B16: ='Data Sources'!A46 -> Diesel | C16: $/Liter | D16: =SUM('Data Sources'!C46/'Data Sources'!$C$72) -> 0 | F16: =Financials!B54 -> Property Taxes | G16: ='Data Sources'!C101 -> 85000 | H16: =G16/12 -> 7083.3333 | O16: 9 | P16: 0.39087093 | Q16: 0.39102014 | R16: 0.39116707 | S16: 0.391314 | T16: 0.39146094 | U16: 0.39175981 | V16: 0.39190676 | W16: 0.39205371 | X16: 0.39220065 | Y16: 0.3923476 | Z16: 0.39249457
B17: ='Data Sources'!A47 -> JP | C17: $/Liter | D17: =SUM('Data Sources'!C47/'Data Sources'!$C$72) -> 0 | F17: =Financials!B55 -> Miscellaneous | G17: ='Data Sources'!C102 -> 100000 | H17: =G17/12 -> 8333.3333 | O17: 9.37 | P17: 0.39100006 | Q17: 0.39115303 | R17: 0.391306 | S17: 0.39145898 | T17: 0.39161195 | U17: 0.39192312 | V17: 0.39207612 | W17: 0.39222911 | X17: 0.3923821 | Y17: 0.3925351 | Z17: 0.3926881
B18: ='Data Sources'!A48 -> Gas | C18: $/Liter | D18: =SUM('Data Sources'!C48/'Data Sources'!$C$72) -> 0 | F18: =Financials!B45 -> Land Rental | G18: ='Data Sources'!C103 -> 100000 | H18: =SUM(G18/12) -> 8333.3333 | O18: 9.5 | P18: 0.39104462 | Q18: 0.39119973 | R18: 0.39135482 | S18: 0.39150992 | T18: 0.39166501 | U18: 0.39198051 | V18: 0.39213561 | W18: 0.39229073 | X18: 0.39244586 | Y18: 0.39260098 | Z18: 0.39275611
B19: ='Data Sources'!A49 -> Lube oil | C19: $/Liter | D19: =SUM('Data Sources'!C49/'Data Sources'!$C$72) -> 0 | O19: 9.75 | P19: 0.39113033 | Q19: 0.39128951 | R19: 0.39144869 | S19: 0.39160787 | T19: 0.39176705 | U19: 0.39209085 | V19: 0.39225006 | W19: 0.39240926 | X19: 0.39256846 | Y19: 0.39272767 | Z19: 0.39288688
B20: ='Data Sources'!A50 -> Petroleum Coke | C20: $/Liter | D20: =SUM('Data Sources'!C50/'Data Sources'!$C$72) -> 0 | F20: Tax | O20: 10 | P20: 0.39121605 | Q20: 0.3913793 | R20: 0.39154257 | S20: 0.39170583 | T20: 0.39186911 | U20: 0.3922012 | V20: 0.39236448 | W20: 0.39252778 | X20: 0.39269107 | Y20: 0.39285436 | Z20: 0.39301766
B21: ='Data Sources'!A51 -> RNG Sale price | C21: $ / MMBTU | D21: ='Data Sources'!C51 -> 0
B22: Plant Production | F22: Federal Corporate Income Tax Rate | G22: 0.2 | H22: Current US tax code
B23: Power (PPA Px) | C23: $/MWh | D23: ='Data Sources'!C30 -> 66.55 | F23: Colorado Corporate Income Tax Rate | G23: 0 | H23: N/A plant is not in Colorado | P23: Steel from Tires ($/ST)
B24: Net capacity | F24: Investment Tax Credit | H24: Month | O24: =Summary!$H$12 -> 0.39179596 | P24: 105 | Q24: =P24+5 -> 110 | R24: =Q24+5 -> 115 | S24: =R24+5 -> 120 | T24: =S24+5 -> 125 | U24: 127.08 | V24: 130 | W24: =V24+5 -> 135 | X24: =W24+5 -> 140 | Y24: =X24+5 -> 145 | Z24: =Y24+5 -> 150
B25: Power year 4 through 25 | C25: MW/Hour | D25: ='Data Sources'!C31 -> 37.335738 | F25: Tax Incentive (Years) | G25: 10 | H25: =G25*12 -> 120 | N25: ST / day | O25: 15 | P25: 0.38529728 | Q25: 0.38554423 | R25: 0.38578892 | S25: 0.38603362 | T25: 0.38627833 | U25: 0.38638013 | V25: 0.38652305 | W25: 0.38676777 | X25: 0.38701251 | Y25: 0.38725725 | Z25: 0.38750201
B26: Power year 1 through 3 | C26: MW/Hour | D26: ='Data Sources'!C32 -> 27.335738 | F26: Maintenance Fund | O26: 17.5 | P26: 0.38615597 | Q26: 0.38644148 | R26: 0.38672698 | S26: 0.38701251 | T26: 0.38729804 | U26: 0.38741683 | V26: 0.3875836 | W26: 0.38786915 | X26: 0.38815473 | Y26: 0.38844251 | Z26: 0.3887281
B27: =B3 -> Activated Carbon Ash | C27: MT/day | D27: ='Data Sources'!C59 -> 67.544634 | F27: Contribution (% of Cashflow) | G27: ='Data Sources'!C20 -> 0.05 | O27: 19.19 | P27: 0.38673498 | Q27: 0.38704807 | R27: 0.38736119 | S27: 0.38767431 | T27: 0.38798746 | U27: 0.38811774 | V27: 0.38830282 | W27: 0.38861598 | X27: 0.38892917 | Y27: 0.38924236 | Z27: 0.38955558
B28: =B4 -> Aluminum | C28: MT/day | D28: ='Data Sources'!C60 -> 4.95 | F28: Maximum Fund Amount | G28: ='Data Sources'!C21 -> 45000000 | H28: cap at the maximum placed into the fund by user description | O28: 20 | P28: 0.38701251 | Q28: 0.38733884 | R28: 0.38766518 | S28: 0.38799154 | T28: 0.38832012 | U28: 0.38845589 | V28: 0.3886465 | W28: 0.38897291 | X28: 0.38929933 | Y28: 0.38962576 | Z28: 0.38995221
B29: =B5 -> Ferrous Metals | C29: MT/day | D29: ='Data Sources'!C61 -> 6.82 | O29: 22.5 | P29: 0.38786915 | Q29: 0.38823852 | R29: 0.38860571 | S29: 0.38897291 | T29: 0.38934013 | U29: 0.3894929 | V29: 0.38970737 | W29: 0.39007464 | X29: 0.39044191 | Y29: 0.39080922 | Z29: 0.39117883
B30: =B6 -> Non-Ferrous Metals | C30: MT/day | D30: ='Data Sources'!C62 -> 3.3 | O30: 25 | P30: 0.3887281 | Q30: 0.38913612 | R30: 0.38954415 | S30: 0.38995221 | T30: 0.3903603 | U30: 0.39053007 | V30: 0.39076841 | W30: 0.39117883 | X30: 0.39158698 | Y30: 0.39199515 | Z30: 0.39240335
B31: =B7 -> Steel from Tires | C31: MT/day | D31: =SUM(D36 * 'Data Sources'!C74) -> 15
B32: =B8 -> Steel, OTR Tires | C32: MT/day | D32: 0 | P32: Annual Employee Costs
B33: =B9 -> Carbon Black | C33: MT/day | D33: ='Data Sources'!C63 -> 25.16 | F33: Gallons Conversion | O33: =Summary!$H$12 -> 0.39179596 | P33: =Q33-100000 -> 3570858 | Q33: =R33-100000 -> 3670858 | R33: =S33-100000 -> 3770858 | S33: =T33-100000 -> 3870858 | T33: =U33-100000 -> 3970858 | U33: 4070858 | V33: =U33+100000 -> 4170858 | W33: =V33+100000 -> 4270858 | X33: =W33+100000 -> 4370858 | Y33: =X33+100000 -> 4470858 | Z33: =Y33+100000 -> 4570858
B34: =B10 -> Graphene | C34: MT/day | D34: ='Data Sources'!C64 -> 5.661 | F34: =SUM(D37 / 'Data Sources'!$C$72) -> 6704.1199 | H34: Wholesale Price per gallon | N34: Total O&M Expense | O34: =O35-100000 -> 2848800 | P34: 0.39063134 | Q34: 0.38976352 | R34: 0.38889589 | S34: 0.38802628 | T34: 0.38715906 | U34: 0.38629205 | V34: 0.38542297 | W34: 0.38455637 | X34: 0.38368999 | Y34: 0.38282155 | Z34: 0.38195559
B35: MSW consumption | C35: MT/day | D35: =SUM('Data Sources'!C53) -> 550 | F35: =SUM(D39 / 'Data Sources'!$C$72) -> 1340.824 | O35: =O36-100000 -> 2948800 | P35: 0.38973696 | Q35: 0.38886929 | R35: 0.38799964 | S35: 0.38713236 | T35: 0.38626531 | U35: 0.3853962 | V35: 0.38452955 | W35: 0.38366312 | X35: 0.38279465 | Y35: 0.38192864 | Z35: 0.38106286
B36: Gross Tires Processed | C36: MT/day | D36: ='Data Sources'!C54 -> 100 | F36: =SUM(D40 / 'Data Sources'!$C$72) -> 1340.824 | O36: =O37-100000 -> 3048800 | P36: 0.38884268 | Q36: 0.38797298 | R36: 0.38710567 | S36: 0.38623857 | T36: 0.38536941 | U36: 0.38450273 | V36: 0.38363625 | W36: 0.38276773 | X36: 0.38190168 | Y36: 0.38103586 | Z36: 0.38017026
B37: Oil from Tires | C37: Liters/day | D37: =SUM('Data Sources'!C66*'Data Sources'!C72) -> 25377.843 | F37: =SUM(D41 / 'Data Sources'!$C$72) -> 1340.824 | H37: 1.881 | J37: =SUM(H37/'Data Sources'!C72) -> 0.49690786 | O37: =O38-100000 -> 3148800 | P37: 0.38794633 | Q37: 0.38707897 | R37: 0.38621183 | S37: 0.38534263 | T37: 0.38447589 | U37: 0.38360938 | V37: 0.38274081 | W37: 0.38187472 | X37: 0.38100885 | Y37: 0.3801432 | Z37: 0.37927558
B38: =B15 -> Light Oil Sale | C38: Barrel/day | D38: =SUM('Data Sources'!C66/42) -> 159.6219 | F38: =SUM(D42 / 'Data Sources'!$C$72) -> 1340.824 | O38: 3248800 | P38: 0.38705227 | Q38: 0.38618509 | R38: 0.38531584 | S38: 0.38444906 | T38: 0.3835825 | U38: 0.3827139 | V38: 0.38184776 | W38: 0.38098183 | X38: 0.38011397 | Y38: 0.37924848 | Z38: 0.37838323
B39: Diesel | C39: Liters/day | D39: =SUM($D$37 * 'Data Sources'!C67) -> 5075.5685 | F39: =SUM(D43 / 'Data Sources'!$C$72) -> 1340.824 | O39: =O38+100000 -> 3348800 | P39: 0.38615834 | Q39: 0.38528904 | R39: 0.38442222 | S39: 0.38355562 | T39: 0.38268697 | U39: 0.38182078 | V39: 0.38095482 | W39: 0.3800869 | X39: 0.37922137 | Y39: 0.37835608 | Z39: 0.37749102
B40: JP | C40: Liters/day | D40: =SUM($D$37 * 'Data Sources'!C68) -> 5075.5685 | O40: =O39+100000 -> 3448800 | P40: 0.38526224 | Q40: 0.38439539 | R40: 0.38352874 | S40: 0.38266004 | T40: 0.38179381 | U40: 0.38092781 | V40: 0.38005984 | W40: 0.37919427 | X40: 0.37832893 | Y40: 0.37746155 | Z40: 0.37659665
B41: Gas | C41: Liters/day | D41: =SUM($D$37 * 'Data Sources'!C69) -> 5075.5685 | O41: =O40+100000 -> 3548800 | P41: 0.38436854 | Q41: 0.38350186 | R41: 0.38263311 | S41: 0.38176684 | T41: 0.38090078 | U41: 0.38003278 | V41: 0.37916716 | W41: 0.37830177 | X41: 0.37743436 | Y41: 0.37656941 | Z41: 0.3757047
B42: Lube oil | C42: Liters/day | D42: =SUM($D$37 * 'Data Sources'!C70) -> 5075.5685 | O42: =O41+100000 -> 3648800 | P42: 0.38347496 | Q42: 0.38260618 | R42: 0.38173986 | S42: 0.38087377 | T42: 0.38000571 | U42: 0.37914005 | V42: 0.37827461 | W42: 0.37740715 | X42: 0.37654216 | Y42: 0.37567741 | Z42: 0.3748129
B43: Petroleum Coke | C43: Liters/day | D43: =SUM($D$37 * 'Data Sources'!C71) -> 5075.5685 | O43: =O42+100000 -> 3748800 | P43: 0.38257924 | Q43: 0.38171288 | R43: 0.38084674 | S43: 0.37997864 | T43: 0.37911294 | U43: 0.37824746 | V43: 0.37737995 | W43: 0.37651491 | X43: 0.37565011 | Y43: 0.37478555 | Z43: 0.37391903
B44: RNG Production | C44: MMBTU/day | D44: ='Data Sources'!C75 -> 7539.0971 | O44: =O43+100000 -> 3848800 | P44: 0.38168589 | Q44: 0.38081971 | R44: 0.37995157 | S44: 0.37908582 | T44: 0.37822029 | U44: 0.37735273 | V44: 0.37648765 | W44: 0.37562281 | X44: 0.37475602 | Y44: 0.37389163 | Z44: 0.37302749
P46: Carbon Black ($/ST)
O47: =Summary!$H$12 -> 0.39179596 | P47: 780 | Q47: 790 | R47: 800 | S47: 810 | T47: 820 | U47: 830 | V47: 840 | W47: 850 | X47: 860 | Y47: 870 | Z47: 880
N48: ST / day | O48: =O49-2 -> 30 | P48: 0.39426724 | Q48: 0.39524725 | R48: 0.3962274 | S48: 0.39720995 | T48: 0.39819034 | U48: 0.39917085 | V48: 0.40015351 | W48: 0.40113426 | X48: 0.40211512 | Y48: 0.40309837 | Z48: 0.40407946
O49: =O50-2 -> 32 | P49: 0.39936901 | Q49: 0.40041503 | R49: 0.4014612 | S49: 0.40250979 | T49: 0.4035562 | U49: 0.40460274 | V49: 0.40565171 | W49: 0.40669848 | X49: 0.40774539 | Y49: 0.40879462 | Z49: 0.40984175
O50: =O51-2 -> 34 | P50: 0.40447192 | Q50: 0.40558628 | R50: 0.40669848 | S50: 0.40781083 | T50: 0.4089255 | U50: 0.4100381 | V50: 0.41115313 | W50: 0.41226597 | X50: 0.41337894 | Y50: 0.41449425 | Z50: 0.41560743
O51: 36 | P51: 0.40957996 | Q51: 0.41075808 | R51: 0.41193865 | S51: 0.41311705 | T51: 0.41429781 | U51: 0.41547647 | V51: 0.41665526 | W51: 0.41783648 | X51: 0.41901551 | Y51: 0.42019699 | Z51: 0.42137625
O52: =O51+2 -> 38 | P52: 0.41469068 | Q52: 0.41593487 | R52: 0.41718152 | S52: 0.41842598 | T52: 0.41967059 | U52: 0.42091764 | V52: 0.42216249 | W52: 0.42340972 | X52: 0.42465481 | Y52: 0.42590002 | Z52: 0.42714768
O53: =O52+2 -> 40 | P53: 0.4198016 | Q53: 0.42111418 | R53: 0.42242457 | S53: 0.42373735 | T53: 0.42504802 | U53: 0.42636115 | V53: 0.42767206 | W53: 0.4289831 | X53: 0.43029651 | Y53: 0.43160778 | Z53: 0.4329215
O54: =O53+2 -> 42 | P54: 0.42491694 | Q54: 0.42629561 | R54: 0.42767206 | S54: 0.42904866 | T54: 0.43042763 | U54: 0.43180447 | V54: 0.4331838 | W54: 0.43456087 | X54: 0.43594016 | Y54: 0.43731746 | Z54: 0.43869724
P57: Power (PPA px) $/MWh
O58: =Summary!$H$12 -> 0.39179596 | P58: 61.5 | Q58: 62.5 | R58: 63.5 | S58: 64.5 | T58: 65.5 | U58: 66.5 | V58: 67.5 | W58: 68.5 | X58: 69.5 | Y58: 70.5 | Z58: 71.5
N59: MW/Hour | O59: =O60-1 -> 29.5 | P59: 0.35571182 | Q59: 0.35732659 | R59: 0.35893895 | S59: 0.36054671 | T59: 0.36215422 | U59: 0.36375938 | V59: 0.36535992 | W59: 0.36696017 | X59: 0.36855809 | Y59: 0.37015333 | Z59: 0.37174415
O60: =O61-1 -> 30.5 | P60: 0.3590753 | Q60: 0.36073732 | R60: 0.36239888 | S60: 0.36405796 | T60: 0.36571439 | U60: 0.36736609 | V60: 0.3690174 | W60: 0.37066589 | X60: 0.37231202 | Y60: 0.3739533 | Z60: 0.37559419
O61: =O62-1 -> 31.5 | P61: 0.36242607 | Q61: 0.36413938 | R61: 0.36584987 | S61: 0.36755547 | T61: 0.3692605 | U61: 0.37096253 | V61: 0.37266201 | W61: 0.37435649 | X61: 0.37605041 | Y61: 0.37774145 | Z61: 0.37942979
O62: =O63-1 -> 32.5 | P62: 0.36576859 | Q62: 0.36752841 | R62: 0.36928751 | S62: 0.37104341 | T62: 0.3727966 | U62: 0.3745446 | V62: 0.37629185 | W62: 0.37803605 | X62: 0.37977735 | Y62: 0.38151343 | Z62: 0.38324869
O63: 33.5 | P63: 0.36909844 | Q63: 0.3709086 | R63: 0.37271585 | S63: 0.37451773 | T63: 0.37631868 | U63: 0.37811638 | V63: 0.37991101 | W63: 0.38170239 | X63: 0.38348842 | Y63: 0.38527353 | Z63: 0.38705546
O64: =O63+1 -> 34.5 | P64: 0.37241972 | Q64: 0.37427587 | R64: 0.3761309 | S64: 0.37798249 | T64: 0.37983082 | U64: 0.38167571 | V64: 0.38351505 | W64: 0.38535329 | X64: 0.38718815 | Y64: 0.38901957 | Z64: 0.3908454
O65: =O64+1 -> 35.5 | P65: 0.3757284 | Q65: 0.3776343 | R65: 0.37953674 | S65: 0.38143337 | T65: 0.38332861 | U65: 0.38522035 | V65: 0.38710855 | W65: 0.38899308 | X65: 0.39087184 | Y65: 0.3927493 | Z65: 0.39462311
O66: =O65+1 -> 36.5 | P66: 0.37902635 | Q66: 0.38097958 | R66: 0.38292896 | S66: 0.38487466 | T66: 0.38681659 | U66: 0.38875467 | V66: 0.39068677 | W66: 0.39261736 | X66: 0.39454409 | Y66: 0.39646713 | Z66: 0.39838614
O67: =O66+1 -> 37.5 | P67: 0.38231586 | Q67: 0.38431597 | R67: 0.38630986 | S67: 0.388302 | T67: 0.39029006 | U67: 0.39227424 | V67: 0.39425433 | W67: 0.39623054 | X67: 0.39820248 | Y67: 0.40016838 | Z67: 0.40213258

Sheet Project Equity %
B2: Total Project Equity | C2: =Summary!D3 -> 64955662
B4: Total Equity Contributed
B5: CREC Equity | C5: 0 | D5: 0.25
B6: Outside Equity | C6: =$C$2 -> 64955662 | D6: =1-D5 -> 0.75
C8: Project Level Equity Ownership %
B9: $USD | C9: =D9-0.05 -> 0.25 | D9: =E9-0.05 -> 0.3 | E9: =F9-0.05 -> 0.35 | F9: =G9-0.05 -> 0.4 | G9: =H9-0.05 -> 0.45 | H9: =I9-0.05 -> 0.5 | I9: =J9-0.05 -> 0.55 | J9: =K9-0.05 -> 0.6 | ... L9: =M9-0.05 -> 0.7 | M9: =D6 -> 0.75
B10: Equity Contributions | C10: =(C9/$D$6)*$C$6 -> 21651887 | D10: =(D9/$D$6)*$C$6 -> 25982265 | E10: =(E9/$D$6)*$C$6 -> 30312642 | F10: =(F9/$D$6)*$C$6 -> 34643020 | G10: =(G9/$D$6)*$C$6 -> 38973397 | H10: =(H9/$D$6)*$C$6 -> 43303774 | I10: =(I9/$D$6)*$C$6 -> 47634152 | J10: =(J9/$D$6)*$C$6 -> 51964529 | ... L10: =(L9/$D$6)*$C$6 -> 60625284 | M10: =C6 -> 64955662
B11: Equity Cash Flows | C11: =C$9*Summary!$H$11 -> 2.8234519e+08 | D11: =D$9*Summary!$H$11 -> 3.3881422e+08 | E11: =E$9*Summary!$H$11 -> 3.9528326e+08 | F11: =F$9*Summary!$H$11 -> 4.517523e+08 | G11: =G$9*Summary!$H$11 -> 5.0822133e+08 | H11: =H$9*Summary!$H$11 -> 5.6469037e+08 | I11: =I$9*Summary!$H$11 -> 6.2115941e+08 | J11: =J$9*Summary!$H$11 -> 6.7762844e+08 | ... M11: =M$9*Summary!$H$11 -> 8.4703556e+08
B12: Net Present Value | C12: =C$9*Summary!$H$13 -> 58267428 | D12: =D$9*Summary!$H$13 -> 69920914 | E12: =E$9*Summary!$H$13 -> 81574399 | F12: =F$9*Summary!$H$13 -> 93227885 | G12: =G$9*Summary!$H$13 -> 1.0488137e+08 | H12: =H$9*Summary!$H$13 -> 1.1653486e+08 | I12: =I$9*Summary!$H$13 -> 1.2818834e+08 | J12: =J$9*Summary!$H$13 -> 1.3984183e+08 | ... M12: =M$9*Summary!$H$13 -> 1.7480228e+08

Sheet CapEx
A1: Value by Country amount on orgin amount | C1: USA | D1: =SUM(D11+D12+D13+D14+D15+D16+D46+D47+D48+D49+D50+D51+D52+D53+D54+D55+D56+D57+D58+D59+D60+D61+D62+D63+D64+D65+D66+D69+D73+D74+D75+D76+D84+D85+D86+D88+D98+D101+D102+D87) -> 1.1754615e+08
C2: Djibouti | D2: =SUM(D103+D112) -> 7146511.8
C3: India | D3: =SUM(D89+D90+D91+D92+D93+D94) -> 2240000
C4: UK | D4: =SUM(D70+D71+D72+D67+D77+D78+D79+D80+D82+D83+D68+D95+D96+D97+D99+D100+D104+D105+D108+D110) -> 1.073307e+08
C5: Finland | D5: =SUM(F10+F18+F19+F35+F36) -> 2583373.3 | F5: Tire Only Processing column flag is whether the equipment would be used for a tire only facility. This provides only a high level assumption. Design would be required to solidify the numbers. Also the MSW value in Data Sources needs to be set to "0"
C6: Germany | D6: =SUM(D18+D19+D35+D36+D20+D21+D22+D23+D24+D25+D26+D27+D28+D29+D30+D31+D32+D33+D34+D37+D38+D39+D40+D41+D42+D43+D44) -> 9149476.3
C7: Holland | D7: =SUM(D45) -> 1148000 | N7: Month Plant Online | O7: ='Data Sources'!C4 -> 16
C8: Total Capital Expenditures | D8: =SUM(D1:D7) -> 2.471442e+08 | J8: Draw Down schedule for equipment purchase
B9: STAGE | C9: Equipment | D9: $ | E9: Comments | F9: Vendor price | G9: Country Purchase | H9: Country Origin | I9: Tire Only Processing | J9: Upon order | K9: Complete before shipment | L9: Delivered and installed | M9: Lead Time in Months | N9: Capital Expenditures Timeline | R9: Depreciation Schedule
B10: 1 | C10: Base Primary Shredder | D10: =IF(I10="N",F10,0) -> 700000 | F10: 700000 | G10: NC, USA | H10: Finland | I10: =IF('Data Sources'!$C$27="N","N","Y") -> N | J10: 0.5 | K10: 0.4 | L10: 0.1 | M10: 8 | N10: Month | O10: Period | P10: Cumulative | R10: Year | S10: Annual | T10: Month | U10: Monthly | V10: Cumulative
B11: 1 | C11: CM4R Liberator Unit Price | D11: =IF(I11="Y",F11,0) -> 1203500 | F11: 1203500 | G11: FL, USA | H11: FL, USA | I11: Y | J11: 0.5 | K11: 0.4 | L11: 0.1 | M11: 8 | N11: 1 | O11: 0.21716081 | P11: =SUM($O$11:O11) -> 0.21716081 | R11: 1 | S11: =1/7 -> 0.14285714 | T11: =O7+11 -> 27 | U11: =S11/12 -> 0.011904762 | V11: =SUM($S$11:S11) -> 0.14285714
B12: 1 | C12: Spare parts for the year | D12: =IF(I12="Y",F12,0) -> 34573.8 | F12: 34573.8 | G12: FL, USA | H12: FL, USA | I12: Y | J12: 0.5 | K12: 0.4 | L12: 0.1 | M12: 8 | N12: 2 | O12: 0.068334204 | P12: =SUM($O$11:O12) -> 0.28549501 | R12: =R11+1 -> 2 | S12: =1/7 -> 0.14285714 | T12: =T11+12 -> 39 | U12: =S12/12 -> 0.011904762 | V12: =SUM($S$11:S12) -> 0.28571429
B13: 1 | C13: Eagle OTR debeader | D13: 446430 | E13: 3/10/2025 updated | F13: 407774 | G13: NE, USA | H13: NE, USA | I13: Y | J13: 0.5 | K13: 0.4 | L13: 0.1 | M13: 8 | N13: 3 | O13: 0.055080355 | P13: =SUM($O$11:O13) -> 0.34057537 | R13: =R12+1 -> 3 | S13: =1/7 -> 0.14285714 | T13: =T12+12 -> 51 | U13: =S13/12 -> 0.011904762 | V13: =SUM($S$11:S13) -> 0.42857143
B14: 1 | C14: Eagle punch cutter 2 | D14: 304858 | E14: 3/10/2025 updated | F14: 231396 | G14: NE, USA | H14: NE, USA | I14: Y | J14: 0.5 | K14: 0.4 | L14: 0.1 | M14: 8 | N14: 4 | O14: 0.035148729 | P14: =SUM($O$11:O14) -> 0.3757241 | R14: =R13+1 -> 4 | S14: =1/7 -> 0.14285714 | T14: =T13+12 -> 63 | U14: =S14/12 -> 0.011904762 | V14: =SUM($S$11:S14) -> 0.57142857
B15: 1 | C15: Eagle titan 2 | D15: 516512 | E15: 3/10/2025 updated | F15: 507209 | G15: NE, USA | H15: NE, USA | I15: Y | J15: 0.5 | K15: 0.4 | L15: 0.1 | M15: 8 | N15: 5 | O15: 0.083342618 | P15: =SUM($O$11:O15) -> 0.45906672 | R15: =R14+1 -> 5 | S15: =1/7 -> 0.14285714 | T15: =T14+12 -> 75 | U15: =S15/12 -> 0.011904762 | V15: =SUM($S$11:S15) -> 0.71428571
B16: 1 | C16: Cuber for MSW Warren n Baerg | D16: =IF(I16="N",F16,0) -> 2685974 | F16: 2685974 | G16: CA, USA | H16: CA, USA | I16: =IF('Data Sources'!$C$27="N","N","Y") -> N | J16: 0.5 | K16: 0.4 | L16: 0.1 | M16: 8 | N16: 6 | O16: 0.10345018 | P16: =SUM($O$11:O16) -> 0.56251689 | R16: =R15+1 -> 6 | S16: =1/7 -> 0.14285714 | T16: =T15+12 -> 87 | U16: =S16/12 -> 0.011904762 | V16: =SUM($S$11:S16) -> 0.85714286
B17: 1 | C17: placeholder for extra feed hoppers and associated conveyors | D17: =IF(I17="N",F17,0) -> 1200000 | F17: 1200000 | G17: CA, USA | H17: CA, USA | I17: =IF('Data Sources'!$C$27="N","N","Y") -> N | J17: 0.5 | K17: 0.4 | L17: 0.1 | M17: 8 | N17: 7 | O17: 0.090610633 | P17: =SUM($O$11:O17) -> 0.65312753 | R17: =R16+1 -> 7 | S17: =1/7 -> 0.14285714 | T17: =T16+12 -> 99 | U17: =S17/12 -> 0.011904762 | V17: =SUM($S$11:S17) -> 1
B18: 1 | C18: Position 1 Metso Pre-Shredder | D18: =IF(I18="N",F18,0) -> 648785.95 | F18: 648785.95 | G18: NC, USA | H18: Finland | I18: =IF('Data Sources'!$C$27="N","N","Y") -> N | J18: 0.5 | K18: 0.4 | L18: 0.1 | M18: 8 | N18: 8 | O18: 0.077696546 | P18: =SUM($O$11:O18) -> 0.73082407 | R18: =R17+1 -> 8 | T18: =T17+12 -> 111
B19: 1 | C19: Position 2 Shredder discharge, Magnetic separation and screen feed | D19: =IF(I19="N",F19,0) -> 128789.5 | F19: 128789.5 | G19: NC, USA | H19: Finland | I19: =IF('Data Sources'!$C$27="N","N","Y") -> N | J19: 0.5 | K19: 0.4 | L19: 0.1 | M19: 8 | N19: 9 | O19: 0.071405245 | P19: =SUM($O$11:O19) -> 0.80222932 | R19: =R18+1 -> 9 | T19: =T18+12 -> 123
B20: 1 | C20: Position 3 Cascade Screen Package | D20: =IF(I20="N",F20,0) -> 255272.59 | F20: 255272.59 | G20: NC, USA | H20: Germany | I20: =IF('Data Sources'!$C$27="N","N","Y") -> N | J20: 0.5 | K20: 0.4 | L20: 0.1 | M20: 8 | N20: 10 | O20: 0.058318105 | P20: =SUM($O$11:O20) -> 0.86054742 | R20: =R19+1 -> 10 | T20: =T19+12 -> 135
B21: 1 | C21: Westeria FlatCon 1400-11200 | D21: =IF(I21="N",F21,0) -> 53428.5 | F21: 53428.5 | G21: NC, USA | H21: Germany | I21: =IF('Data Sources'!$C$27="N","N","Y") -> N | J21: 0.5 | K21: 0.4 | L21: 0.1 | M21: 8 | N21: 11 | O21: 0.056661897 | P21: =SUM($O$11:O21) -> 0.91720932
B22: 1 | C22: Position 5 Eddie Current System | D22: =IF(I22="N",F22,0) -> 234967.15 | F22: 234967.15 | G22: NC, USA | H22: Germany | I22: =IF('Data Sources'!$C$27="N","N","Y") -> N | J22: 0.5 | K22: 0.4 | L22: 0.1 | M22: 8 | N22: 12 | O22: 0.08279068 | P22: =SUM($O$11:O22) -> 1 | Y22: Depreciation Schedule
B23: 1 | C23: Position 6 Wisteria windsifter and feed conveyor to NI includes bag house | D23: =IF(I23="N",F23,0) -> 229153.55 | F23: 229153.55 | G23: NC, USA | H23: Germany | I23: =IF('Data Sources'!$C$27="N","N","Y") -> N | J23: 0.5 | K23: 0.4 | L23: 0.1 | M23: 8 | N23: 13 | P23: =SUM($O$11:O23) -> 1 | R23: Maintenance Capital Expenditures | U23: Depreciation | Y23: ='Data Sources'!C1 -> 2026 | Z23: =SUM(Y23+1) -> 2027 | AA23: =SUM(Z23+1) -> 2028 | AB23: =SUM(AA23+1) -> 2029 | AC23: =SUM(AB23+1) -> 2030 | AD23: =SUM(AC23+1) -> 2031 | AE23: =SUM(AD23+1) -> 2032 | AF23: =SUM(AE23+1) -> 2033 | AG23: =SUM(AF23+1) -> 2034 | ... AU23: =SUM(AT23+1) -> 2048
B24: 1 | C24: Position 7 Bag House for AirStar 2000 | D24: =IF(I24="N",F24,0) -> 65000 | F24: 65000 | G24: NC, USA | H24: Germany | I24: =IF('Data Sources'!$C$27="N","N","Y") -> N | J24: 0.5 | K24: 0.4 | L24: 0.1 | M24: 8 | N24: 14 | P24: =SUM($O$11:O24) -> 1 | R24: Year | S24: Annual | T24: Monthly | U24: Straight Line | V24: Annual | W24: Monthly | Y24: =_xlfn.IFS(Y$23<$R25,0,Y$23>=($R25+$U25),0,Y$23>=$R25,$V25) -> 0 | Z24: =_xlfn.IFS(Z$23<$R25,0,Z$23>=($R25+$U25),0,Z$23>=$R25,$V25) -> 0 | AA24: =_xlfn.IFS(AA$23<$R25,0,AA$23>=($R25+$U25),0,AA$23>=$R25,$V25) -> 0 | AB24: =_xlfn.IFS(AB$23<$R25,0,AB$23>=($R25+$U25),0,AB$23>=$R25,$V25) -> 0 | AC24: =_xlfn.IFS(AC$23<$R25,0,AC$23>=($R25+$U25),0,AC$23>=$R25,$V25) -> 0 | AD24: =_xlfn.IFS(AD$23<$R25,0,AD$23>=($R25+$U25),0,AD$23>=$R25,$V25) -> 0 | AE24: =_xlfn.IFS(AE$23<$R25,0,AE$23>=($R25+$U25),0,AE$23>=$R25,$V25) -> 0 | AF24: =_xlfn.IFS(AF$23<$R25,0,AF$23>=($R25+$U25),0,AF$23>=$R25,$V25) -> 0 | ... AU24: =_xlfn.IFS(AU$23<$R25,0,AU$23>=($R25+$U25),0,AU$23>=$R25,$V25) -> 0
B25: 1 | C25: Position 8 Middle fraction light discharge conveying | D25: =IF(I25="N",F25,0) -> 117497.75 | F25: 117497.75 | G25: NC, USA | H25: Germany | I25: =IF('Data Sources'!$C$27="N","N","Y") -> N | J25: 0.5 | K25: 0.4 | L25: 0.1 | M25: 8 | N25: 15 | P25: =SUM($O$11:O25) -> 1 | R25: =Y23 -> 2026 | S25: 0 | T25: =S25/12 -> 0 | U25: 7 | V25: =S25/U25 -> 0 | W25: =V25/12 -> 0 | Y25: =_xlfn.IFS(Y$23<$R26,0,Y$23>=($R26+$U26),0,Y$23>=$R26,$V26) -> 0 | Z25: =_xlfn.IFS(Z$23<$R26,0,Z$23>=($R26+$U26),0,Z$23>=$R26,$V26) -> 0 | AA25: =_xlfn.IFS(AA$23<$R26,0,AA$23>=($R26+$U26),0,AA$23>=$R26,$V26) -> 0 | AB25: =_xlfn.IFS(AB$23<$R26,0,AB$23>=($R26+$U26),0,AB$23>=$R26,$V26) -> 0 | AC25: =_xlfn.IFS(AC$23<$R26,0,AC$23>=($R26+$U26),0,AC$23>=$R26,$V26) -> 0 | AD25: =_xlfn.IFS(AD$23<$R26,0,AD$23>=($R26+$U26),0,AD$23>=$R26,$V26) -> 0 | AE25: =_xlfn.IFS(AE$23<$R26,0,AE$23>=($R26+$U26),0,AE$23>=$R26,$V26) -> 0 | AF25: =_xlfn.IFS(AF$23<$R26,0,AF$23>=($R26+$U26),0,AF$23>=$R26,$V26) -> 0 | ... AU25: =_xlfn.IFS(AU$23<$R26,0,AU$23>=($R26+$U26),0,AU$23>=$R26,$V26) -> 0
B26: 1 | C26: Position 9 Optical Sorting middle fraction | D26: =IF(I26="N",F26,0) -> 340082.6 | F26: 340082.6 | G26: NC, USA | H26: Germany | I26: =IF('Data Sources'!$C$27="N","N","Y") -> N | J26: 0.5 | K26: 0.4 | L26: 0.1 | M26: 8 | N26: 16 | P26: =SUM($O$11:O26) -> 1 | R26: =R25+1 -> 2027 | S26: 0 | T26: =S26/12 -> 0 | U26: 7 | V26: =S26/U26 -> 0 | W26: =V26/12 -> 0 | Y26: =_xlfn.IFS(Y$23<$R27,0,Y$23>=($R27+$U27),0,Y$23>=$R27,$V27) -> 0 | Z26: =_xlfn.IFS(Z$23<$R27,0,Z$23>=($R27+$U27),0,Z$23>=$R27,$V27) -> 0 | AA26: =_xlfn.IFS(AA$23<$R27,0,AA$23>=($R27+$U27),0,AA$23>=$R27,$V27) -> 0 | AB26: =_xlfn.IFS(AB$23<$R27,0,AB$23>=($R27+$U27),0,AB$23>=$R27,$V27) -> 0 | AC26: =_xlfn.IFS(AC$23<$R27,0,AC$23>=($R27+$U27),0,AC$23>=$R27,$V27) -> 0 | AD26: =_xlfn.IFS(AD$23<$R27,0,AD$23>=($R27+$U27),0,AD$23>=$R27,$V27) -> 0 | AE26: =_xlfn.IFS(AE$23<$R27,0,AE$23>=($R27+$U27),0,AE$23>=$R27,$V27) -> 0 | AF26: =_xlfn.IFS(AF$23<$R27,0,AF$23>=($R27+$U27),0,AF$23>=$R27,$V27) -> 0 | ... AU26: =_xlfn.IFS(AU$23<$R27,0,AU$23>=($R27+$U27),0,AU$23>=$R27,$V27) -> 0
B27: 1 | C27: westeria flatcon 1200-18200 | D27: =IF(I27="N",F27,0) -> 40819.25 | F27: 40819.25 | G27: NC, USA | H27: Germany | I27: =IF('Data Sources'!$C$27="N","N","Y") -> N | J27: 0.5 | K27: 0.4 | L27: 0.1 | M27: 8 | N27: 17 | P27: =SUM($O$11:O27) -> 1 | R27: =R26+1 -> 2028 | S27: 0 | T27: =S27/12 -> 0 | U27: 7 | V27: =S27/U27 -> 0 | W27: =V27/12 -> 0 | Y27: =_xlfn.IFS(Y$23<$R28,0,Y$23>=($R28+$U28),0,Y$23>=$R28,$V28) -> 0 | Z27: =_xlfn.IFS(Z$23<$R28,0,Z$23>=($R28+$U28),0,Z$23>=$R28,$V28) -> 0 | AA27: =_xlfn.IFS(AA$23<$R28,0,AA$23>=($R28+$U28),0,AA$23>=$R28,$V28) -> 0 | AB27: =_xlfn.IFS(AB$23<$R28,0,AB$23>=($R28+$U28),0,AB$23>=$R28,$V28) -> 0 | AC27: =_xlfn.IFS(AC$23<$R28,0,AC$23>=($R28+$U28),0,AC$23>=$R28,$V28) -> 0 | AD27: =_xlfn.IFS(AD$23<$R28,0,AD$23>=($R28+$U28),0,AD$23>=$R28,$V28) -> 0 | AE27: =_xlfn.IFS(AE$23<$R28,0,AE$23>=($R28+$U28),0,AE$23>=$R28,$V28) -> 0 | AF27: =_xlfn.IFS(AF$23<$R28,0,AF$23>=($R28+$U28),0,AF$23>=$R28,$V28) -> 0 | ... AU27: =_xlfn.IFS(AU$23<$R28,0,AU$23>=($R28+$U28),0,AU$23>=$R28,$V28) -> 0
B28: 1 | C28: steinert nes 250 300 e 6109-5 | D28: =IF(I28="N",F28,0) -> 240975.19 | F28: 240975.19 | G28: NC, USA | H28: Germany | I28: =IF('Data Sources'!$C$27="N","N","Y") -> N | J28: 0.5 | K28: 0.4 | L28: 0.1 | M28: 8 | N28: 18 | P28: =SUM($O$11:O28) -> 1 | R28: =R27+1 -> 2029 | S28: 0 | T28: =S28/12 -> 0 | U28: 7 | V28: =S28/U28 -> 0 | W28: =V28/12 -> 0 | Y28: =_xlfn.IFS(Y$23<$R29,0,Y$23>=($R29+$U29),0,Y$23>=$R29,$V29) -> 0 | Z28: =_xlfn.IFS(Z$23<$R29,0,Z$23>=($R29+$U29),0,Z$23>=$R29,$V29) -> 0 | AA28: =_xlfn.IFS(AA$23<$R29,0,AA$23>=($R29+$U29),0,AA$23>=$R29,$V29) -> 0 | AB28: =_xlfn.IFS(AB$23<$R29,0,AB$23>=($R29+$U29),0,AB$23>=$R29,$V29) -> 0 | AC28: =_xlfn.IFS(AC$23<$R29,0,AC$23>=($R29+$U29),0,AC$23>=$R29,$V29) -> 0 | AD28: =_xlfn.IFS(AD$23<$R29,0,AD$23>=($R29+$U29),0,AD$23>=$R29,$V29) -> 0 | AE28: =_xlfn.IFS(AE$23<$R29,0,AE$23>=($R29+$U29),0,AE$23>=$R29,$V29) -> 0 | AF28: =_xlfn.IFS(AF$23<$R29,0,AF$23>=($R29+$U29),0,AF$23>=$R29,$V29) -> 0 | ... AU28: =_xlfn.IFS(AU$23<$R29,0,AU$23>=($R29+$U29),0,AU$23>=$R29,$V29) -> 0
B29: 1 | C29: westeria flatcon 1200-14500 | D29: =IF(I29="N",F29,0) -> 36990.75 | F29: 36990.75 | G29: NC, USA | H29: Germany | I29: =IF('Data Sources'!$C$27="N","N","Y") -> N | J29: 0.5 | K29: 0.4 | L29: 0.1 | M29: 8 | N29: 19 | P29: =SUM($O$11:O29) -> 1 | R29: =R28+1 -> 2030 | S29: 0 | T29: =S29/12 -> 0 | U29: 7 | V29: =S29/U29 -> 0 | W29: =V29/12 -> 0 | Y29: =_xlfn.IFS(Y$23<$R30,0,Y$23>=($R30+$U30),0,Y$23>=$R30,$V30) -> 0 | Z29: =_xlfn.IFS(Z$23<$R30,0,Z$23>=($R30+$U30),0,Z$23>=$R30,$V30) -> 0 | AA29: =_xlfn.IFS(AA$23<$R30,0,AA$23>=($R30+$U30),0,AA$23>=$R30,$V30) -> 0 | AB29: =_xlfn.IFS(AB$23<$R30,0,AB$23>=($R30+$U30),0,AB$23>=$R30,$V30) -> 0 | AC29: =_xlfn.IFS(AC$23<$R30,0,AC$23>=($R30+$U30),0,AC$23>=$R30,$V30) -> 0 | AD29: =_xlfn.IFS(AD$23<$R30,0,AD$23>=($R30+$U30),0,AD$23>=$R30,$V30) -> 0 | AE29: =_xlfn.IFS(AE$23<$R30,0,AE$23>=($R30+$U30),0,AE$23>=$R30,$V30) -> 0 | AF29: =_xlfn.IFS(AF$23<$R30,0,AF$23>=($R30+$U30),0,AF$23>=$R30,$V30) -> 0 | ... AU29: =_xlfn.IFS(AU$23<$R30,0,AU$23>=($R30+$U30),0,AU$23>=$R30,$V30) -> 0
B30: 1 | C30: WESTERIA airstar 2000 l1 wind sifter | D30: =IF(I30="N",F30,0) -> 229153.55 | F30: 229153.55 | G30: NC, USA | H30: Germany | I30: =IF('Data Sources'!$C$27="N","N","Y") -> N | J30: 0.5 | K30: 0.4 | L30: 0.1 | M30: 8 | N30: 20 | P30: =SUM($O$11:O30) -> 1 | R30: =R29+1 -> 2031 | S30: 0 | T30: =S30/12 -> 0 | U30: 7 | V30: =S30/U30 -> 0 | W30: =V30/12 -> 0 | Y30: =_xlfn.IFS(Y$23<$R31,0,Y$23>=($R31+$U31),0,Y$23>=$R31,$V31) -> 0 | Z30: =_xlfn.IFS(Z$23<$R31,0,Z$23>=($R31+$U31),0,Z$23>=$R31,$V31) -> 0 | AA30: =_xlfn.IFS(AA$23<$R31,0,AA$23>=($R31+$U31),0,AA$23>=$R31,$V31) -> 0 | AB30: =_xlfn.IFS(AB$23<$R31,0,AB$23>=($R31+$U31),0,AB$23>=$R31,$V31) -> 0 | AC30: =_xlfn.IFS(AC$23<$R31,0,AC$23>=($R31+$U31),0,AC$23>=$R31,$V31) -> 0 | AD30: =_xlfn.IFS(AD$23<$R31,0,AD$23>=($R31+$U31),0,AD$23>=$R31,$V31) -> 0 | AE30: =_xlfn.IFS(AE$23<$R31,0,AE$23>=($R31+$U31),0,AE$23>=$R31,$V31) -> 0 | AF30: =_xlfn.IFS(AF$23<$R31,0,AF$23>=($R31+$U31),0,AF$23>=$R31,$V31) -> 0 | ... AU30: =_xlfn.IFS(AU$23<$R31,0,AU$23>=($R31+$U31),0,AU$23>=$R31,$V31) -> 0
B31: 1 | C31: westerial ws2-2000 filter house | D31: =IF(I31="N",F31,0) -> 65000 | F31: 65000 | G31: NC, USA | H31: Germany | I31: =IF('Data Sources'!$C$27="N","N","Y") -> N | J31: 0.5 | K31: 0.4 | L31: 0.1 | M31: 8 | N31: 21 | P31: =SUM($O$11:O31) -> 1 | R31: =R30+1 -> 2032 | S31: 0 | T31: =S31/12 -> 0 | U31: 7 | V31: =S31/U31 -> 0 | W31: =V31/12 -> 0 | Y31: =_xlfn.IFS(Y$23<$R32,0,Y$23>=($R32+$U32),0,Y$23>=$R32,$V32) -> 0 | Z31: =_xlfn.IFS(Z$23<$R32,0,Z$23>=($R32+$U32),0,Z$23>=$R32,$V32) -> 0 | AA31: =_xlfn.IFS(AA$23<$R32,0,AA$23>=($R32+$U32),0,AA$23>=$R32,$V32) -> 0 | AB31: =_xlfn.IFS(AB$23<$R32,0,AB$23>=($R32+$U32),0,AB$23>=$R32,$V32) -> 0 | AC31: =_xlfn.IFS(AC$23<$R32,0,AC$23>=($R32+$U32),0,AC$23>=$R32,$V32) -> 0 | AD31: =_xlfn.IFS(AD$23<$R32,0,AD$23>=($R32+$U32),0,AD$23>=$R32,$V32) -> 0 | AE31: =_xlfn.IFS(AE$23<$R32,0,AE$23>=($R32+$U32),0,AE$23>=$R32,$V32) -> 0 | AF31: =_xlfn.IFS(AF$23<$R32,0,AF$23>=($R32+$U32),0,AF$23>=$R32,$V32) -> 142857.14 | ... AU31: =_xlfn.IFS(AU$23<$R32,0,AU$23>=($R32+$U32),0,AU$23>=$R32,$V32) -> 0
B32: 1 | C32: westeria flatcon 1800-28500 | D32: =IF(I32="N",F32,0) -> 95123.75 | F32: 95123.75 | G32: NC, USA | H32: Germany | I32: =IF('Data Sources'!$C$27="N","N","Y") -> N | J32: 0.5 | K32: 0.4 | L32: 0.1 | M32: 8 | N32: 22 | P32: =SUM($O$11:O32) -> 1 | R32: =R31+1 -> 2033 | S32: 1000000 | T32: =S32/12 -> 83333.333 | U32: 7 | V32: =S32/U32 -> 142857.14 | W32: =V32/12 -> 11904.762 | Y32: =_xlfn.IFS(Y$23<$R33,0,Y$23>=($R33+$U33),0,Y$23>=$R33,$V33) -> 0 | Z32: =_xlfn.IFS(Z$23<$R33,0,Z$23>=($R33+$U33),0,Z$23>=$R33,$V33) -> 0 | AA32: =_xlfn.IFS(AA$23<$R33,0,AA$23>=($R33+$U33),0,AA$23>=$R33,$V33) -> 0 | AB32: =_xlfn.IFS(AB$23<$R33,0,AB$23>=($R33+$U33),0,AB$23>=$R33,$V33) -> 0 | AC32: =_xlfn.IFS(AC$23<$R33,0,AC$23>=($R33+$U33),0,AC$23>=$R33,$V33) -> 0 | AD32: =_xlfn.IFS(AD$23<$R33,0,AD$23>=($R33+$U33),0,AD$23>=$R33,$V33) -> 0 | AE32: =_xlfn.IFS(AE$23<$R33,0,AE$23>=($R33+$U33),0,AE$23>=$R33,$V33) -> 0 | AF32: =_xlfn.IFS(AF$23<$R33,0,AF$23>=($R33+$U33),0,AF$23>=$R33,$V33) -> 0 | ... AU32: =_xlfn.IFS(AU$23<$R33,0,AU$23>=($R33+$U33),0,AU$23>=$R33,$V33) -> 0
B33: 1 | C33: Position 16 Main Fraction Optical Sorting | D33: =IF(I33="N",F33,0) -> 905560.6 | F33: 905560.6 | G33: NC, USA | H33: Germany | I33: =IF('Data Sources'!$C$27="N","N","Y") -> N | J33: 0.5 | K33: 0.4 | L33: 0.1 | M33: 8 | N33: 23 | P33: =SUM($O$11:O33) -> 1 | R33: =R32+1 -> 2034 | S33: 1000000 | T33: =S33/12 -> 83333.333 | U33: 7 | V33: =S33/U33 -> 142857.14 | W33: =V33/12 -> 11904.762 | Y33: =_xlfn.IFS(Y$23<$R34,0,Y$23>=($R34+$U34),0,Y$23>=$R34,$V34) -> 0 | Z33: =_xlfn.IFS(Z$23<$R34,0,Z$23>=($R34+$U34),0,Z$23>=$R34,$V34) -> 0 | AA33: =_xlfn.IFS(AA$23<$R34,0,AA$23>=($R34+$U34),0,AA$23>=$R34,$V34) -> 0 | AB33: =_xlfn.IFS(AB$23<$R34,0,AB$23>=($R34+$U34),0,AB$23>=$R34,$V34) -> 0 | AC33: =_xlfn.IFS(AC$23<$R34,0,AC$23>=($R34+$U34),0,AC$23>=$R34,$V34) -> 0 | AD33: =_xlfn.IFS(AD$23<$R34,0,AD$23>=($R34+$U34),0,AD$23>=$R34,$V34) -> 0 | AE33: =_xlfn.IFS(AE$23<$R34,0,AE$23>=($R34+$U34),0,AE$23>=$R34,$V34) -> 0 | AF33: =_xlfn.IFS(AF$23<$R34,0,AF$23>=($R34+$U34),0,AF$23>=$R34,$V34) -> 0 | ... AU33: =_xlfn.IFS(AU$23<$R34,0,AU$23>=($R34+$U34),0,AU$23>=$R34,$V34) -> 0
B34: 1 | C34: westeria flatcon 1200-18500 | D34: =IF(I34="N",F34,0) -> 111297.75 | F34: 111297.75 | G34: NC, USA | H34: Germany | I34: =IF('Data Sources'!$C$27="N","N","Y") -> N | J34: 0.5 | K34: 0.4 | L34: 0.1 | M34: 8 | N34: 24 | P34: =SUM($O$11:O34) -> 1 | R34: =R33+1 -> 2035 | S34: 1000000 | T34: =S34/12 -> 83333.333 | U34: 7 | V34: =S34/U34 -> 142857.14 | W34: =V34/12 -> 11904.762 | Y34: =_xlfn.IFS(Y$23<$R35,0,Y$23>=($R35+$U35),0,Y$23>=$R35,$V35) -> 0 | Z34: =_xlfn.IFS(Z$23<$R35,0,Z$23>=($R35+$U35),0,Z$23>=$R35,$V35) -> 0 | AA34: =_xlfn.IFS(AA$23<$R35,0,AA$23>=($R35+$U35),0,AA$23>=$R35,$V35) -> 0 | AB34: =_xlfn.IFS(AB$23<$R35,0,AB$23>=($R35+$U35),0,AB$23>=$R35,$V35) -> 0 | AC34: =_xlfn.IFS(AC$23<$R35,0,AC$23>=($R35+$U35),0,AC$23>=$R35,$V35) -> 0 | AD34: =_xlfn.IFS(AD$23<$R35,0,AD$23>=($R35+$U35),0,AD$23>=$R35,$V35) -> 0 | AE34: =_xlfn.IFS(AE$23<$R35,0,AE$23>=($R35+$U35),0,AE$23>=$R35,$V35) -> 0 | AF34: =_xlfn.IFS(AF$23<$R35,0,AF$23>=($R35+$U35),0,AF$23>=$R35,$V35) -> 0 | ... AU34: =_xlfn.IFS(AU$23<$R35,0,AU$23>=($R35+$U35),0,AU$23>=$R35,$V35) -> 0
B35: 1 | C35: Position 18 Metso ETA 3550 shredders | D35: =IF(I35="N",F35,0) -> 1059553.6 | F35: 1059553.6 | G35: NC, USA | H35: Germany | I35: =IF('Data Sources'!$C$27="N","N","Y") -> N | J35: 0.5 | K35: 0.4 | L35: 0.1 | M35: 8 | R35: =R34+1 -> 2036 | S35: 1000000 | T35: =S35/12 -> 83333.333 | U35: 7 | V35: =S35/U35 -> 142857.14 | W35: =V35/12 -> 11904.762 | Y35: =_xlfn.IFS(Y$23<$R36,0,Y$23>=($R36+$U36),0,Y$23>=$R36,$V36) -> 0 | Z35: =_xlfn.IFS(Z$23<$R36,0,Z$23>=($R36+$U36),0,Z$23>=$R36,$V36) -> 0 | AA35: =_xlfn.IFS(AA$23<$R36,0,AA$23>=($R36+$U36),0,AA$23>=$R36,$V36) -> 0 | AB35: =_xlfn.IFS(AB$23<$R36,0,AB$23>=($R36+$U36),0,AB$23>=$R36,$V36) -> 0 | AC35: =_xlfn.IFS(AC$23<$R36,0,AC$23>=($R36+$U36),0,AC$23>=$R36,$V36) -> 0 | AD35: =_xlfn.IFS(AD$23<$R36,0,AD$23>=($R36+$U36),0,AD$23>=$R36,$V36) -> 0 | AE35: =_xlfn.IFS(AE$23<$R36,0,AE$23>=($R36+$U36),0,AE$23>=$R36,$V36) -> 0 | AF35: =_xlfn.IFS(AF$23<$R36,0,AF$23>=($R36+$U36),0,AF$23>=$R36,$V36) -> 0 | ... AU35: =_xlfn.IFS(AU$23<$R36,0,AU$23>=($R36+$U36),0,AU$23>=$R36,$V36) -> 0
B36: 1 | C36: 20ft container for power pack | D36: =IF(I36="N",F36,0) -> 46244.25 | F36: 46244.25 | G36: NC, USA | H36: Germany | I36: =IF('Data Sources'!$C$27="N","N","Y") -> N | J36: 0.5 | K36: 0.4 | L36: 0.1 | M36: 8 | R36: =R35+1 -> 2037 | S36: 1000000 | T36: =S36/12 -> 83333.333 | U36: 7 | V36: =S36/U36 -> 142857.14 | W36: =V36/12 -> 11904.762 | Y36: =_xlfn.IFS(Y$23<$R37,0,Y$23>=($R37+$U37),0,Y$23>=$R37,$V37) -> 0 | Z36: =_xlfn.IFS(Z$23<$R37,0,Z$23>=($R37+$U37),0,Z$23>=$R37,$V37) -> 0 | AA36: =_xlfn.IFS(AA$23<$R37,0,AA$23>=($R37+$U37),0,AA$23>=$R37,$V37) -> 0 | AB36: =_xlfn.IFS(AB$23<$R37,0,AB$23>=($R37+$U37),0,AB$23>=$R37,$V37) -> 0 | AC36: =_xlfn.IFS(AC$23<$R37,0,AC$23>=($R37+$U37),0,AC$23>=$R37,$V37) -> 0 | AD36: =_xlfn.IFS(AD$23<$R37,0,AD$23>=($R37+$U37),0,AD$23>=$R37,$V37) -> 0 | AE36: =_xlfn.IFS(AE$23<$R37,0,AE$23>=($R37+$U37),0,AE$23>=$R37,$V37) -> 0 | AF36: =_xlfn.IFS(AF$23<$R37,0,AF$23>=($R37+$U37),0,AF$23>=$R37,$V37) -> 0 | ... AU36: =_xlfn.IFS(AU$23<$R37,0,AU$23>=($R37+$U37),0,AU$23>=$R37,$V37) -> 0
B37: 1 | C37: Position 19 discharge conveyors and bunker | D37: =IF(I37="N",F37,0) -> 274394.95 | F37: 274394.95 | G37: NC, USA | H37: Germany | I37: =IF('Data Sources'!$C$27="N","N","Y") -> N | J37: 0.5 | K37: 0.4 | L37: 0.1 | M37: 8 | R37: =R36+1 -> 2038 | S37: 1000000 | T37: =S37/12 -> 83333.333 | U37: 7 | V37: =S37/U37 -> 142857.14 | W37: =V37/12 -> 11904.762 | Y37: =_xlfn.IFS(Y$23<$R38,0,Y$23>=($R38+$U38),0,Y$23>=$R38,$V38) -> 0 | Z37: =_xlfn.IFS(Z$23<$R38,0,Z$23>=($R38+$U38),0,Z$23>=$R38,$V38) -> 0 | AA37: =_xlfn.IFS(AA$23<$R38,0,AA$23>=($R38+$U38),0,AA$23>=$R38,$V38) -> 0 | AB37: =_xlfn.IFS(AB$23<$R38,0,AB$23>=($R38+$U38),0,AB$23>=$R38,$V38) -> 0 | AC37: =_xlfn.IFS(AC$23<$R38,0,AC$23>=($R38+$U38),0,AC$23>=$R38,$V38) -> 0 | AD37: =_xlfn.IFS(AD$23<$R38,0,AD$23>=($R38+$U38),0,AD$23>=$R38,$V38) -> 0 | AE37: =_xlfn.IFS(AE$23<$R38,0,AE$23>=($R38+$U38),0,AE$23>=$R38,$V38) -> 0 | AF37: =_xlfn.IFS(AF$23<$R38,0,AF$23>=($R38+$U38),0,AF$23>=$R38,$V38) -> 0 | ... AU37: =_xlfn.IFS(AU$23<$R38,0,AU$23>=($R38+$U38),0,AU$23>=$R38,$V38) -> 0
B38: 1 | C38: Position 20 Discharge conveyors | D38: =IF(I38="N",F38,0) -> 184247.59 | F38: 184247.59 | G38: NC, USA | H38: Germany | I38: =IF('Data Sources'!$C$27="N","N","Y") -> N | J38: 0.5 | K38: 0.4 | L38: 0.1 | M38: 8 | R38: =R37+1 -> 2039 | S38: 1000000 | T38: =S38/12 -> 83333.333 | U38: 7 | V38: =S38/U38 -> 142857.14 | W38: =V38/12 -> 11904.762 | Y38: =_xlfn.IFS(Y$23<$R39,0,Y$23>=($R39+$U39),0,Y$23>=$R39,$V39) -> 0 | Z38: =_xlfn.IFS(Z$23<$R39,0,Z$23>=($R39+$U39),0,Z$23>=$R39,$V39) -> 0 | AA38: =_xlfn.IFS(AA$23<$R39,0,AA$23>=($R39+$U39),0,AA$23>=$R39,$V39) -> 0 | AB38: =_xlfn.IFS(AB$23<$R39,0,AB$23>=($R39+$U39),0,AB$23>=$R39,$V39) -> 0 | AC38: =_xlfn.IFS(AC$23<$R39,0,AC$23>=($R39+$U39),0,AC$23>=$R39,$V39) -> 0 | AD38: =_xlfn.IFS(AD$23<$R39,0,AD$23>=($R39+$U39),0,AD$23>=$R39,$V39) -> 0 | AE38: =_xlfn.IFS(AE$23<$R39,0,AE$23>=($R39+$U39),0,AE$23>=$R39,$V39) -> 0 | AF38: =_xlfn.IFS(AF$23<$R39,0,AF$23>=($R39+$U39),0,AF$23>=$R39,$V39) -> 0 | ... AU38: =_xlfn.IFS(AU$23<$R39,0,AU$23>=($R39+$U39),0,AU$23>=$R39,$V39) -> 0
B39: 1 | C39: Position 21 Chutes, steel work and control panel | D39: =IF(I39="N",F39,0) -> 942762.5 | F39: 942762.5 | G39: NC, USA | H39: Germany | I39: =IF('Data Sources'!$C$27="N","N","Y") -> N | J39: 0.5 | K39: 0.4 | L39: 0.1 | M39: 8 | R39: =R38+1 -> 2040 | S39: 1000000 | T39: =S39/12 -> 83333.333 | U39: 7 | V39: =S39/U39 -> 142857.14 | W39: =V39/12 -> 11904.762 | Y39: =_xlfn.IFS(Y$23<$R40,0,Y$23>=($R40+$U40),0,Y$23>=$R40,$V40) -> 0 | Z39: =_xlfn.IFS(Z$23<$R40,0,Z$23>=($R40+$U40),0,Z$23>=$R40,$V40) -> 0 | AA39: =_xlfn.IFS(AA$23<$R40,0,AA$23>=($R40+$U40),0,AA$23>=$R40,$V40) -> 0 | AB39: =_xlfn.IFS(AB$23<$R40,0,AB$23>=($R40+$U40),0,AB$23>=$R40,$V40) -> 0 | AC39: =_xlfn.IFS(AC$23<$R40,0,AC$23>=($R40+$U40),0,AC$23>=$R40,$V40) -> 0 | AD39: =_xlfn.IFS(AD$23<$R40,0,AD$23>=($R40+$U40),0,AD$23>=$R40,$V40) -> 0 | AE39: =_xlfn.IFS(AE$23<$R40,0,AE$23>=($R40+$U40),0,AE$23>=$R40,$V40) -> 0 | AF39: =_xlfn.IFS(AF$23<$R40,0,AF$23>=($R40+$U40),0,AF$23>=$R40,$V40) -> 0 | ... AU39: =_xlfn.IFS(AU$23<$R40,0,AU$23>=($R40+$U40),0,AU$23>=$R40,$V40) -> 0
B40: 1 | C40: Position 22 shipping | D40: =IF(I40="N",F40,0) -> 400625 | F40: 400625 | G40: NC, USA | H40: Germany | I40: =IF('Data Sources'!$C$27="N","N","Y") -> N | J40: 0.5 | K40: 0.4 | L40: 0.1 | M40: 8 | R40: =R39+1 -> 2041 | S40: 1000000 | T40: =S40/12 -> 83333.333 | U40: 7 | V40: =S40/U40 -> 142857.14 | W40: =V40/12 -> 11904.762 | Y40: =_xlfn.IFS(Y$23<$R41,0,Y$23>=($R41+$U41),0,Y$23>=$R41,$V41) -> 0 | Z40: =_xlfn.IFS(Z$23<$R41,0,Z$23>=($R41+$U41),0,Z$23>=$R41,$V41) -> 0 | AA40: =_xlfn.IFS(AA$23<$R41,0,AA$23>=($R41+$U41),0,AA$23>=$R41,$V41) -> 0 | AB40: =_xlfn.IFS(AB$23<$R41,0,AB$23>=($R41+$U41),0,AB$23>=$R41,$V41) -> 0 | AC40: =_xlfn.IFS(AC$23<$R41,0,AC$23>=($R41+$U41),0,AC$23>=$R41,$V41) -> 0 | AD40: =_xlfn.IFS(AD$23<$R41,0,AD$23>=($R41+$U41),0,AD$23>=$R41,$V41) -> 0 | AE40: =_xlfn.IFS(AE$23<$R41,0,AE$23>=($R41+$U41),0,AE$23>=$R41,$V41) -> 0 | AF40: =_xlfn.IFS(AF$23<$R41,0,AF$23>=($R41+$U41),0,AF$23>=$R41,$V41) -> 0 | ... AU40: =_xlfn.IFS(AU$23<$R41,0,AU$23>=($R41+$U41),0,AU$23>=$R41,$V41) -> 142857.14
B41: 1 | C41: westeria engineering and project support | D41: =IF(I41="N",F41,0) -> 112500 | F41: 112500 | G41: NC, USA | H41: Germany | I41: =IF('Data Sources'!$C$27="N","N","Y") -> N | J41: 0.5 | K41: 0.4 | L41: 0.1 | M41: 8 | R41: =R40+1 -> 2042 | S41: 1000000 | T41: =S41/12 -> 83333.333 | U41: 7 | V41: =S41/U41 -> 142857.14 | W41: =V41/12 -> 11904.762 | Y41: =_xlfn.IFS(Y$23<$R42,0,Y$23>=($R42+$U42),0,Y$23>=$R42,$V42) -> 0 | Z41: =_xlfn.IFS(Z$23<$R42,0,Z$23>=($R42+$U42),0,Z$23>=$R42,$V42) -> 0 | AA41: =_xlfn.IFS(AA$23<$R42,0,AA$23>=($R42+$U42),0,AA$23>=$R42,$V42) -> 0 | AB41: =_xlfn.IFS(AB$23<$R42,0,AB$23>=($R42+$U42),0,AB$23>=$R42,$V42) -> 0 | AC41: =_xlfn.IFS(AC$23<$R42,0,AC$23>=($R42+$U42),0,AC$23>=$R42,$V42) -> 0 | AD41: =_xlfn.IFS(AD$23<$R42,0,AD$23>=($R42+$U42),0,AD$23>=$R42,$V42) -> 0 | AE41: =_xlfn.IFS(AE$23<$R42,0,AE$23>=($R42+$U42),0,AE$23>=$R42,$V42) -> 0 | AF41: =_xlfn.IFS(AF$23<$R42,0,AF$23>=($R42+$U42),0,AF$23>=$R42,$V42) -> 0 | ... AU41: =_xlfn.IFS(AU$23<$R42,0,AU$23>=($R42+$U42),0,AU$23>=$R42,$V42) -> 142857.14
B42: 1 | C42: Mechanical and Electrical installation | D42: =IF(I42="N",F42,0) -> 725000 | F42: 725000 | G42: NC, USA | H42: Germany | I42: =IF('Data Sources'!$C$27="N","N","Y") -> N | J42: 0.5 | K42: 0.4 | L42: 0.1 | M42: 8 | R42: =R41+1 -> 2043 | S42: 1000000 | T42: =S42/12 -> 83333.333 | U42: 7 | V42: =S42/U42 -> 142857.14 | W42: =V42/12 -> 11904.762 | Y42: =_xlfn.IFS(Y$23<$R43,0,Y$23>=($R43+$U43),0,Y$23>=$R43,$V43) -> 0 | Z42: =_xlfn.IFS(Z$23<$R43,0,Z$23>=($R43+$U43),0,Z$23>=$R43,$V43) -> 0 | AA42: =_xlfn.IFS(AA$23<$R43,0,AA$23>=($R43+$U43),0,AA$23>=$R43,$V43) -> 0 | AB42: =_xlfn.IFS(AB$23<$R43,0,AB$23>=($R43+$U43),0,AB$23>=$R43,$V43) -> 0 | AC42: =_xlfn.IFS(AC$23<$R43,0,AC$23>=($R43+$U43),0,AC$23>=$R43,$V43) -> 0 | AD42: =_xlfn.IFS(AD$23<$R43,0,AD$23>=($R43+$U43),0,AD$23>=$R43,$V43) -> 0 | AE42: =_xlfn.IFS(AE$23<$R43,0,AE$23>=($R43+$U43),0,AE$23>=$R43,$V43) -> 0 | AF42: =_xlfn.IFS(AF$23<$R43,0,AF$23>=($R43+$U43),0,AF$23>=$R43,$V43) -> 0 | ... AU42: =_xlfn.IFS(AU$23<$R43,0,AU$23>=($R43+$U43),0,AU$23>=$R43,$V43) -> 142857.14
B43: 1 | C43: Final set up and training | D43: =IF(I43="N",F43,0) -> 206250 | F43: 206250 | G43: NC, USA | H43: Germany | I43: =IF('Data Sources'!$C$27="N","N","Y") -> N | J43: 0.5 | K43: 0.4 | L43: 0.1 | M43: 8 | R43: =R42+1 -> 2044 | S43: 1000000 | T43: =S43/12 -> 83333.333 | U43: 7 | V43: =S43/U43 -> 142857.14 | W43: =V43/12 -> 11904.762 | Y43: =_xlfn.IFS(Y$23<$R44,0,Y$23>=($R44+$U44),0,Y$23>=$R44,$V44) -> 0 | Z43: =_xlfn.IFS(Z$23<$R44,0,Z$23>=($R44+$U44),0,Z$23>=$R44,$V44) -> 0 | AA43: =_xlfn.IFS(AA$23<$R44,0,AA$23>=($R44+$U44),0,AA$23>=$R44,$V44) -> 0 | AB43: =_xlfn.IFS(AB$23<$R44,0,AB$23>=($R44+$U44),0,AB$23>=$R44,$V44) -> 0 | AC43: =_xlfn.IFS(AC$23<$R44,0,AC$23>=($R44+$U44),0,AC$23>=$R44,$V44) -> 0 | AD43: =_xlfn.IFS(AD$23<$R44,0,AD$23>=($R44+$U44),0,AD$23>=$R44,$V44) -> 0 | AE43: =_xlfn.IFS(AE$23<$R44,0,AE$23>=($R44+$U44),0,AE$23>=$R44,$V44) -> 0 | AF43: =_xlfn.IFS(AF$23<$R44,0,AF$23>=($R44+$U44),0,AF$23>=$R44,$V44) -> 0 | ... AU43: =_xlfn.IFS(AU$23<$R44,0,AU$23>=($R44+$U44),0,AU$23>=$R44,$V44) -> 142857.14
B44: 1 | C44: Piping and discharge handling | D44: =IF(I44="N",F44,0) -> 1400000 | F44: 1400000 | G44: NC, USA | H44: Germany | I44: =IF('Data Sources'!$C$27="N","N","Y") -> N | J44: 0.5 | K44: 0.4 | L44: 0.1 | M44: 8 | R44: =R43+1 -> 2045 | S44: 1000000 | T44: =S44/12 -> 83333.333 | U44: 7 | V44: =S44/U44 -> 142857.14 | W44: =V44/12 -> 11904.762 | Y44: =_xlfn.IFS(Y$23<$R45,0,Y$23>=($R45+$U45),0,Y$23>=$R45,$V45) -> 0 | Z44: =_xlfn.IFS(Z$23<$R45,0,Z$23>=($R45+$U45),0,Z$23>=$R45,$V45) -> 0 | AA44: =_xlfn.IFS(AA$23<$R45,0,AA$23>=($R45+$U45),0,AA$23>=$R45,$V45) -> 0 | AB44: =_xlfn.IFS(AB$23<$R45,0,AB$23>=($R45+$U45),0,AB$23>=$R45,$V45) -> 0 | AC44: =_xlfn.IFS(AC$23<$R45,0,AC$23>=($R45+$U45),0,AC$23>=$R45,$V45) -> 0 | AD44: =_xlfn.IFS(AD$23<$R45,0,AD$23>=($R45+$U45),0,AD$23>=$R45,$V45) -> 0 | AE44: =_xlfn.IFS(AE$23<$R45,0,AE$23>=($R45+$U45),0,AE$23>=$R45,$V45) -> 0 | AF44: =_xlfn.IFS(AF$23<$R45,0,AF$23>=($R45+$U45),0,AF$23>=$R45,$V45) -> 0 | ... AU44: =_xlfn.IFS(AU$23<$R45,0,AU$23>=($R45+$U45),0,AU$23>=$R45,$V45) -> 142857.14
B45: 1 | C45: Fluidized Bed Ventalex Drying System | D45: =IF(I45="N",F45,0) -> 1148000 | F45: 1148000 | G45: Finland | H45: Holland | I45: =IF('Data Sources'!$C$27="N","N","Y") -> N | J45: 0.5 | K45: 0.4 | L45: 0.1 | M45: 8 | R45: =R44+1 -> 2046 | S45: 1000000 | T45: =S45/12 -> 83333.333 | U45: 7 | V45: =S45/U45 -> 142857.14 | W45: =V45/12 -> 11904.762 | Y45: =_xlfn.IFS(Y$23<$R46,0,Y$23>=($R46+$U46),0,Y$23>=$R46,$V46) -> 0 | Z45: =_xlfn.IFS(Z$23<$R46,0,Z$23>=($R46+$U46),0,Z$23>=$R46,$V46) -> 0 | AA45: =_xlfn.IFS(AA$23<$R46,0,AA$23>=($R46+$U46),0,AA$23>=$R46,$V46) -> 0 | AB45: =_xlfn.IFS(AB$23<$R46,0,AB$23>=($R46+$U46),0,AB$23>=$R46,$V46) -> 0 | AC45: =_xlfn.IFS(AC$23<$R46,0,AC$23>=($R46+$U46),0,AC$23>=$R46,$V46) -> 0 | AD45: =_xlfn.IFS(AD$23<$R46,0,AD$23>=($R46+$U46),0,AD$23>=$R46,$V46) -> 0 | AE45: =_xlfn.IFS(AE$23<$R46,0,AE$23>=($R46+$U46),0,AE$23>=$R46,$V46) -> 0 | AF45: =_xlfn.IFS(AF$23<$R46,0,AF$23>=($R46+$U46),0,AF$23>=$R46,$V46) -> 0 | ... AU45: =_xlfn.IFS(AU$23<$R46,0,AU$23>=($R46+$U46),0,AU$23>=$R46,$V46) -> 142857.14
B46: 2 | C46: ARTI-48T | D46: =IF(I46="Y",F46,0) -> 6200000 | F46: 6200000 | G46: CA, USA | H46: TX, USA | I46: Y | J46: 0.5 | K46: 0.4 | L46: 0.1 | M46: 9 | R46: =R45+1 -> 2047 | S46: 1000000 | T46: =S46/12 -> 83333.333 | U46: 7 | V46: =S46/U46 -> 142857.14 | W46: =V46/12 -> 11904.762 | Y46: =_xlfn.IFS(Y$23<$R47,0,Y$23>=($R47+$U47),0,Y$23>=$R47,$V47) -> 0 | Z46: =_xlfn.IFS(Z$23<$R47,0,Z$23>=($R47+$U47),0,Z$23>=$R47,$V47) -> 0 | AA46: =_xlfn.IFS(AA$23<$R47,0,AA$23>=($R47+$U47),0,AA$23>=$R47,$V47) -> 0 | AB46: =_xlfn.IFS(AB$23<$R47,0,AB$23>=($R47+$U47),0,AB$23>=$R47,$V47) -> 0 | AC46: =_xlfn.IFS(AC$23<$R47,0,AC$23>=($R47+$U47),0,AC$23>=$R47,$V47) -> 0 | AD46: =_xlfn.IFS(AD$23<$R47,0,AD$23>=($R47+$U47),0,AD$23>=$R47,$V47) -> 0 | AE46: =_xlfn.IFS(AE$23<$R47,0,AE$23>=($R47+$U47),0,AE$23>=$R47,$V47) -> 0 | AF46: =_xlfn.IFS(AF$23<$R47,0,AF$23>=($R47+$U47),0,AF$23>=$R47,$V47) -> 0 | ... AU46: =_xlfn.IFS(AU$23<$R47,0,AU$23>=($R47+$U47),0,AU$23>=$R47,$V47) -> 142857.14
B47: 2 | C47: ARTI-48T | D47: =IF(I47="Y",F47,0) -> 6200000 | F47: 6200000 | G47: CA, USA | H47: TX, USA | I47: Y | J47: 0.5 | K47: 0.4 | L47: 0.1 | M47: 9 | R47: =R46+1 -> 2048 | S47: 1000000 | T47: =S47/12 -> 83333.333 | U47: 7 | V47: =S47/U47 -> 142857.14 | W47: =V47/12 -> 11904.762 | Y47: =SUM(Y24:Y46) -> 0 | Z47: =SUM(Z24:Z46) -> 0 | AA47: =SUM(AA24:AA46) -> 0 | AB47: =SUM(AB24:AB46) -> 0 | AC47: =SUM(AC24:AC46) -> 0 | AD47: =SUM(AD24:AD46) -> 0 | AE47: =SUM(AE24:AE46) -> 0 | AF47: =SUM(AF24:AF46) -> 142857.14 | ... AU47: =SUM(AU24:AU46) -> 1000000
B48: 2 | C48: ARTI-48T | D48: =IF(I48="Y",F48,0) -> 6200000 | F48: 6200000 | G48: CA, USA | H48: TX, USA | I48: Y | J48: 0.5 | K48: 0.4 | L48: 0.1 | M48: 9
B49: 2 | C49: ARTI-48T | D49: =IF(I49="Y",F49,0) -> 0 | F49: 6200000 | G49: CA, USA | H49: TX, USA | I49: N | J49: 0.5 | K49: 0.4 | L49: 0.1 | M49: 9
B50: 2 | C50: ARTI-48RDF | D50: =IF(I50="Y",F50,0) -> 6200000 | F50: 6200000 | G50: CA, USA | H50: TX, USA | I50: Y | J50: 0.5 | K50: 0.4 | L50: 0.1 | M50: 9
B51: 2 | C51: ATRI-48RDF | D51: =IF(I51="Y",F51,0) -> 6200000 | F51: 6200000 | G51: CA, USA | H51: TX, USA | I51: Y | J51: 0.5 | K51: 0.4 | L51: 0.1 | M51: 9
B52: 2 | C52: ARTI-48RDF | D52: =IF(I52="Y",F52,0) -> 6200000 | F52: 6200000 | G52: CA, USA | H52: TX, USA | I52: Y | J52: 0.5 | K52: 0.4 | L52: 0.1 | M52: 9
B53: 2 | C53: ARTI-48RDF | D53: =IF(I53="Y",F53,0) -> 6200000 | F53: 6200000 | G53: CA, USA | H53: TX, USA | I53: Y | J53: 0.5 | K53: 0.4 | L53: 0.1 | M53: 9
B54: 2 | C54: ARTI-48RDF | D54: =IF(I54="Y",F54,0) -> 6200000 | F54: 6200000 | G54: CA, USA | H54: TX, USA | I54: Y | J54: 0.5 | K54: 0.4 | L54: 0.1 | M54: 9
B55: 2 | C55: ARTI-48RDF | D55: =IF(I55="Y",F55,0) -> 6200000 | F55: 6200000 | G55: CA, USA | H55: TX, USA | I55: Y | J55: 0.5 | K55: 0.4 | L55: 0.1 | M55: 9
B56: 2 | C56: ARTI-48RDF | D56: =IF(I56="Y",F56,0) -> 6200000 | F56: 6200000 | G56: CA, USA | H56: TX, USA | I56: Y | J56: 0.5 | K56: 0.4 | L56: 0.1 | M56: 9
B57: 2 | C57: ARTI-48RDF | D57: =IF(I57="Y",F57,0) -> 6200000 | F57: 6200000 | G57: CA, USA | H57: TX, USA | I57: Y | J57: 0.5 | K57: 0.4 | L57: 0.1 | M57: 9
B58: 2 | C58: ARTI-48RDF | D58: =IF(I58="Y",F58,0) -> 6200000 | F58: 6200000 | G58: CA, USA | H58: TX, USA | I58: Y | J58: 0.5 | K58: 0.4 | L58: 0.1 | M58: 9
B59: 2 | C59: ARTI-48RDF | D59: =IF(I59="Y",F59,0) -> 6200000 | F59: 6200000 | G59: CA, USA | H59: TX, USA | I59: Y | J59: 0.5 | K59: 0.4 | L59: 0.1 | M59: 9
B60: 2 | C60: ARTI-48RDF | D60: =IF(I60="Y",F60,0) -> 0 | F60: 0 | G60: CA, USA | H60: TX, USA | I60: =IF('Data Sources'!$C$27="N","N","Y") -> N | J60: 0.5 | K60: 0.4 | L60: 0.1 | M60: 9
B61: 2 | C61: Safety flair | D61: =IF(I61="Y",F61,0) -> 0 | E61: No but this is a minimal cost. Captured in Installation % 4 flairs utilized for safety | F61: 0 | G61: CA, USA | H61: TX, USA | I61: Y | J61: 0.5 | K61: 0.4 | L61: 0.1 | M61: 9
B62: 2 | C62: Syngas storage | D62: =IF(I62="Y",F62,0) -> 0 | E62: No. Once tank sized and pressure between ARTI and Solar for the tank is agreed to then price will be determined. Cost is part of installation % at bottom. gas storage for 4 hours of run time on 1 titan 130 turbine | F62: 0 | G62: CA, USA | H62: NM, USA | I62: Y | J62: 0.5 | K62: 0.4 | L62: 0.1 | M62: 5
B63: 2 | C63: oil tank | D63: =IF(I63="Y",F63,0) -> 0 | E63: No. Cost is part of installation % at bottom. In this instance we are discussing if should just utilize a tanker truck on site or a permanent tank sized at 7000 gal a day | F63: 0 | G63: CA, USA | H63: NM, USA | I63: Y | J63: 0.5 | K63: 0.4 | L63: 0.1 | M63: 5
B64: 2 | C64: Pyrolysis water cleanup skid | D64: =IF(I64="Y",F64,0) -> 0 | E64: No. Cost is part of installation % at bottom. RO to clean up water created in pyrolysis process | F64: 0 | G64: CA, USA | H64: TX, USA | I64: Y | J64: 0.5 | K64: 0.4 | L64: 0.1 | M64: 5
B65: 3 | C65: Fuel Tanks | D65: =IF(I65="Y",F65,0) -> 500000 | F65: 500000 | G65: CA, USA | H65: TX, USA | I65: Y | J65: 0.5 | K65: 0.4 | L65: 0.1 | M65: 5
B66: 3 | C66: RNG Fuel cleanup skids | D66: =IF(I66="Y",F66,0) -> 0 | E66: if focus on oil production | F66: 0 | G66: CA, USA | H66: TX, USA | I66: Y | J66: 0.5 | K66: 0.4 | L66: 0.1 | M66: 8
B67: 3 | C67: Compressors | D67: =IF(I67="Y",F67,0) -> 2063400 | F67: 2063400 | G67: UK | H67: UK | I67: Y | J67: 0.5 | K67: 0.4 | L67: 0.1 | M67: 11
B68: 3 | C68: commissioning and test | D68: =IF(I68="Y",F68,0) -> 305400 | F68: 305400 | G68: UK | H68: UK | I68: Y | J68: 0.5 | K68: 0.4 | L68: 0.1 | M68: 8 | N68: RNG Cost Estimate
B69: 3 | C69: Solar T70 startup turbine (7.9 MWh) | D69: 0 | E69: New price is $5.3M increase of $1.9M was 3.2M | F69: 3200000 | G69: CA, USA | H69: CA, USA | J69: 0.5 | K69: 0.4 | L69: 0.1 | M69: 11
B70: 3 | C70: Siemens STG400 Turbine dual fuel (13 MWH) | D70: 11500000 | G70: UK | H70: UK | J70: 0.2 | K70: 0.7 | L70: 0.1 | M70: 11
B71: 3 | C71: Siemens STG400 Turbine dual fuel (13 MWH) | D71: 11500000 | G71: UK | H71: UK | J71: 0.2 | K71: 0.7 | L71: 0.1 | M71: 11
B72: 3 | C72: Siemens STG400 Turbine dual fuel (13 MWH) | D72: 11500000 | G72: UK | H72: UK | J72: 0.2 | K72: 0.7 | L72: 0.1 | M72: 11
B73: 3 | C73: Solar T70 startup turbine (7.9 MWh) | D73: 0 | J73: 0.5 | K73: 0.4 | L73: 0.1 | M73: 11
B74: 3 | C74: Solar T70 startup turbine (7.9 MWh) | D74: 0 | J74: 0.5 | K74: 0.4 | L74: 0.1 | M74: 11
B75: 3 | C75: Solar Titan 130 (15.8 MW) | D75: 0 | E75: 3/17/2025 updated price went from $6.9M to $11.5M checking On Seimens price | F75: 6900000 | G75: CA, USA | H75: CA, USA | I75: Y | J75: 0.5 | K75: 0.4 | L75: 0.1 | M75: 11 | N75: Clean Up Skid | O75: 6000000 | P75: Rough Estimate
B76: 3 | C76: Solar Titan 130 (15.8 MW) | D76: 0 | E76: 3/17/2025 updated price went from $6.9M to $11.5M checking On Seimens price | F76: 6900000 | G76: CA, USA | H76: CA, USA | I76: Y | J76: 0.5 | K76: 0.4 | L76: 0.1 | M76: 11 | N76: Pipeline to connect | O76: 850000 | P76: Rough Estimate
B77: 3 | C77: Switchgear ,MCC, Neutral grounding resister, and bkrs. | D77: =IF(I77="Y",F77,0) -> 1653700 | F77: 1653700 | G77: UK | H77: UK | I77: Y | J77: 0.5 | K77: 0.4 | L77: 0.1 | M77: 11 | N77: Totals | O77: =SUM(O75:O76) -> 6850000
B78: 3 | C78: 10 Mwe Steam Cycle | D78: =IF(I78="Y",F78,0) -> 16000000 | F78: 16000000 | G78: UK | H78: UK | I78: Y | J78: 0.5 | K78: 0.4 | L78: 0.1 | M78: 11
B79: 3 | C79: Step Up Transformer (excluded from their quote) | D79: =IF(I79="Y",F79,0) -> 750000 | F79: 750000 | G79: UK | H79: UK | I79: Y | J79: 0.5 | K79: 0.4 | L79: 0.1 | M79: 11
B80: 3 | C80: emissions cleanup | D80: =IF(I80="Y",F80,0) -> 3000000 | F80: 3000000 | G80: UK | H80: UK | I80: Y | J80: 0.5 | K80: 0.4 | L80: 0.1 | M80: 11 | N80: Graphene Cost Estimate (Will be refined more after lab testing
B81: 3 | C81: Continuous Emission monitoring | D81: =IF(I81="Y",F81,0) -> 166000 | F81: 166000 | G81: USA | H81: USA | I81: Y | J81: 0.5 | K81: 0.4 | L81: 0.1 | M81: 8 | N81: Building | O81: 6000000 | P81: Rough Estimate
B82: 3 | C82: Shipping and install cost | D82: =IF(I82="Y",F82,0) -> 8925000 | F82: 8925000 | G82: UK | H82: UK | I82: Y | J82: 0.5 | K82: 0.4 | L82: 0.1 | M82: 3 | N82: Equipment | O82: 9000000 | P82: Rough Estimate
B83: 3 | C83: Chillers | D83: =IF(I83="Y",F83,0) -> 3000000 | F83: 3000000 | G83: UK | H83: UK | I83: Y | J83: 0.5 | K83: 0.4 | L83: 0.1 | M83: 3 | N83: Totals | O83: =SUM(O81:O82) -> 15000000
B84: 3 | C84: Modular Oil Refinery | D84: 0 | F84: 600000 | G84: CA, USA | H84: CA, USA | I84: Y | J84: 0.5 | K84: 0.4 | L84: 0.1 | M84: 8
B85: 3 | C85: RNG Gas Cleanup Skid | D85: =IF(I85="Y",F85,0) -> 0 | G85: CA, USA | H85: CA, USA | I85: Y | J85: 0.5 | K85: 0.4 | L85: 0.1 | M85: 8 | N85: Equipment Cost per MRF
B86: 3 | C86: Pipeline extension for CIG | D86: =IF(I86="Y",F86,0) -> 0 | G86: CA, USA | H86: CA, USA | I86: Y | J86: 0.5 | K86: 0.4 | L86: 0.1 | M86: 8 | N86: Item | O86: Cost | P86: Description
B87: 3 | C87: Graphene Processing building | D87: =IF('Data Sources'!C24="Y",CapEx!O83, 0) -> 15000000 | G87: CA, USA | H87: CA, USA | I87: Y | J87: 0.5 | K87: 0.4 | L87: 0.1 | M87: 9 | N87: Fuel storage tank | O87: 25000 | P87: Diesel fuel and DEF storage tanks
B88: 4 | C88: Bitcoin Equipment | D88: =F88 -> 0 | F88: 0 | G88: CA, USA | H88: CA, USA | J88: 0.5 | K88: 0.4 | L88: 0.1 | M88: 9
B89: 4 | C89: Skid Steer | D89: =IF(I89="Y",F89,0) -> 50000 | F89: 50000 | G89: India | H89: India | I89: Y | J89: 0.5 | K89: 0.4 | L89: 0.1 | M89: 3 | N89: Freight | O89: 50000 | P89: Transport containers to Djibouti from USA
B90: 4 | C90: Skid Steer | D90: =IF(I90="Y",F90,0) -> 50000 | F90: 50000 | G90: India | H90: India | I90: Y | J90: 0.5 | K90: 0.4 | L90: 0.1 | M90: 8 | N90: Compactor into container | O90: 15000 | P90: hydraulic push to force trash into containers
B91: 4 | C91: Front End Loader / Telehenadler and Container lifts | D91: =IF(I91="Y",F91,0) -> 1500000 | F91: 1500000 | G91: India | H91: India | I91: Y | J91: 0.5 | K91: 0.4 | L91: 0.1 | M91: 8 | N91: cost for all Compactor into container needed | O91: 60692.85 | P91: Assume 4 for a site
B92: 4 | C92: Scale unit | D92: =IF(I92="Y",F92,0) -> 100000 | F92: 100000 | G92: India | H92: India | I92: Y | J92: 0.5 | K92: 0.4 | L92: 0.1 | M92: 8 | N92: Loader for the site | O92: 45000 | P92: Two skid steers to move the trash
B93: 4 | C93: Track crane | D93: =IF(I93="Y",F93,0) -> 380000 | F93: 380000 | G93: India | H93: India | I93: Y | J93: 0.5 | K93: 0.4 | L93: 0.1 | M93: 5 | N93: Trucks to move containers to REP | O93: 125000 | P93: Two truck per site
B94: 4 | C94: Truck | D94: =IF(I94="Y",F94,0) -> 160000 | F94: 160000 | G94: India | H94: India | I94: Y | J94: 0.5 | K94: 0.4 | L94: 0.1 | M94: 3 | N94: Leached aid cleaning RO | O94: 125000 | P94: Placeholder until final quote is received.
B95: 5 | C95: Balance of plant Chiller system | D95: =IF(I95="Y",F95,0) -> 150000 | F95: 150000 | G95: UK | H95: UK | I95: Y | J95: 0.5 | K95: 0.4 | L95: 0.1 | M95: 8 | N95: Portable Office site and building too unload in | O95: 400000 | P95: Trailer to be setup on site as a portable office for the workers
B96: 5 | C96: TDF Storage building | D96: =IF(I96="Y",F96,0) -> 300000 | F96: 300000 | G96: UK | H96: UK | I96: Y | J96: 0.5 | K96: 0.4 | L96: 0.1 | M96: 5 | N96: Totals | O96: =SUM(O87:O95) -> 845692.85
B97: 5 | C97: RDF Storage Building | D97: =IF(I97="N",F97,0) -> 300000 | F97: 300000 | G97: UK | H97: UK | I97: N | J97: 0.5 | K97: 0.4 | L97: 0.1 | M97: 5
B98: 5 | C98: Carbon Ash storage Silo | D98: =IF(I98="N",F98,0) -> 418100 | F98: 418100 | G98: USA | I98: N | J98: 0.5 | K98: 0.4 | L98: 0.1 | M98: 5
B99: 5 | C99: admin building | D99: =IF(I99="Y",F99,0) -> 1200000 | F99: 1200000 | G99: UK | H99: UK | I99: Y | J99: 0.5 | K99: 0.4 | L99: 0.1 | M99: 5
B100: 5 | C100: Workshop parts and storage | D100: =IF(I100="Y",F100,0) -> 300000 | F100: 300000 | G100: UK | H100: UK | I100: Y | J100: 0.5 | K100: 0.4 | L100: 0.1 | M100: 5
...

Sheet Financials Yearly
C2: =Financials!C5 -> 2026 | D2: =SUM(C2+1) -> 2027 | E2: =SUM(D2+1) -> 2028 | F2: =SUM(E2+1) -> 2029 | G2: =SUM(F2+1) -> 2030 | H2: =SUM(G2+1) -> 2031 | I2: =SUM(H2+1) -> 2032 | J2: =SUM(I2+1) -> 2033 | K2: =SUM(J2+1) -> 2034 | ... Y2: =SUM(X2+1) -> 2048
B4: Revenue Commodities
B5: =Financials!B12 -> Income Power | C5: =SUM(Financials!C12:N12) -> 0 | D5: =SUM(Financials!O12:Z12) -> 0 | E5: =SUM(Financials!AA12:AL12) -> 16398976 | F5: =SUM(Financials!AM12:AX12) -> 21765914 | G5: =SUM(Financials!AY12:BJ12) -> 21825546 | H5: =SUM(Financials!BK12:BV12) -> 21765914 | I5: =SUM(Financials!BW12:CH12) -> 21765914 | J5: =SUM(Financials!CI12:CT12) -> 21765914 | K5: =SUM(Financials!CU12:DF12) -> 21765914 | L5: =SUM(Financials!DG12:DR12) -> 21765914 | M5: =SUM(Financials!DS12:ED12) -> 21765914 | N5: =SUM(Financials!EE12:EP12) -> 21765914 | O5: =SUM(Financials!EQ12:FB12) -> 21765914 | P5: =SUM(Financials!FC12:FN12) -> 21765914 | Q5: =SUM(Financials!FO12:FZ12) -> 21765914 | R5: =SUM(Financials!GA12:GL12) -> 21765914 | S5: =SUM(Financials!GM12:GX12) -> 21765914 | T5: =SUM(Financials!GY12:HJ12) -> 21765914 | U5: =SUM(Financials!HK12:HV12) -> 21765914 | V5: =SUM(Financials!HW12:IH12) -> 21765914 | W5: =SUM(Financials!II12:IT12) -> 21765914 | X5: =SUM(Financials!IU12:JF12) -> 21765914 | Y5: =SUM(Financials!JG12:JR12) -> 21765914
B6: =Financials!B13 -> RNG Sale price | C6: =SUM(Financials!C13:N13) -> 0 | D6: =SUM(Financials!O13:Z13) -> 0 | E6: =SUM(Financials!AA13:AL13) -> 0 | F6: =SUM(Financials!AM13:AX13) -> 0 | G6: =SUM(Financials!AY13:BJ13) -> 0 | H6: =SUM(Financials!BK13:BV13) -> 0 | I6: =SUM(Financials!BW13:CH13) -> 0 | J6: =SUM(Financials!CI13:CT13) -> 0 | K6: =SUM(Financials!CU13:DF13) -> 0 | L6: =SUM(Financials!DG13:DR13) -> 0 | M6: =SUM(Financials!DS13:ED13) -> 0 | N6: =SUM(Financials!EE13:EP13) -> 0 | O6: =SUM(Financials!EQ13:FB13) -> 0 | P6: =SUM(Financials!FC13:FN13) -> 0 | Q6: =SUM(Financials!FO13:FZ13) -> 0 | R6: =SUM(Financials!GA13:GL13) -> 0 | S6: =SUM(Financials!GM13:GX13) -> 0 | T6: =SUM(Financials!GY13:HJ13) -> 0 | U6: =SUM(Financials!HK13:HV13) -> 0 | V6: =SUM(Financials!HW13:IH13) -> 0 | W6: =SUM(Financials!II13:IT13) -> 0 | X6: =SUM(Financials!IU13:JF13) -> 0 | Y6: =SUM(Financials!JG13:JR13) -> 0
B7: =Financials!B14 -> Activated Carbon Ash | C7: =SUM(Financials!C14:N14) -> 0 | D7: =SUM(Financials!O14:Z14) -> 11780568 | E7: =SUM(Financials!AA14:AL14) -> 15912447 | F7: =SUM(Financials!AM14:AX14) -> 16233629 | G7: =SUM(Financials!AY14:BJ14) -> 16606326 | H7: =SUM(Financials!BK14:BV14) -> 16895573 | I7: =SUM(Financials!BW14:CH14) -> 17236600 | J7: =SUM(Financials!CI14:CT14) -> 17584509 | K7: =SUM(Financials!CU14:DF14) -> 17939441 | L7: =SUM(Financials!DG14:DR14) -> 18301537 | M7: =SUM(Financials!DS14:ED14) -> 18670942 | N7: =SUM(Financials!EE14:EP14) -> 19047803 | O7: =SUM(Financials!EQ14:FB14) -> 19432271 | P7: =SUM(Financials!FC14:FN14) -> 19824499 | Q7: =SUM(Financials!FO14:FZ14) -> 20224643 | R7: =SUM(Financials!GA14:GL14) -> 20632865 | S7: =SUM(Financials!GM14:GX14) -> 21049326 | T7: =SUM(Financials!GY14:HJ14) -> 21474193 | U7: =SUM(Financials!HK14:HV14) -> 21907636 | V7: =SUM(Financials!HW14:IH14) -> 22349827 | W7: =SUM(Financials!II14:IT14) -> 22800944 | X7: =SUM(Financials!IU14:JF14) -> 23261166 | Y7: =SUM(Financials!JG14:JR14) -> 23730678
B8: =Financials!B15 -> Aluminum | C8: =SUM(Financials!C15:N15) -> 0 | D8: =SUM(Financials!O15:Z15) -> 2627012.6 | E8: =SUM(Financials!AA15:AL15) -> 3548402.5 | F8: =SUM(Financials!AM15:AX15) -> 3620024.7 | G8: =SUM(Financials!AY15:BJ15) -> 3703134.5 | H8: =SUM(Financials!BK15:BV15) -> 3767635.2 | I8: =SUM(Financials!BW15:CH15) -> 3843682.5 | J8: =SUM(Financials!CI15:CT15) -> 3921264.8 | K8: =SUM(Financials!CU15:DF15) -> 4000413 | L8: =SUM(Financials!DG15:DR15) -> 4081158.7 | M8: =SUM(Financials!DS15:ED15) -> 4163534.3 | N8: =SUM(Financials!EE15:EP15) -> 4247572.6 | O8: =SUM(Financials!EQ15:FB15) -> 4333307.1 | P8: =SUM(Financials!FC15:FN15) -> 4420772.1 | Q8: =SUM(Financials!FO15:FZ15) -> 4510002.5 | R8: =SUM(Financials!GA15:GL15) -> 4601034 | S8: =SUM(Financials!GM15:GX15) -> 4693902.9 | T8: =SUM(Financials!GY15:HJ15) -> 4788646.3 | U8: =SUM(Financials!HK15:HV15) -> 4885302.1 | V8: =SUM(Financials!HW15:IH15) -> 4983908.7 | W8: =SUM(Financials!II15:IT15) -> 5084505.7 | X8: =SUM(Financials!IU15:JF15) -> 5187133.2 | Y8: =SUM(Financials!JG15:JR15) -> 5291832.1
B9: =Financials!B16 -> Ferrous Metals | C9: =SUM(Financials!C16:N16) -> 0 | D9: =SUM(Financials!O16:Z16) -> 339853.48 | E9: =SUM(Financials!AA16:AL16) -> 459052.59 | F9: =SUM(Financials!AM16:AX16) -> 468318.27 | G9: =SUM(Financials!AY16:BJ16) -> 479070.08 | H9: =SUM(Financials!BK16:BV16) -> 487414.47 | I9: =SUM(Financials!BW16:CH16) -> 497252.62 | J9: =SUM(Financials!CI16:CT16) -> 507289.34 | K9: =SUM(Financials!CU16:DF16) -> 517528.65 | L9: =SUM(Financials!DG16:DR16) -> 527974.63 | M9: =SUM(Financials!DS16:ED16) -> 538631.46 | N9: =SUM(Financials!EE16:EP16) -> 549503.39 | O9: =SUM(Financials!EQ16:FB16) -> 560594.76 | P9: =SUM(Financials!FC16:FN16) -> 571910 | Q9: =SUM(Financials!FO16:FZ16) -> 583453.64 | R9: =SUM(Financials!GA16:GL16) -> 595230.27 | S9: =SUM(Financials!GM16:GX16) -> 607244.61 | T9: =SUM(Financials!GY16:HJ16) -> 619501.46 | U9: =SUM(Financials!HK16:HV16) -> 632005.69 | V9: =SUM(Financials!HW16:IH16) -> 644762.32 | W9: =SUM(Financials!II16:IT16) -> 657776.43 | X9: =SUM(Financials!IU16:JF16) -> 671053.23 | Y9: =SUM(Financials!JG16:JR16) -> 684598
B10: =Financials!B17 -> Non-Ferrous Metals | C10: =SUM(Financials!C17:N17) -> 0 | D10: =SUM(Financials!O17:Z17) -> 7030033.8 | E10: =SUM(Financials!AA17:AL17) -> 9495724.9 | F10: =SUM(Financials!AM17:AX17) -> 9687390 | G10: =SUM(Financials!AY17:BJ17) -> 9909796.5 | H10: =SUM(Financials!BK17:BV17) -> 10082404 | I10: =SUM(Financials!BW17:CH17) -> 10285911 | J10: =SUM(Financials!CI17:CT17) -> 10493525 | K10: =SUM(Financials!CU17:DF17) -> 10705331 | L10: =SUM(Financials!DG17:DR17) -> 10921411 | M10: =SUM(Financials!DS17:ED17) -> 11141852 | N10: =SUM(Financials!EE17:EP17) -> 11366743 | O10: =SUM(Financials!EQ17:FB17) -> 11596174 | P10: =SUM(Financials!FC17:FN17) -> 11830235 | Q10: =SUM(Financials!FO17:FZ17) -> 12069021 | R10: =SUM(Financials!GA17:GL17) -> 12312626 | S10: =SUM(Financials!GM17:GX17) -> 12561149 | T10: =SUM(Financials!GY17:HJ17) -> 12814687 | U10: =SUM(Financials!HK17:HV17) -> 13073344 | V10: =SUM(Financials!HW17:IH17) -> 13337221 | W10: =SUM(Financials!II17:IT17) -> 13606424 | X10: =SUM(Financials!IU17:JF17) -> 13881061 | Y10: =SUM(Financials!JG17:JR17) -> 14161241
B11: =Financials!B18 -> Steel from Tires | C11: =SUM(Financials!C18:N18) -> 0 | D11: =SUM(Financials!O18:Z18) -> 986671.41 | E11: =SUM(Financials!AA18:AL18) -> 1332733.3 | F11: =SUM(Financials!AM18:AX18) -> 1359633.7 | G11: =SUM(Financials!AY18:BJ18) -> 1390848.6 | H11: =SUM(Financials!BK18:BV18) -> 1415074.3 | I11: =SUM(Financials!BW18:CH18) -> 1443636.6 | J11: =SUM(Financials!CI18:CT18) -> 1472775.5 | K11: =SUM(Financials!CU18:DF18) -> 1502502.5 | L11: =SUM(Financials!DG18:DR18) -> 1532829.6 | M11: =SUM(Financials!DS18:ED18) -> 1563768.8 | N11: =SUM(Financials!EE18:EP18) -> 1595332.4 | O11: =SUM(Financials!EQ18:FB18) -> 1627533.2 | P11: =SUM(Financials!FC18:FN18) -> 1660383.9 | Q11: =SUM(Financials!FO18:FZ18) -> 1693897.7 | R11: =SUM(Financials!GA18:GL18) -> 1728087.9 | S11: =SUM(Financials!GM18:GX18) -> 1762968.2 | T11: =SUM(Financials!GY18:HJ18) -> 1798552.6 | U11: =SUM(Financials!HK18:HV18) -> 1834855.2 | V11: =SUM(Financials!HW18:IH18) -> 1871890.6 | W11: =SUM(Financials!II18:IT18) -> 1909673.5 | X11: =SUM(Financials!IU18:JF18) -> 1948219 | Y11: =SUM(Financials!JG18:JR18) -> 1987542.6
B12: =Financials!B19 -> Steel, OTR Tires | C12: =SUM(Financials!C19:N19) -> 0 | D12: =SUM(Financials!O19:Z19) -> 0 | E12: =SUM(Financials!AA19:AL19) -> 0 | F12: =SUM(Financials!AM19:AX19) -> 0 | G12: =SUM(Financials!AY19:BJ19) -> 0 | H12: =SUM(Financials!BK19:BV19) -> 0 | I12: =SUM(Financials!BW19:CH19) -> 0 | J12: =SUM(Financials!CI19:CT19) -> 0 | K12: =SUM(Financials!CU19:DF19) -> 0 | L12: =SUM(Financials!DG19:DR19) -> 0 | M12: =SUM(Financials!DS19:ED19) -> 0 | N12: =SUM(Financials!EE19:EP19) -> 0 | O12: =SUM(Financials!EQ19:FB19) -> 0 | P12: =SUM(Financials!FC19:FN19) -> 0 | Q12: =SUM(Financials!FO19:FZ19) -> 0 | R12: =SUM(Financials!GA19:GL19) -> 0 | S12: =SUM(Financials!GM19:GX19) -> 0 | T12: =SUM(Financials!GY19:HJ19) -> 0 | U12: =SUM(Financials!HK19:HV19) -> 0 | V12: =SUM(Financials!HW19:IH19) -> 0 | W12: =SUM(Financials!II19:IT19) -> 0 | X12: =SUM(Financials!IU19:JF19) -> 0 | Y12: =SUM(Financials!JG19:JR19) -> 0
B13: =Financials!B20 -> Carbon Black | C13: =SUM(Financials!C20:N20) -> 0 | D13: =SUM(Financials!O20:Z20) -> 6268851.7 | E13: =SUM(Financials!AA20:AL20) -> 8467568.3 | F13: =SUM(Financials!AM20:AX20) -> 8638480.7 | G13: =SUM(Financials!AY20:BJ20) -> 8836805.9 | H13: =SUM(Financials!BK20:BV20) -> 8990724.4 | I13: =SUM(Financials!BW20:CH20) -> 9172196.4 | J13: =SUM(Financials!CI20:CT20) -> 9357331.2 | K13: =SUM(Financials!CU20:DF20) -> 9546202.9 | L13: =SUM(Financials!DG20:DR20) -> 9738886.9 | M13: =SUM(Financials!DS20:ED20) -> 9935460.1 | N13: =SUM(Financials!EE20:EP20) -> 10136001 | O13: =SUM(Financials!EQ20:FB20) -> 10340590 | P13: =SUM(Financials!FC20:FN20) -> 10549308 | Q13: =SUM(Financials!FO20:FZ20) -> 10762239 | R13: =SUM(Financials!GA20:GL20) -> 10979468 | S13: =SUM(Financials!GM20:GX20) -> 11201081 | T13: =SUM(Financials!GY20:HJ20) -> 11427168 | U13: =SUM(Financials!HK20:HV20) -> 11657818 | V13: =SUM(Financials!HW20:IH20) -> 11893123 | W13: =SUM(Financials!II20:IT20) -> 12133178 | X13: =SUM(Financials!IU20:JF20) -> 12378079 | Y13: =SUM(Financials!JG20:JR20) -> 12627922
B14: =Financials!B21 -> Graphene | C14: =SUM(Financials!C21:N21) -> 0 | D14: =SUM(Financials!O21:Z21) -> 14104916 | E14: =SUM(Financials!AA21:AL21) -> 19052029 | F14: =SUM(Financials!AM21:AX21) -> 19436581 | G14: =SUM(Financials!AY21:BJ21) -> 19882813 | H14: =SUM(Financials!BK21:BV21) -> 20229130 | I14: =SUM(Financials!BW21:CH21) -> 20637442 | J14: =SUM(Financials!CI21:CT21) -> 21053995 | K14: =SUM(Financials!CU21:DF21) -> 21478957 | L14: =SUM(Financials!DG21:DR21) -> 21912496 | M14: =SUM(Financials!DS21:ED21) -> 22354785 | N14: =SUM(Financials!EE21:EP21) -> 22806002 | O14: =SUM(Financials!EQ21:FB21) -> 23266327 | P14: =SUM(Financials!FC21:FN21) -> 23735942 | Q14: =SUM(Financials!FO21:FZ21) -> 24215037 | R14: =SUM(Financials!GA21:GL21) -> 24703802 | S14: =SUM(Financials!GM21:GX21) -> 25202432 | T14: =SUM(Financials!GY21:HJ21) -> 25711127 | U14: =SUM(Financials!HK21:HV21) -> 26230090 | V14: =SUM(Financials!HW21:IH21) -> 26759527 | W14: =SUM(Financials!II21:IT21) -> 27299651 | X14: =SUM(Financials!IU21:JF21) -> 27850677 | Y14: =SUM(Financials!JG21:JR21) -> 28412825
B15: =Financials!B22 -> Light Oil Sale | C15: =SUM(Financials!C22:N22) -> 0 | D15: =SUM(Financials!O22:Z22) -> 0 | E15: =SUM(Financials!AA22:AL22) -> 0 | F15: =SUM(Financials!AM22:AX22) -> 0 | G15: =SUM(Financials!AY22:BJ22) -> 0 | H15: =SUM(Financials!BK22:BV22) -> 0 | I15: =SUM(Financials!BW22:CH22) -> 0 | J15: =SUM(Financials!CI22:CT22) -> 0 | K15: =SUM(Financials!CU22:DF22) -> 0 | L15: =SUM(Financials!DG22:DR22) -> 0 | M15: =SUM(Financials!DS22:ED22) -> 0 | N15: =SUM(Financials!EE22:EP22) -> 0 | O15: =SUM(Financials!EQ22:FB22) -> 0 | P15: =SUM(Financials!FC22:FN22) -> 0 | Q15: =SUM(Financials!FO22:FZ22) -> 0 | R15: =SUM(Financials!GA22:GL22) -> 0 | S15: =SUM(Financials!GM22:GX22) -> 0 | T15: =SUM(Financials!GY22:HJ22) -> 0 | U15: =SUM(Financials!HK22:HV22) -> 0 | V15: =SUM(Financials!HW22:IH22) -> 0 | W15: =SUM(Financials!II22:IT22) -> 0 | X15: =SUM(Financials!IU22:JF22) -> 0 | Y15: =SUM(Financials!JG22:JR22) -> 0
B16: =Financials!B23 -> Diesel | C16: =SUM(Financials!C23:N23) -> 0 | D16: =SUM(Financials!O23:Z23) -> 0 | E16: =SUM(Financials!AA23:AL23) -> 0 | F16: =SUM(Financials!AM23:AX23) -> 0 | G16: =SUM(Financials!AY23:BJ23) -> 0 | H16: =SUM(Financials!BK23:BV23) -> 0 | I16: =SUM(Financials!BW23:CH23) -> 0 | J16: =SUM(Financials!CI23:CT23) -> 0 | K16: =SUM(Financials!CU23:DF23) -> 0 | L16: =SUM(Financials!DG23:DR23) -> 0 | M16: =SUM(Financials!DS23:ED23) -> 0 | N16: =SUM(Financials!EE23:EP23) -> 0 | O16: =SUM(Financials!EQ23:FB23) -> 0 | P16: =SUM(Financials!FC23:FN23) -> 0 | Q16: =SUM(Financials!FO23:FZ23) -> 0 | R16: =SUM(Financials!GA23:GL23) -> 0 | S16: =SUM(Financials!GM23:GX23) -> 0 | T16: =SUM(Financials!GY23:HJ23) -> 0 | U16: =SUM(Financials!HK23:HV23) -> 0 | V16: =SUM(Financials!HW23:IH23) -> 0 | W16: =SUM(Financials!II23:IT23) -> 0 | X16: =SUM(Financials!IU23:JF23) -> 0 | Y16: =SUM(Financials!JG23:JR23) -> 0
... B20: =Financials!B27 -> Petroleum Coke | C20: =SUM(Financials!C27:N27) -> 0 | D20: =SUM(Financials!O27:Z27) -> 0 | E20: =SUM(Financials!AA27:AL27) -> 0 | F20: =SUM(Financials!AM27:AX27) -> 0 | G20: =SUM(Financials!AY27:BJ27) -> 0 | H20: =SUM(Financials!BK27:BV27) -> 0 | I20: =SUM(Financials!BW27:CH27) -> 0 | J20: =SUM(Financials!CI27:CT27) -> 0 | K20: =SUM(Financials!CU27:DF27) -> 0 | L20: =SUM(Financials!DG27:DR27) -> 0 | M20: =SUM(Financials!DS27:ED27) -> 0 | N20: =SUM(Financials!EE27:EP27) -> 0 | O20: =SUM(Financials!EQ27:FB27) -> 0 | P20: =SUM(Financials!FC27:FN27) -> 0 | Q20: =SUM(Financials!FO27:FZ27) -> 0 | R20: =SUM(Financials!GA27:GL27) -> 0 | S20: =SUM(Financials!GM27:GX27) -> 0 | T20: =SUM(Financials!GY27:HJ27) -> 0 | U20: =SUM(Financials!HK27:HV27) -> 0 | V20: =SUM(Financials!HW27:IH27) -> 0 | W20: =SUM(Financials!II27:IT27) -> 0 | X20: =SUM(Financials!IU27:JF27) -> 0 | Y20: =SUM(Financials!JG27:JR27) -> 0
B21: Total Commodity Revenue | C21: =SUM(C5:C20) -> 0 | D21: =SUM(D5:D20) -> 43137908 | E21: =SUM(E5:E20) -> 74666933 | F21: =SUM(F5:F20) -> 81209972 | G21: =SUM(G5:G20) -> 82634342 | H21: =SUM(H5:H20) -> 83633870 | I21: =SUM(I5:I20) -> 84882634 | J21: =SUM(J5:J20) -> 86156605 | ... Y21: =SUM(Y5:Y20) -> 1.0866255e+08
B23: Revenue Byproducts
B24: MSW tipping fees | C24: =SUM(Financials!C31:N31) -> 0 | D24: =SUM(Financials!O31:Z31) -> -1058750 | E24: =SUM(Financials!AA31:AL31) -> -1405250 | F24: =SUM(Financials!AM31:AX31) -> -1405250 | G24: =SUM(Financials!AY31:BJ31) -> -1409100 | H24: =SUM(Financials!BK31:BV31) -> -1405250 | I24: =SUM(Financials!BW31:CH31) -> -1405250 | J24: =SUM(Financials!CI31:CT31) -> -1405250 | K24: =SUM(Financials!CU31:DF31) -> -1405250 | L24: =SUM(Financials!DG31:DR31) -> -1405250 | M24: =SUM(Financials!DS31:ED31) -> -1405250 | N24: =SUM(Financials!EE31:EP31) -> -1405250 | O24: =SUM(Financials!EQ31:FB31) -> -1405250 | P24: =SUM(Financials!FC31:FN31) -> -1405250 | Q24: =SUM(Financials!FO31:FZ31) -> -1405250 | R24: =SUM(Financials!GA31:GL31) -> -1405250 | S24: =SUM(Financials!GM31:GX31) -> -1405250 | T24: =SUM(Financials!GY31:HJ31) -> -1405250 | U24: =SUM(Financials!HK31:HV31) -> -1405250 | V24: =SUM(Financials!HW31:IH31) -> -1405250 | W24: =SUM(Financials!II31:IT31) -> -1405250 | X24: =SUM(Financials!IU31:JF31) -> -1405250 | Y24: =SUM(Financials!JG31:JR31) -> -1405250
B25: Tire tipping fees | C25: =SUM(Financials!C32:N32) -> 0 | D25: =SUM(Financials!O32:Z32) -> 0 | E25: =SUM(Financials!AA32:AL32) -> 0 | F25: =SUM(Financials!AM32:AX32) -> 0 | G25: =SUM(Financials!AY32:BJ32) -> 0 | H25: =SUM(Financials!BK32:BV32) -> 0 | I25: =SUM(Financials!BW32:CH32) -> 0 | J25: =SUM(Financials!CI32:CT32) -> 0 | K25: =SUM(Financials!CU32:DF32) -> 0 | L25: =SUM(Financials!DG32:DR32) -> 0 | M25: =SUM(Financials!DS32:ED32) -> 0 | N25: =SUM(Financials!EE32:EP32) -> 0 | O25: =SUM(Financials!EQ32:FB32) -> 0 | P25: =SUM(Financials!FC32:FN32) -> 0 | Q25: =SUM(Financials!FO32:FZ32) -> 0 | R25: =SUM(Financials!GA32:GL32) -> 0 | S25: =SUM(Financials!GM32:GX32) -> 0 | T25: =SUM(Financials!GY32:HJ32) -> 0 | U25: =SUM(Financials!HK32:HV32) -> 0 | V25: =SUM(Financials!HW32:IH32) -> 0 | W25: =SUM(Financials!II32:IT32) -> 0 | X25: =SUM(Financials!IU32:JF32) -> 0 | Y25: =SUM(Financials!JG32:JR32) -> 0
B26: REC Revenue | C26: =SUM(Financials!C33:N33) -> 0 | D26: =SUM(Financials!O33:Z33) -> 0 | E26: =SUM(Financials!AA33:AL33) -> 0 | F26: =SUM(Financials!AM33:AX33) -> 0 | G26: =SUM(Financials!AY33:BJ33) -> 0 | H26: =SUM(Financials!BK33:BV33) -> 0 | I26: =SUM(Financials!BW33:CH33) -> 0 | J26: =SUM(Financials!CI33:CT33) -> 0 | K26: =SUM(Financials!CU33:DF33) -> 0 | L26: =SUM(Financials!DG33:DR33) -> 0 | M26: =SUM(Financials!DS33:ED33) -> 0 | N26: =SUM(Financials!EE33:EP33) -> 0 | O26: =SUM(Financials!EQ33:FB33) -> 0 | P26: =SUM(Financials!FC33:FN33) -> 0 | Q26: =SUM(Financials!FO33:FZ33) -> 0 | R26: =SUM(Financials!GA33:GL33) -> 0 | S26: =SUM(Financials!GM33:GX33) -> 0 | T26: =SUM(Financials!GY33:HJ33) -> 0 | U26: =SUM(Financials!HK33:HV33) -> 0 | V26: =SUM(Financials!HW33:IH33) -> 0 | W26: =SUM(Financials!II33:IT33) -> 0 | X26: =SUM(Financials!IU33:JF33) -> 0 | Y26: =SUM(Financials!JG33:JR33) -> 0
B27: Carbon Credit Revenue | C27: =SUM(Financials!C34:N34) -> 0 | D27: =SUM(Financials!O34:Z34) -> 0 | E27: =SUM(Financials!AA34:AL34) -> 0 | F27: =SUM(Financials!AM34:AX34) -> 0 | G27: =SUM(Financials!AY34:BJ34) -> 0 | H27: =SUM(Financials!BK34:BV34) -> 0 | I27: =SUM(Financials!BW34:CH34) -> 0 | J27: =SUM(Financials!CI34:CT34) -> 0 | K27: =SUM(Financials!CU34:DF34) -> 0 | L27: =SUM(Financials!DG34:DR34) -> 0 | M27: =SUM(Financials!DS34:ED34) -> 0 | N27: =SUM(Financials!EE34:EP34) -> 0 | O27: =SUM(Financials!EQ34:FB34) -> 0 | P27: =SUM(Financials!FC34:FN34) -> 0 | Q27: =SUM(Financials!FO34:FZ34) -> 0 | R27: =SUM(Financials!GA34:GL34) -> 0 | S27: =SUM(Financials!GM34:GX34) -> 0 | T27: =SUM(Financials!GY34:HJ34) -> 0 | U27: =SUM(Financials!HK34:HV34) -> 0 | V27: =SUM(Financials!HW34:IH34) -> 0 | W27: =SUM(Financials!II34:IT34) -> 0 | X27: =SUM(Financials!IU34:JF34) -> 0 | Y27: =SUM(Financials!JG34:JR34) -> 0
B28: Total Byproduct Revenue | C28: =SUM(C24:C27) -> 0 | D28: =SUM(D24:D27) -> -1058750 | E28: =SUM(E24:E27) -> -1405250 | F28: =SUM(F24:F27) -> -1405250 | G28: =SUM(G24:G27) -> -1409100 | H28: =SUM(H24:H27) -> -1405250 | I28: =SUM(I24:I27) -> -1405250 | J28: =SUM(J24:J27) -> -1405250 | ... Y28: =SUM(Y24:Y27) -> -1405250
B30: Total Revenue | C30: =C21+C28 -> 0 | D30: =D21+D28 -> 42079158 | E30: =E21+E28 -> 73261683 | F30: =F21+F28 -> 79804722 | G30: =G21+G28 -> 81225242 | H30: =H21+H28 -> 82228620 | I30: =I21+I28 -> 83477384 | J30: =J21+J28 -> 84751355 | ... Y30: =Y21+Y28 -> 1.072573e+08
B32: Expenses
B33: =Financials!B40 -> Employee Cost | C33: =SUM(Financials!C40:C55) -> 601983.15 | D33: =SUM(Financials!O40:Z40) -> 3603546.1 | E33: =SUM(Financials!AA40:AL40) -> 4846945.1 | F33: =SUM(Financials!AM40:AX40) -> 4895637.3 | G33: =SUM(Financials!AY40:BJ40) -> 4944818.7 | H33: =SUM(Financials!BK40:BV40) -> 4994494.1 | I33: =SUM(Financials!BW40:CH40) -> 5044668.6 | J33: =SUM(Financials!CI40:CT40) -> 5095347.2 | K33: =SUM(Financials!CU40:DF40) -> 5146534.8 | L33: =SUM(Financials!DG40:DR40) -> 5198236.7 | M33: =SUM(Financials!DS40:ED40) -> 5250458 | N33: =SUM(Financials!EE40:EP40) -> 5303203.9 | O33: =SUM(Financials!EQ40:FB40) -> 5356479.7 | P33: =SUM(Financials!FC40:FN40) -> 5410290.7 | Q33: =SUM(Financials!FO40:FZ40) -> 5464642.2 | R33: =SUM(Financials!GA40:GL40) -> 5519539.8 | S33: =SUM(Financials!GM40:GX40) -> 5574988.9 | T33: =SUM(Financials!GY40:HJ40) -> 5630995 | U33: =SUM(Financials!HK40:HV40) -> 5687563.8 | V33: =SUM(Financials!HW40:IH40) -> 5744700.8 | W33: =SUM(Financials!II40:IT40) -> 5802411.9 | X33: =SUM(Financials!IU40:JF40) -> 5860702.7 | Y33: =SUM(Financials!JG40:JR40) -> 5919579.1
B34: =Financials!B41 -> Turbine LTMA Cost 5 year term | C34: =SUM(Financials!C41:C56) -> 1203966.3 | D34: =SUM(Financials!O41:Z41) -> 1630842.1 | E34: =SUM(Financials!AA41:AL41) -> 2212827.9 | F34: =SUM(Financials!AM41:AX41) -> 560150.9 | G34: =SUM(Financials!AY41:BJ41) -> 0 | H34: =SUM(Financials!BK41:BV41) -> 0 | I34: =SUM(Financials!BW41:CH41) -> 0 | J34: =SUM(Financials!CI41:CT41) -> 0 | K34: =SUM(Financials!CU41:DF41) -> 0 | L34: =SUM(Financials!DG41:DR41) -> 0 | M34: =SUM(Financials!DS41:ED41) -> 0 | N34: =SUM(Financials!EE41:EP41) -> 0 | O34: =SUM(Financials!EQ41:FB41) -> 0 | P34: =SUM(Financials!FC41:FN41) -> 0 | Q34: =SUM(Financials!FO41:FZ41) -> 0 | R34: =SUM(Financials!GA41:GL41) -> 0 | S34: =SUM(Financials!GM41:GX41) -> 0 | T34: =SUM(Financials!GY41:HJ41) -> 0 | U34: =SUM(Financials!HK41:HV41) -> 0 | V34: =SUM(Financials!HW41:IH41) -> 0 | W34: =SUM(Financials!II41:IT41) -> 0 | X34: =SUM(Financials!IU41:JF41) -> 0 | Y34: =SUM(Financials!JG41:JR41) -> 0
B35: =Financials!B42 -> Pyrolysis LTMA Cost yrs. 3+ | C35: =SUM(Financials!C42:C57) -> 1203966.3 | D35: =SUM(Financials!O42:Z42) -> 0 | E35: =SUM(Financials!AA42:AL42) -> 0 | F35: =SUM(Financials!AM42:AX42) -> 174768.73 | G35: =SUM(Financials!AY42:BJ42) -> 266557.69 | H35: =SUM(Financials!BK42:BV42) -> 271937.99 | I35: =SUM(Financials!BW42:CH42) -> 277426.88 | J35: =SUM(Financials!CI42:CT42) -> 283026.56 | K35: =SUM(Financials!CU42:DF42) -> 288739.27 | L35: =SUM(Financials!DG42:DR42) -> 294567.29 | M35: =SUM(Financials!DS42:ED42) -> 300512.94 | N35: =SUM(Financials!EE42:EP42) -> 306578.6 | O35: =SUM(Financials!EQ42:FB42) -> 312766.69 | P35: =SUM(Financials!FC42:FN42) -> 319079.68 | Q35: =SUM(Financials!FO42:FZ42) -> 325520.1 | R35: =SUM(Financials!GA42:GL42) -> 332090.51 | S35: =SUM(Financials!GM42:GX42) -> 338793.55 | T35: =SUM(Financials!GY42:HJ42) -> 345631.88 | U35: =SUM(Financials!HK42:HV42) -> 352608.23 | V35: =SUM(Financials!HW42:IH42) -> 359725.4 | W35: =SUM(Financials!II42:IT42) -> 366986.23 | X35: =SUM(Financials!IU42:JF42) -> 374393.61 | Y35: =SUM(Financials!JG42:JR42) -> 381950.5
B36: =Financials!B43 -> Total O&M | C36: =SUM(Financials!C43:C58) -> 601983.15 | D36: =SUM(Financials!O43:Z43) -> 1160465 | E36: =SUM(Financials!AA43:AL43) -> 1574591 | F36: =SUM(Financials!AM43:AX43) -> 1606373.1 | G36: =SUM(Financials!AY43:BJ43) -> 1638796.7 | H36: =SUM(Financials!BK43:BV43) -> 1671874.7 | I36: =SUM(Financials!BW43:CH43) -> 1705620.5 | J36: =SUM(Financials!CI43:CT43) -> 1740047.3 | K36: =SUM(Financials!CU43:DF43) -> 1775169 | L36: =SUM(Financials!DG43:DR43) -> 1810999.7 | M36: =SUM(Financials!DS43:ED43) -> 1847553.5 | N36: =SUM(Financials!EE43:EP43) -> 1884845.2 | O36: =SUM(Financials!EQ43:FB43) -> 1922889.6 | P36: =SUM(Financials!FC43:FN43) -> 1961701.9 | Q36: =SUM(Financials!FO43:FZ43) -> 2001297.6 | R36: =SUM(Financials!GA43:GL43) -> 2041692.5 | S36: =SUM(Financials!GM43:GX43) -> 2082902.7 | T36: =SUM(Financials!GY43:HJ43) -> 2124944.8 | U36: =SUM(Financials!HK43:HV43) -> 2167835.4 | V36: =SUM(Financials!HW43:IH43) -> 2211591.8 | W36: =SUM(Financials!II43:IT43) -> 2256231.3 | X36: =SUM(Financials!IU43:JF43) -> 2301771.9 | Y36: =SUM(Financials!JG43:JR43) -> 2348231.7
B37: =Financials!B44 -> All insurance for the plant and risks | C37: =SUM(Financials!C44:C59) -> 601983.15 | D37: =SUM(Financials!O44:Z44) -> 7511416.3 | E37: =SUM(Financials!AA44:AL44) -> 7147871.2 | F37: =SUM(Financials!AM44:AX44) -> 6758045.3 | G37: =SUM(Financials!AY44:BJ44) -> 6340039 | H37: =SUM(Financials!BK44:BV44) -> 5891814.9 | I37: =SUM(Financials!BW44:CH44) -> 5411188.6 | J37: =SUM(Financials!CI44:CT44) -> 4895817.9 | K37: =SUM(Financials!CU44:DF44) -> 4343190.9 | L37: =SUM(Financials!DG44:DR44) -> 3750614.5 | M37: =SUM(Financials!DS44:ED44) -> 3115200.8 | N37: =SUM(Financials!EE44:EP44) -> 2734927.1 | O37: =SUM(Financials!EQ44:FB44) -> 2483036.2 | P37: =SUM(Financials!FC44:FN44) -> 2212936.2 | Q37: =SUM(Financials!FO44:FZ44) -> 1923310.5 | R37: =SUM(Financials!GA44:GL44) -> 1612747.8 | S37: =SUM(Financials!GM44:GX44) -> 1504315.7 | T37: =SUM(Financials!GY44:HJ44) -> 1504315.7 | U37: =SUM(Financials!HK44:HV44) -> 1504315.7 | V37: =SUM(Financials!HW44:IH44) -> 1504315.7 | W37: =SUM(Financials!II44:IT44) -> 1504315.7 | X37: =SUM(Financials!IU44:JF44) -> 1504315.7 | Y37: =SUM(Financials!JG44:JR44) -> 1504315.7
B38: =Financials!B45 -> Land Rental | C38: =SUM(Financials!C45:C60) -> 0 | D38: =SUM(Financials!O45:Z45) -> 75501.949 | E38: =SUM(Financials!AA45:AL45) -> 102445.74 | F38: =SUM(Financials!AM45:AX45) -> 104513.54 | G38: =SUM(Financials!AY45:BJ45) -> 106623.08 | H38: =SUM(Financials!BK45:BV45) -> 108775.19 | I38: =SUM(Financials!BW45:CH45) -> 110970.75 | J38: =SUM(Financials!CI45:CT45) -> 113210.62 | K38: =SUM(Financials!CU45:DF45) -> 115495.71 | L38: =SUM(Financials!DG45:DR45) -> 117826.91 | M38: =SUM(Financials!DS45:ED45) -> 120205.17 | N38: =SUM(Financials!EE45:EP45) -> 122631.44 | O38: =SUM(Financials!EQ45:FB45) -> 125106.68 | P38: =SUM(Financials!FC45:FN45) -> 127631.87 | Q38: =SUM(Financials!FO45:FZ45) -> 130208.04 | R38: =SUM(Financials!GA45:GL45) -> 132836.21 | S38: =SUM(Financials!GM45:GX45) -> 135517.42 | T38: =SUM(Financials!GY45:HJ45) -> 138252.75 | U38: =SUM(Financials!HK45:HV45) -> 141043.29 | V38: =SUM(Financials!HW45:IH45) -> 143890.16 | W38: =SUM(Financials!II45:IT45) -> 146794.49 | X38: =SUM(Financials!IU45:JF45) -> 149757.44 | Y38: =SUM(Financials!JG45:JR45) -> 152780.2
B39: =Financials!B46 -> IT outsourced | C39: =SUM(Financials!C46:C60) -> 0 | D39: =SUM(Financials!O46:Z46) -> 53701.504 | E39: =SUM(Financials!AA46:AL46) -> 81956.589 | F39: =SUM(Financials!AM46:AX46) -> 83610.83 | G39: =SUM(Financials!AY46:BJ46) -> 85298.461 | H39: =SUM(Financials!BK46:BV46) -> 87020.155 | I39: =SUM(Financials!BW46:CH46) -> 88776.601 | J39: =SUM(Financials!CI46:CT46) -> 90568.5 | K39: =SUM(Financials!CU46:DF46) -> 92396.567 | L39: =SUM(Financials!DG46:DR46) -> 94261.532 | M39: =SUM(Financials!DS46:ED46) -> 96164.14 | N39: =SUM(Financials!EE46:EP46) -> 98105.151 | O39: =SUM(Financials!EQ46:FB46) -> 100085.34 | P39: =SUM(Financials!FC46:FN46) -> 102105.5 | Q39: =SUM(Financials!FO46:FZ46) -> 104166.43 | R39: =SUM(Financials!GA46:GL46) -> 106268.96 | S39: =SUM(Financials!GM46:GX46) -> 108413.94 | T39: =SUM(Financials!GY46:HJ46) -> 110602.2 | U39: =SUM(Financials!HK46:HV46) -> 112834.63 | V39: =SUM(Financials!HW46:IH46) -> 115112.13 | W39: =SUM(Financials!II46:IT46) -> 117435.59 | X39: =SUM(Financials!IU46:JF46) -> 119805.96 | Y39: =SUM(Financials!JG46:JR46) -> 122224.16
B40: =Financials!B47 -> Utilities | C40: =SUM(Financials!C47:C61) -> 0 | D40: =SUM(Financials!O47:Z47) -> 151003.9 | E40: =SUM(Financials!AA47:AL47) -> 204891.47 | F40: =SUM(Financials!AM47:AX47) -> 209027.08 | G40: =SUM(Financials!AY47:BJ47) -> 213246.15 | H40: =SUM(Financials!BK47:BV47) -> 217550.39 | I40: =SUM(Financials!BW47:CH47) -> 221941.5 | J40: =SUM(Financials!CI47:CT47) -> 226421.25 | K40: =SUM(Financials!CU47:DF47) -> 230991.42 | L40: =SUM(Financials!DG47:DR47) -> 235653.83 | M40: =SUM(Financials!DS47:ED47) -> 240410.35 | N40: =SUM(Financials!EE47:EP47) -> 245262.88 | O40: =SUM(Financials!EQ47:FB47) -> 250213.35 | P40: =SUM(Financials!FC47:FN47) -> 255263.75 | Q40: =SUM(Financials!FO47:FZ47) -> 260416.08 | R40: =SUM(Financials!GA47:GL47) -> 265672.41 | S40: =SUM(Financials!GM47:GX47) -> 271034.84 | T40: =SUM(Financials!GY47:HJ47) -> 276505.5 | U40: =SUM(Financials!HK47:HV47) -> 282086.59 | V40: =SUM(Financials!HW47:IH47) -> 287780.32 | W40: =SUM(Financials!II47:IT47) -> 293588.98 | X40: =SUM(Financials!IU47:JF47) -> 299514.89 | Y40: =SUM(Financials!JG47:JR47) -> 305560.4
B41: =Financials!B48 -> OVD Fee for exporting | C41: =SUM(Financials!C48:C62) -> 0 | D41: =SUM(Financials!O48:Z48) -> 0 | E41: =SUM(Financials!AA48:AL48) -> 0 | F41: =SUM(Financials!AM48:AX48) -> 0 | G41: =SUM(Financials!AY48:BJ48) -> 0 | H41: =SUM(Financials!BK48:BV48) -> 0 | I41: =SUM(Financials!BW48:CH48) -> 0 | J41: =SUM(Financials!CI48:CT48) -> 0 | K41: =SUM(Financials!CU48:DF48) -> 0 | L41: =SUM(Financials!DG48:DR48) -> 0 | M41: =SUM(Financials!DS48:ED48) -> 0 | N41: =SUM(Financials!EE48:EP48) -> 0 | O41: =SUM(Financials!EQ48:FB48) -> 0 | P41: =SUM(Financials!FC48:FN48) -> 0 | Q41: =SUM(Financials!FO48:FZ48) -> 0 | R41: =SUM(Financials!GA48:GL48) -> 0 | S41: =SUM(Financials!GM48:GX48) -> 0 | T41: =SUM(Financials!GY48:HJ48) -> 0 | U41: =SUM(Financials!HK48:HV48) -> 0 | V41: =SUM(Financials!HW48:IH48) -> 0 | W41: =SUM(Financials!II48:IT48) -> 0 | X41: =SUM(Financials!IU48:JF48) -> 0 | Y41: =SUM(Financials!JG48:JR48) -> 0
B42: =Financials!B49 -> Electricity | C42: =SUM(Financials!C49:C62) -> 0 | D42: =SUM(Financials!O49:Z49) -> 0 | E42: =SUM(Financials!AA49:AL49) -> 0 | F42: =SUM(Financials!AM49:AX49) -> 0 | G42: =SUM(Financials!AY49:BJ49) -> 0 | H42: =SUM(Financials!BK49:BV49) -> 0 | I42: =SUM(Financials!BW49:CH49) -> 0 | J42: =SUM(Financials!CI49:CT49) -> 0 | K42: =SUM(Financials!CU49:DF49) -> 0 | L42: =SUM(Financials!DG49:DR49) -> 0 | M42: =SUM(Financials!DS49:ED49) -> 0 | N42: =SUM(Financials!EE49:EP49) -> 0 | O42: =SUM(Financials!EQ49:FB49) -> 0 | P42: =SUM(Financials!FC49:FN49) -> 0 | Q42: =SUM(Financials!FO49:FZ49) -> 0 | R42: =SUM(Financials!GA49:GL49) -> 0 | S42: =SUM(Financials!GM49:GX49) -> 0 | T42: =SUM(Financials!GY49:HJ49) -> 0 | U42: =SUM(Financials!HK49:HV49) -> 0 | V42: =SUM(Financials!HW49:IH49) -> 0 | W42: =SUM(Financials!II49:IT49) -> 0 | X42: =SUM(Financials!IU49:JF49) -> 0 | Y42: =SUM(Financials!JG49:JR49) -> 0
B43: =Financials!B50 -> Accounting & Auditing | C43: =SUM(Financials!C50:C62) -> 0 | D43: =SUM(Financials!O50:Z50) -> 64176.657 | E43: =SUM(Financials!AA50:AL50) -> 87078.876 | F43: =SUM(Financials!AM50:AX50) -> 88836.507 | G43: =SUM(Financials!AY50:BJ50) -> 90629.615 | H43: =SUM(Financials!BK50:BV50) -> 92458.915 | I43: =SUM(Financials!BW50:CH50) -> 94325.139 | J43: =SUM(Financials!CI50:CT50) -> 96229.031 | K43: =SUM(Financials!CU50:DF50) -> 98171.352 | L43: =SUM(Financials!DG50:DR50) -> 100152.88 | M43: =SUM(Financials!DS50:ED50) -> 102174.4 | N43: =SUM(Financials!EE50:EP50) -> 104236.72 | O43: =SUM(Financials!EQ50:FB50) -> 106340.67 | P43: =SUM(Financials!FC50:FN50) -> 108487.09 | Q43: =SUM(Financials!FO50:FZ50) -> 110676.83 | R43: =SUM(Financials!GA50:GL50) -> 112910.77 | S43: =SUM(Financials!GM50:GX50) -> 115189.81 | T43: =SUM(Financials!GY50:HJ50) -> 117514.84 | U43: =SUM(Financials!HK50:HV50) -> 119886.8 | V43: =SUM(Financials!HW50:IH50) -> 122306.64 | W43: =SUM(Financials!II50:IT50) -> 124775.32 | X43: =SUM(Financials!IU50:JF50) -> 127293.83 | Y43: =SUM(Financials!JG50:JR50) -> 129863.17
B44: =Financials!B51 -> Office Supplies | C44: =SUM(Financials!C51:C63) -> 0 | D44: =SUM(Financials!O51:Z51) -> 56626.462 | E44: =SUM(Financials!AA51:AL51) -> 76834.302 | F44: =SUM(Financials!AM51:AX51) -> 78385.153 | G44: =SUM(Financials!AY51:BJ51) -> 79967.307 | H44: =SUM(Financials!BK51:BV51) -> 81581.396 | I44: =SUM(Financials!BW51:CH51) -> 83228.064 | J44: =SUM(Financials!CI51:CT51) -> 84907.968 | K44: =SUM(Financials!CU51:DF51) -> 86621.781 | L44: =SUM(Financials!DG51:DR51) -> 88370.186 | M44: =SUM(Financials!DS51:ED51) -> 90153.881 | N44: =SUM(Financials!EE51:EP51) -> 91973.579 | O44: =SUM(Financials!EQ51:FB51) -> 93830.007 | P44: =SUM(Financials!FC51:FN51) -> 95723.905 | Q44: =SUM(Financials!FO51:FZ51) -> 97656.03 | R44: =SUM(Financials!GA51:GL51) -> 99627.154 | S44: =SUM(Financials!GM51:GX51) -> 101638.06 | T44: =SUM(Financials!GY51:HJ51) -> 103689.56 | U44: =SUM(Financials!HK51:HV51) -> 105782.47 | V44: =SUM(Financials!HW51:IH51) -> 107917.62 | W44: =SUM(Financials!II51:IT51) -> 110095.87 | X44: =SUM(Financials!IU51:JF51) -> 112318.08 | Y44: =SUM(Financials!JG51:JR51) -> 114585.15
B45: =Financials!B52 -> Gas Transmission Costs | C45: =SUM(Financials!C52:C64) -> 0 | D45: =SUM(Financials!O52:Z52) -> 0 | E45: =SUM(Financials!AA52:AL52) -> 0 | F45: =SUM(Financials!AM52:AX52) -> 0 | G45: =SUM(Financials!AY52:BJ52) -> 0 | H45: =SUM(Financials!BK52:BV52) -> 0 | I45: =SUM(Financials!BW52:CH52) -> 0 | J45: =SUM(Financials!CI52:CT52) -> 0 | K45: =SUM(Financials!CU52:DF52) -> 0 | L45: =SUM(Financials!DG52:DR52) -> 0 | M45: =SUM(Financials!DS52:ED52) -> 0 | N45: =SUM(Financials!EE52:EP52) -> 0 | O45: =SUM(Financials!EQ52:FB52) -> 0 | P45: =SUM(Financials!FC52:FN52) -> 0 | Q45: =SUM(Financials!FO52:FZ52) -> 0 | R45: =SUM(Financials!GA52:GL52) -> 0 | S45: =SUM(Financials!GM52:GX52) -> 0 | T45: =SUM(Financials!GY52:HJ52) -> 0 | U45: =SUM(Financials!HK52:HV52) -> 0 | V45: =SUM(Financials!HW52:IH52) -> 0 | W45: =SUM(Financials!II52:IT52) -> 0 | X45: =SUM(Financials!IU52:JF52) -> 0 | Y45: =SUM(Financials!JG52:JR52) -> 0
B46: =Financials!B53 -> Permit Renewals | C46: =SUM(Financials!C53:C65) -> 0 | D46: =SUM(Financials!O53:Z53) -> 56626.462 | E46: =SUM(Financials!AA53:AL53) -> 76834.302 | F46: =SUM(Financials!AM53:AX53) -> 78385.153 | G46: =SUM(Financials!AY53:BJ53) -> 79967.307 | H46: =SUM(Financials!BK53:BV53) -> 81581.396 | I46: =SUM(Financials!BW53:CH53) -> 83228.064 | J46: =SUM(Financials!CI53:CT53) -> 84907.968 | K46: =SUM(Financials!CU53:DF53) -> 86621.781 | L46: =SUM(Financials!DG53:DR53) -> 88370.186 | M46: =SUM(Financials!DS53:ED53) -> 90153.881 | N46: =SUM(Financials!EE53:EP53) -> 91973.579 | O46: =SUM(Financials!EQ53:FB53) -> 93830.007 | P46: =SUM(Financials!FC53:FN53) -> 95723.905 | Q46: =SUM(Financials!FO53:FZ53) -> 97656.03 | R46: =SUM(Financials!GA53:GL53) -> 99627.154 | S46: =SUM(Financials!GM53:GX53) -> 101638.06 | T46: =SUM(Financials!GY53:HJ53) -> 103689.56 | U46: =SUM(Financials!HK53:HV53) -> 105782.47 | V46: =SUM(Financials!HW53:IH53) -> 107917.62 | W46: =SUM(Financials!II53:IT53) -> 110095.87 | X46: =SUM(Financials!IU53:JF53) -> 112318.08 | Y46: =SUM(Financials!JG53:JR53) -> 114585.15
B47: =Financials!B54 -> Property Taxes | C47: =SUM(Financials!C54:C66) -> 0 | D47: =SUM(Financials!O54:Z54) -> 64176.657 | E47: =SUM(Financials!AA54:AL54) -> 87078.876 | F47: =SUM(Financials!AM54:AX54) -> 88836.507 | G47: =SUM(Financials!AY54:BJ54) -> 90629.615 | H47: =SUM(Financials!BK54:BV54) -> 92458.915 | I47: =SUM(Financials!BW54:CH54) -> 94325.139 | J47: =SUM(Financials!CI54:CT54) -> 96229.031 | K47: =SUM(Financials!CU54:DF54) -> 98171.352 | L47: =SUM(Financials!DG54:DR54) -> 100152.88 | M47: =SUM(Financials!DS54:ED54) -> 102174.4 | N47: =SUM(Financials!EE54:EP54) -> 104236.72 | O47: =SUM(Financials!EQ54:FB54) -> 106340.67 | P47: =SUM(Financials!FC54:FN54) -> 108487.09 | Q47: =SUM(Financials!FO54:FZ54) -> 110676.83 | R47: =SUM(Financials!GA54:GL54) -> 112910.77 | S47: =SUM(Financials!GM54:GX54) -> 115189.81 | T47: =SUM(Financials!GY54:HJ54) -> 117514.84 | U47: =SUM(Financials!HK54:HV54) -> 119886.8 | V47: =SUM(Financials!HW54:IH54) -> 122306.64 | W47: =SUM(Financials!II54:IT54) -> 124775.32 | X47: =SUM(Financials!IU54:JF54) -> 127293.83 | Y47: =SUM(Financials!JG54:JR54) -> 129863.17
B48: =Financials!B55 -> Miscellaneous | C48: =SUM(Financials!C55:C67) -> 0 | D48: =SUM(Financials!O55:Z55) -> 75501.949 | E48: =SUM(Financials!AA55:AL55) -> 102445.74 | F48: =SUM(Financials!AM55:AX55) -> 104513.54 | G48: =SUM(Financials!AY55:BJ55) -> 106623.08 | H48: =SUM(Financials!BK55:BV55) -> 108775.19 | I48: =SUM(Financials!BW55:CH55) -> 110970.75 | J48: =SUM(Financials!CI55:CT55) -> 113210.62 | K48: =SUM(Financials!CU55:DF55) -> 115495.71 | L48: =SUM(Financials!DG55:DR55) -> 117826.91 | M48: =SUM(Financials!DS55:ED55) -> 120205.17 | N48: =SUM(Financials!EE55:EP55) -> 122631.44 | O48: =SUM(Financials!EQ55:FB55) -> 125106.68 | P48: =SUM(Financials!FC55:FN55) -> 127631.87 | Q48: =SUM(Financials!FO55:FZ55) -> 130208.04 | R48: =SUM(Financials!GA55:GL55) -> 132836.21 | S48: =SUM(Financials!GM55:GX55) -> 135517.42 | T48: =SUM(Financials!GY55:HJ55) -> 138252.75 | U48: =SUM(Financials!HK55:HV55) -> 141043.29 | V48: =SUM(Financials!HW55:IH55) -> 143890.16 | W48: =SUM(Financials!II55:IT55) -> 146794.49 | X48: =SUM(Financials!IU55:JF55) -> 149757.44 | Y48: =SUM(Financials!JG55:JR55) -> 152780.2
B49: Total Expenses | C49: =SUM(C33:C48) -> 4213882 | D49: =SUM(D33:D48) -> 14503585 | E49: =SUM(E33:E48) -> 16601801 | F49: =SUM(F33:F48) -> 14831084 | G49: =SUM(G33:G48) -> 14043197 | H49: =SUM(H33:H48) -> 13700323 | I49: =SUM(I33:I48) -> 13326671 | J49: =SUM(J33:J48) -> 12919924 | ... Y49: =SUM(Y33:Y48) -> 11376319
B51: EBITDA | C51: =C30-C49 -> -4213882 | D51: =D30-D49 -> 27575573 | E51: =E30-E49 -> 56659882 | F51: =F30-F49 -> 64973638 | G51: =G30-G49 -> 67182045 | H51: =H30-H49 -> 68528296 | I51: =I30-I49 -> 70150714 | J51: =J30-J49 -> 71831431 | ... Y51: =Y30-Y49 -> 95880984
B53: Capital Expenditures | C53: =SUM(Financials!C60:N60) -> 0 | D53: =SUM(Financials!O60:Z60) -> 0 | E53: =SUM(Financials!AA60:AL60) -> 0 | F53: =SUM(Financials!AM60:AX60) -> 0 | G53: =SUM(Financials!AY60:BJ60) -> 0 | H53: =SUM(Financials!BK60:BV60) -> 0 | I53: =SUM(Financials!BW60:CH60) -> 0 | J53: =SUM(Financials!CI60:CT60) -> 1000000 | K53: =SUM(Financials!CU60:DF60) -> 1000000 | L53: =SUM(Financials!DG60:DR60) -> 1000000 | M53: =SUM(Financials!DS60:ED60) -> 1000000 | N53: =SUM(Financials!EE60:EP60) -> 1000000 | O53: =SUM(Financials!EQ60:FB60) -> 1000000 | P53: =SUM(Financials!FC60:FN60) -> 1000000 | Q53: =SUM(Financials!FO60:FZ60) -> 1000000 | R53: =SUM(Financials!GA60:GL60) -> 1000000 | S53: =SUM(Financials!GM60:GX60) -> 1000000 | T53: =SUM(Financials!GY60:HJ60) -> 1000000 | U53: =SUM(Financials!HK60:HV60) -> 1000000 | V53: =SUM(Financials!HW60:IH60) -> 1000000 | W53: =SUM(Financials!II60:IT60) -> 1000000 | X53: =SUM(Financials!IU60:JF60) -> 1000000 | Y53: =SUM(Financials!JG60:JR60) -> 1000000
P54: =SUM(Financials!FC61:FN61) -> 0 | Q54: =SUM(Financials!FO61:FZ61) -> 0 | R54: =SUM(Financials!GA61:GL61) -> 0 | S54: =SUM(Financials!GM61:GX61) -> 0 | T54: =SUM(Financials!GY61:HJ61) -> 0 | U54: =SUM(Financials!HK61:HV61) -> 0 | V54: =SUM(Financials!HW61:IH61) -> 0 | W54: =SUM(Financials!II61:IT61) -> 0 | X54: =SUM(Financials!IU61:JF61) -> 0 | Y54: =SUM(Financials!JG61:JR61) -> 0
B55: Depreciation Year | C55: =SUM(Financials!C62:N62) -> 0 | D55: =SUM(Financials!O62:Z62) -> 9 | E55: =SUM(Financials!AA62:AL62) -> 21 | F55: =SUM(Financials!AM62:AX62) -> 33 | G55: =SUM(Financials!AY62:BJ62) -> 45 | H55: =SUM(Financials!BK62:BV62) -> 57 | I55: =SUM(Financials!BW62:CH62) -> 69 | J55: =SUM(Financials!CI62:CT62) -> 81 | K55: =SUM(Financials!CU62:DF62) -> 93 | L55: =SUM(Financials!DG62:DR62) -> 105 | M55: =SUM(Financials!DS62:ED62) -> 117 | N55: =SUM(Financials!EE62:EP62) -> 30 | O55: =SUM(Financials!EQ62:FB62) -> 0 | P55: =SUM(Financials!FC62:FN62) -> 0 | Q55: =SUM(Financials!FO62:FZ62) -> 0 | R55: =SUM(Financials!GA62:GL62) -> 0 | S55: =SUM(Financials!GM62:GX62) -> 0 | T55: =SUM(Financials!GY62:HJ62) -> 0 | U55: =SUM(Financials!HK62:HV62) -> 0 | V55: =SUM(Financials!HW62:IH62) -> 0 | W55: =SUM(Financials!II62:IT62) -> 0 | X55: =SUM(Financials!IU62:JF62) -> 0 | Y55: =SUM(Financials!JG62:JR62) -> 0
B56: Initial CapEx Depreciation | C56: =SUM(Financials!C63:N63) -> 0 | D56: =SUM(Financials!O63:Z63) -> 27292295 | E56: =SUM(Financials!AA63:AL63) -> 36389726 | F56: =SUM(Financials!AM63:AX63) -> 36389726 | G56: =SUM(Financials!AY63:BJ63) -> 36389726 | H56: =SUM(Financials!BK63:BV63) -> 36389726 | I56: =SUM(Financials!BW63:CH63) -> 36389726 | J56: =SUM(Financials!CI63:CT63) -> 36389726 | K56: =SUM(Financials!CU63:DF63) -> 9097431.6 | L56: =SUM(Financials!DG63:DR63) -> 0 | M56: =SUM(Financials!DS63:ED63) -> 0 | N56: =SUM(Financials!EE63:EP63) -> 0 | O56: =SUM(Financials!EQ63:FB63) -> 0 | P56: =SUM(Financials!FC63:FN63) -> 0 | Q56: =SUM(Financials!FO63:FZ63) -> 0 | R56: =SUM(Financials!GA63:GL63) -> 0 | S56: =SUM(Financials!GM63:GX63) -> 0 | T56: =SUM(Financials!GY63:HJ63) -> 0 | U56: =SUM(Financials!HK63:HV63) -> 0 | V56: =SUM(Financials!HW63:IH63) -> 0 | W56: =SUM(Financials!II63:IT63) -> 0 | X56: =SUM(Financials!IU63:JF63) -> 0 | Y56: =SUM(Financials!JG63:JR63) -> 0
B57: Maintenance CapEx Depreciation | C57: =SUM(Financials!C64:N64) -> 0 | D57: =SUM(Financials!O64:Z64) -> 0 | E57: =SUM(Financials!AA64:AL64) -> 0 | F57: =SUM(Financials!AM64:AX64) -> 0 | G57: =SUM(Financials!AY64:BJ64) -> 0 | H57: =SUM(Financials!BK64:BV64) -> 0 | I57: =SUM(Financials!BW64:CH64) -> 0 | J57: =SUM(Financials!CI64:CT64) -> 142857.14 | K57: =SUM(Financials!CU64:DF64) -> 285714.29 | L57: =SUM(Financials!DG64:DR64) -> 428571.43 | M57: =SUM(Financials!DS64:ED64) -> 571428.57 | N57: =SUM(Financials!EE64:EP64) -> 714285.71 | O57: =SUM(Financials!EQ64:FB64) -> 857142.86 | P57: =SUM(Financials!FC64:FN64) -> 1000000 | Q57: =SUM(Financials!FO64:FZ64) -> 1000000 | R57: =SUM(Financials!GA64:GL64) -> 1000000 | S57: =SUM(Financials!GM64:GX64) -> 1000000 | T57: =SUM(Financials!GY64:HJ64) -> 1000000 | U57: =SUM(Financials!HK64:HV64) -> 1000000 | V57: =SUM(Financials!HW64:IH64) -> 1000000 | W57: =SUM(Financials!II64:IT64) -> 1000000 | X57: =SUM(Financials!IU64:JF64) -> 1000000 | Y57: =SUM(Financials!JG64:JR64) -> 1000000
B58: Amortization | C58: =SUM(Financials!C65:N65) -> 0 | D58: =SUM(Financials!O65:Z65) -> 1834042.2 | E58: =SUM(Financials!AA65:AL65) -> 203782.47 | F58: =SUM(Financials!AM65:AX65) -> 203782.47 | G58: =SUM(Financials!AY65:BJ65) -> 203782.47 | H58: =SUM(Financials!BK65:BV65) -> 203782.47 | I58: =SUM(Financials!BW65:CH65) -> 203782.47 | J58: =SUM(Financials!CI65:CT65) -> 203782.47 | K58: =SUM(Financials!CU65:DF65) -> 203782.47 | L58: =SUM(Financials!DG65:DR65) -> 203782.47 | M58: =SUM(Financials!DS65:ED65) -> 203782.47 | N58: =SUM(Financials!EE65:EP65) -> 203782.47 | O58: =SUM(Financials!EQ65:FB65) -> 203782.47 | P58: =SUM(Financials!FC65:FN65) -> 203782.47 | Q58: =SUM(Financials!FO65:FZ65) -> 203782.47 | R58: =SUM(Financials!GA65:GL65) -> 203782.47 | S58: =SUM(Financials!GM65:GX65) -> 203782.47 | T58: =SUM(Financials!GY65:HJ65) -> 203782.47 | U58: =SUM(Financials!HK65:HV65) -> 203782.47 | V58: =SUM(Financials!HW65:IH65) -> 203782.47 | W58: =SUM(Financials!II65:IT65) -> 203782.47 | X58: =SUM(Financials!IU65:JF65) -> 203782.47 | Y58: =SUM(Financials!JG65:JR65) -> 203782.47
B59: Total Depreciation & Amortization | C59: =SUM(C56:C58) -> 0 | D59: =SUM(D56:D58) -> 29126337 | E59: =SUM(E56:E58) -> 36593509 | F59: =SUM(F56:F58) -> 36593509 | G59: =SUM(G56:G58) -> 36593509 | H59: =SUM(H56:H58) -> 36593509 | I59: =SUM(I56:I58) -> 36593509 | J59: =SUM(J56:J58) -> 36736366 | ... Y59: =SUM(Y56:Y58) -> 1203782.5
B61: EBIT | C61: =C51-C59 -> -4213882 | D61: =D51-D59 -> -1550764.3 | E61: =E51-E59 -> 20066373 | F61: =F51-F59 -> 28380129 | G61: =G51-G59 -> 30588536 | H61: =H51-H59 -> 31934787 | I61: =I51-I59 -> 33557205 | J61: =J51-J59 -> 35095065 | ... Y61: =Y51-Y59 -> 94677201
B63: Interest Expense | C63: =SUM('Capital Contributions'!E32:P32) -> 9254241.3 | D63: =SUM('Capital Contributions'!O32:Z32) -> 14539844 | E63: =SUM('Capital Contributions'!AA32:AL32) -> 12846521 | F63: =SUM('Capital Contributions'!AO32:AZ32) -> 11888300 | G63: =SUM('Capital Contributions'!BA32:BL32) -> 11002521 | H63: =SUM('Capital Contributions'!BM32:BX32) -> 10052709 | I63: =SUM('Capital Contributions'!BY32:CJ32) -> 9034234.5 | J63: =SUM('Capital Contributions'!CK32:CV32) -> 7942135 | K63: =SUM('Capital Contributions'!CW32:DH32) -> 6771087.5 | L63: =SUM('Capital Contributions'!DI32:DT32) -> 5515384.8 | M63: =SUM('Capital Contributions'!DU32:EF32) -> 4168907.3 | N63: =SUM('Capital Contributions'!EG32:ER32) -> 2970391.9 | O63: =SUM('Capital Contributions'!ES32:FD32) -> 2396680.3 | P63: =SUM('Capital Contributions'!FE32:FP32) -> 1824323.1 | Q63: =SUM('Capital Contributions'!FQ32:GB32) -> 1210590.1 | R63: =SUM('Capital Contributions'!GC32:GN32) -> 552490.3 | S63: =SUM('Capital Contributions'!GO32:GZ32) -> 29793.111 | T63: =SUM('Capital Contributions'!HA32:HJ32) -> 0 | U63: =SUM('Capital Contributions'!HM32:HX32) -> 0 | V63: =SUM('Capital Contributions'!HY32:IJ32) -> 0 | W63: =SUM('Capital Contributions'!IK32:IV32) -> 0 | X63: =SUM('Capital Contributions'!IW2:JH2) -> 0 | Y63: =SUM('Capital Contributions'!JI2:JT2) -> 0
B65: Earnings Before Taxes | C65: =C61-C63 -> -13468123 | D65: =D61-D63 -> -16090608 | E65: =E61-E63 -> 7219852.4 | F65: =F61-F63 -> 16491830 | G65: =G61-G63 -> 19586016 | H65: =H61-H63 -> 21882079 | I65: =I61-I63 -> 24522970 | J65: =J61-J63 -> 27152930 | ... Y65: =Y61-Y63 -> 94677201
B67: Income Taxes
B68: Colorado
B69: Tax Expense / Liability | C69: =IF(C65<0,0,C65*Inputs!$G$23) -> 0 | D69: =IF(D65<0,0,D65*Inputs!$G$23) -> 0 | E69: =IF(E65<0,0,E65*Inputs!$G$23) -> 0 | F69: =IF(F65<0,0,F65*Inputs!$G$23) -> 0 | G69: =IF(G65<0,0,G65*Inputs!$G$23) -> 0
B70: Total Colorado Tax Expense | C70: =SUM(C69:C69) -> 0 | D70: =SUM(D69:D69) -> 0 | E70: =SUM(E69:E69) -> 0 | F70: =SUM(F69:F69) -> 0 | G70: =SUM(G69:G69) -> 0
B72: Earning after State Taxes | C72: =C65-C70 -> -13468123 | D72: =D65-D70 -> -16090608 | E72: =E65-E70 -> 7219852.4 | F72: =F65-F70 -> 16491830 | G72: =G65-G70 -> 19586016
B74: Net Operating Loss Carryforward | C74: =SUM(Financials!C81:N81) -> -92145167 | D74: =SUM(Financials!O81:Z81) -> -3.1356098e+08 | E74: =SUM(Financials!AA81:AL81) -> -3.8450383e+08 | F74: =SUM(Financials!AM81:AX81) -> -2.5466594e+08 | G74: =SUM(Financials!AY81:BJ81) -> -80835440 | H74: =SUM(Financials!BK81:BV81) -> 0 | I74: =SUM(Financials!BW81:CH81) -> 0 | J74: =SUM(Financials!CI81:CT81) -> 0 | K74: =SUM(Financials!CU81:DF81) -> 0 | L74: =SUM(Financials!DG81:DR81) -> 0 | M74: =SUM(Financials!DS81:ED81) -> 0 | N74: =SUM(Financials!EE81:EP81) -> 0 | O74: =SUM(Financials!EQ81:FB81) -> 0 | P74: =SUM(Financials!FC81:FN81) -> 0 | Q74: =SUM(Financials!FO81:FZ81) -> 0 | R74: =SUM(Financials!GA81:GL81) -> 0 | S74: =SUM(Financials!GM81:GX81) -> 0 | T74: =SUM(Financials!GY81:HJ81) -> 0 | U74: =SUM(Financials!HK81:HV81) -> 0 | V74: =SUM(Financials!HW81:IH81) -> 0 | W74: =SUM(Financials!II81:IT81) -> 0 | X74: =SUM(Financials!IU81:JF81) -> 0 | Y74: =SUM(Financials!JG81:JR81) -> 0
B75: Net Operating Loss Utilization | C75: =SUM(Financials!C82:N82) -> 0 | D75: =SUM(Financials!O82:Z82) -> 0 | E75: =SUM(Financials!AA82:AL82) -> 7982213.8 | F75: =SUM(Financials!AM82:AX82) -> 13193464 | G75: =SUM(Financials!AY82:BJ82) -> 13664037 | H75: =SUM(Financials!BK82:BV82) -> 0 | I75: =SUM(Financials!BW82:CH82) -> 0 | J75: =SUM(Financials!CI82:CT82) -> 0 | K75: =SUM(Financials!CU82:DF82) -> 0 | L75: =SUM(Financials!DG82:DR82) -> 0 | M75: =SUM(Financials!DS82:ED82) -> 0 | N75: =SUM(Financials!EE82:EP82) -> 0 | O75: =SUM(Financials!EQ82:FB82) -> 0 | P75: =SUM(Financials!FC82:FN82) -> 0 | Q75: =SUM(Financials!FO82:FZ82) -> 0 | R75: =SUM(Financials!GA82:GL82) -> 0 | S75: =SUM(Financials!GM82:GX82) -> 0 | T75: =SUM(Financials!GY82:HJ82) -> 0 | U75: =SUM(Financials!HK82:HV82) -> 0 | V75: =SUM(Financials!HW82:IH82) -> 0 | W75: =SUM(Financials!II82:IT82) -> 0 | X75: =SUM(Financials!IU82:JF82) -> 0 | Y75: =SUM(Financials!JG82:JR82) -> 0
B76: Federal Taxable Income | C76: =SUM(Financials!C83:N83) -> 0 | D76: =SUM(Financials!O83:Z83) -> 0 | E76: =SUM(Financials!AA83:AL83) -> 1995553.5 | F76: =SUM(Financials!AM83:AX83) -> 3298365.9 | G76: =SUM(Financials!AY83:BJ83) -> 5921978.8 | H76: =SUM(Financials!BK83:BV83) -> 21882079 | I76: =SUM(Financials!BW83:CH83) -> 24522970 | J76: =SUM(Financials!CI83:CT83) -> 27152930 | K76: =SUM(Financials!CU83:DF83) -> 57215424 | L76: =SUM(Financials!DG83:DR83) -> 69232185 | M76: =SUM(Financials!DS83:ED83) -> 72310153 | N76: =SUM(Financials!EE83:EP83) -> 75010555 | O76: =SUM(Financials!EQ83:FB83) -> 76983828 | P76: =SUM(Financials!FC83:FN83) -> 79000545 | Q76: =SUM(Financials!FO83:FZ83) -> 81248150 | R76: =SUM(Financials!GA83:GL83) -> 83588743 | S76: =SUM(Financials!GM83:GX83) -> 85620051 | T76: =SUM(Financials!GY83:HJ83) -> 87078847 | U76: =SUM(Financials!HK83:HV83) -> 88537261 | V76: =SUM(Financials!HW83:IH83) -> 90025686 | W76: =SUM(Financials!II83:IT83) -> 91544733 | X76: =SUM(Financials!IU83:JF83) -> 93095026 | Y76: =SUM(Financials!JG83:JR83) -> 94677201
B78: Federal
B79: Tax Expense / Liability | C79: =SUM(Financials!C86:N86) -> 0 | D79: =SUM(Financials!O86:Z86) -> 0 | E79: =SUM(Financials!AA86:AL86) -> 399110.69 | F79: =SUM(Financials!AM86:AX86) -> 659673.18 | G79: =SUM(Financials!AY86:BJ86) -> 1184395.8 | H79: =SUM(Financials!BK86:BV86) -> 4376415.8 | I79: =SUM(Financials!BW86:CH86) -> 4904594.1 | J79: =SUM(Financials!CI86:CT86) -> 5430586 | K79: =SUM(Financials!CU86:DF86) -> 11443085 | L79: =SUM(Financials!DG86:DR86) -> 13846437 | M79: =SUM(Financials!DS86:ED86) -> 14462031 | N79: =SUM(Financials!EE86:EP86) -> 15002111 | O79: =SUM(Financials!EQ86:FB86) -> 15396766 | P79: =SUM(Financials!FC86:FN86) -> 15800109 | Q79: =SUM(Financials!FO86:FZ86) -> 16249630 | R79: =SUM(Financials!GA86:GL86) -> 16717749 | S79: =SUM(Financials!GM86:GX86) -> 17124010 | T79: =SUM(Financials!GY86:HJ86) -> 17415769 | U79: =SUM(Financials!HK86:HV86) -> 17707452 | V79: =SUM(Financials!HW86:IH86) -> 18005137 | W79: =SUM(Financials!II86:IT86) -> 18308947 | X79: =SUM(Financials!IU86:JF86) -> 18619005 | Y79: =SUM(Financials!JG86:JR86) -> 18935440
B80: Total Federal Expense | C80: =SUM(C79:C79) -> 0 | D80: =SUM(D79:D79) -> 0 | E80: =SUM(E79:E79) -> 399110.69 | F80: =SUM(F79:F79) -> 659673.18 | G80: =SUM(G79:G79) -> 1184395.8 | H80: =SUM(H79:H79) -> 4376415.8 | I80: =SUM(I79:I79) -> 4904594.1 | J80: =SUM(J79:J79) -> 5430586 | ... Y80: =SUM(Y79:Y79) -> 18935440
B82: Total Tax Expense | C82: =SUM(Financials!C89:N89) -> 0 | D82: =SUM(Financials!O89:Z89) -> 0 | E82: =SUM(Financials!AA89:AL89) -> 0 | F82: =SUM(Financials!AM89:AX89) -> 0 | G82: =SUM(Financials!AY89:BJ89) -> 0 | H82: =SUM(Financials!BK89:BV89) -> 0 | I82: =SUM(Financials!BW89:CH89) -> 0 | J82: =SUM(Financials!CI89:CT89) -> 0 | K82: =SUM(Financials!CU89:DF89) -> 0 | L82: =SUM(Financials!DG89:DR89) -> 1201366.6 | M82: =SUM(Financials!DS89:ED89) -> 14462031 | N82: =SUM(Financials!EE89:EP89) -> 15002111 | O82: =SUM(Financials!EQ89:FB89) -> 15396766 | P82: =SUM(Financials!FC89:FN89) -> 15800109 | Q82: =SUM(Financials!FO89:FZ89) -> 16249630 | R82: =SUM(Financials!GA89:GL89) -> 16717749 | S82: =SUM(Financials!GM89:GX89) -> 17124010 | T82: =SUM(Financials!GY89:HJ89) -> 17415769 | U82: =SUM(Financials!HK89:HV89) -> 17707452 | V82: =SUM(Financials!HW89:IH89) -> 18005137 | W82: =SUM(Financials!II89:IT89) -> 18308947 | X82: =SUM(Financials!IU89:JF89) -> 18619005 | Y82: =SUM(Financials!JG89:JR89) -> 18935440
B84: Net Income | C84: =C65-C82 -> -13468123 | D84: =D65-D82 -> -16090608 | E84: =E65-E82 -> 7219852.4 | F84: =F65-F82 -> 16491830 | G84: =G65-G82 -> 19586016 | H84: =H65-H82 -> 21882079 | I84: =I65-I82 -> 24522970 | J84: =J65-J82 -> 27152930 | ... Y84: =Y65-Y82 -> 75741761
B87: Cashflow Statement
B88: Net Income | C88: =C84 -> -13468123 | D88: =D84 -> -16090608 | E88: =E84 -> 7219852.4 | F88: =F84 -> 16491830 | G88: =G84 -> 19586016 | H88: =H84 -> 21882079 | I88: =I84 -> 24522970 | J88: =J84 -> 27152930 | ... Y88: =Y84 -> 75741761
B89: Depreciation | C89: =SUM(C56:C57) -> 0 | D89: =SUM(D56:D57) -> 27292295 | E89: =SUM(E56:E57) -> 36389726 | F89: =SUM(F56:F57) -> 36389726 | G89: =SUM(G56:G57) -> 36389726 | H89: =SUM(H56:H57) -> 36389726 | I89: =SUM(I56:I57) -> 36389726 | J89: =SUM(J56:J57) -> 36532584 | ... Y89: =SUM(Y56:Y57) -> 1000000
B90: Amortization | C90: =C58 -> 0 | D90: =D58 -> 1834042.2 | E90: =E58 -> 203782.47 | F90: =F58 -> 203782.47 | G90: =G58 -> 203782.47 | H90: =H58 -> 203782.47 | I90: =I58 -> 203782.47 | J90: =J58 -> 203782.47 | ... Y90: =Y58 -> 203782.47
B91: Net Cashflow from Operating Activities | C91: =SUM(C88:C90) -> -13468123 | D91: =SUM(D88:D90) -> 13035729 | E91: =SUM(E88:E90) -> 43813361 | F91: =SUM(F88:F90) -> 53085338 | G91: =SUM(G88:G90) -> 56179524 | H91: =SUM(H88:H90) -> 58475588 | I91: =SUM(I88:I90) -> 61116479 | J91: =SUM(J88:J90) -> 63889296 | ... Y91: =SUM(Y88:Y90) -> 76945544
B93: Capital Expenditures | C93: =C53 -> 0 | D93: =D53 -> 0 | E93: =E53 -> 0 | F93: =F53 -> 0 | G93: =G53 -> 0 | H93: =H53 -> 0 | I93: =I53 -> 0 | J93: =J53 -> 1000000 | ... Y93: =Y53 -> 1000000
B94: Debt Amortization Payments | C94: =SUM('Capital Contributions'!E33:P33) -> 0 | D94: =SUM('Capital Contributions'!Q33:AB33) -> 8061833.3 | E94: =SUM('Capital Contributions'!AC33:AN33) -> 11427056 | F94: =SUM('Capital Contributions'!AO33:AZ33) -> 12253119 | G94: =SUM('Capital Contributions'!BA33:BL33) -> 13138898 | H94: =SUM('Capital Contributions'!BM33:BX33) -> 14088710 | I94: =SUM('Capital Contributions'!BY33:CJ33) -> 15107184 | J94: =SUM('Capital Contributions'!CK33:CV33) -> 16199284 | K94: =SUM('Capital Contributions'!CW33:DH33) -> 17370331 | L94: =SUM('Capital Contributions'!DI33:DT33) -> 18626034 | M94: =SUM('Capital Contributions'!DU33:EF33) -> 19972511 | N94: =SUM('Capital Contributions'!EG33:ER33) -> 10800603 | O94: =SUM('Capital Contributions'!ES33:FD33) -> 7917507.2 | P94: =SUM('Capital Contributions'!FE33:FP33) -> 8489864.4 | Q94: =SUM('Capital Contributions'!FQ33:GB33) -> 9103597.4 | R94: =SUM('Capital Contributions'!GC33:GN33) -> 9761697.2 | S94: =SUM('Capital Contributions'!GO33:GZ33) -> 2548753.8 | T94: =SUM('Capital Contributions'!HA33:HL33) -> 0 | U94: =SUM('Capital Contributions'!HM33:HX33) -> 0 | V94: =SUM('Capital Contributions'!HY33:IJ33) -> 0 | W94: =SUM('Capital Contributions'!IK33:IV33) -> 0 | X94: =SUM('Capital Contributions'!IW33:JH33) -> 0 | Y94: =SUM('Capital Contributions'!JI33:JT33) -> 0
B95: Maintenance Fund Contributions | C95: =SUM(Financials!C102:N102) -> 0 | D95: =SUM(Financials!O102:Z102) -> 567368.14 | E95: =SUM(Financials!AA102:AL102) -> 1625923.2 | F95: =SUM(Financials!AM102:AX102) -> 2041611 | G95: =SUM(Financials!AY102:BJ102) -> 2152031.3 | H95: =SUM(Financials!BK102:BV102) -> 2219343.9 | I95: =SUM(Financials!BW102:CH102) -> 2300464.8 | J95: =SUM(Financials!CI102:CT102) -> 2334500.6 | K95: =SUM(Financials!CU102:DF102) -> 2421601 | L95: =SUM(Financials!DG102:DR102) -> 2451856.9 | M95: =SUM(Financials!DS102:ED102) -> 1882541.1 | N95: =SUM(Financials!EE102:EP102) -> 2456295.5 | O95: =SUM(Financials!EQ102:FB102) -> 2686524 | P95: =SUM(Financials!FC102:FN102) -> 2745717.7 | Q95: =SUM(Financials!FO102:FZ102) -> 2804935.3 | R95: =SUM(Financials!GA102:GL102) -> 2865654 | S95: =SUM(Financials!GM102:GX102) -> 3307553.5 | T95: =SUM(Financials!GY102:HJ102) -> 3493343 | U95: =SUM(Financials!HK102:HV102) -> 3551679.6 | V95: =SUM(Financials!HW102:IH102) -> 1178450 | W95: =SUM(Financials!II102:IT102) -> 0 | X95: =SUM(Financials!IU102:JF102) -> 0 | Y95: =SUM(Financials!JG102:JR102) -> 0
B97: Total Project Cash Flow | C97: =SUM(Financials!C104:N104) -> 0 | D97: =SUM(Financials!O104:Z104) -> 10779995 | E97: =SUM(Financials!AA104:AL104) -> 30892540 | F97: =SUM(Financials!AM104:AX104) -> 38790608 | G97: =SUM(Financials!AY104:BJ104) -> 40888595 | H97: =SUM(Financials!BK104:BV104) -> 42167534 | I97: =SUM(Financials!BW104:CH104) -> 43708830 | J97: =SUM(Financials!CI104:CT104) -> 44355512 | K97: =SUM(Financials!CU104:DF104) -> 46010420 | L97: =SUM(Financials!DG104:DR104) -> 46585282 | M97: =SUM(Financials!DS104:ED104) -> 35768281 | N97: =SUM(Financials!EE104:EP104) -> 46669614 | O97: =SUM(Financials!EQ104:FB104) -> 51043957 | P97: =SUM(Financials!FC104:FN104) -> 52168636 | Q97: =SUM(Financials!FO104:FZ104) -> 53293770 | R97: =SUM(Financials!GA104:GL104) -> 54447426 | S97: =SUM(Financials!GM104:GX104) -> 62843516 | T97: =SUM(Financials!GY104:HJ104) -> 66373517 | U97: =SUM(Financials!HK104:HV104) -> 67481912 | V97: =SUM(Financials!HW104:IH104) -> 71045881 | W97: =SUM(Financials!II104:IT104) -> 73439569 | X97: =SUM(Financials!IU104:JF104) -> 74679803 | Y97: =SUM(Financials!JG104:JR104) -> 75945544 | Z97: =SUM(E97:Y97) -> 1.1186007e+09 | AA97: =SUM(Z97/20) -> 55930037
B99: Maintenance Fund | C99: =Financials!N106 -> 0 | D99: =Financials!Z106 -> 567368.14 | E99: =Financials!AL106 -> 2193291.3 | F99: =Financials!AX106 -> 4234902.3 | G99: =Financials!BJ106 -> 6386933.6 | H99: =Financials!BV106 -> 8606277.5 | I99: =Financials!CH106 -> 10906742 | J99: =Financials!CT106 -> 13241243 | K99: =Financials!DF106 -> 15662844 | L99: =Financials!DR106 -> 18114701 | M99: =Financials!ED106 -> 19997242 | N99: =Financials!EP106 -> 22453537 | O99: =Financials!FB106 -> 25140061 | P99: =Financials!FN106 -> 27885779 | Q99: =Financials!FZ106 -> 30690714 | R99: =Financials!GL106 -> 33556368 | S99: =Financials!GX106 -> 36863922 | T99: =Financials!HJ106 -> 40357265 | U99: =Financials!HV106 -> 43908944 | V99: =Financials!IH106 -> 45087394 | W99: =Financials!IT106 -> 45087394 | X99: =Financials!JF106 -> 45087394 | Y99: =Financials!JR106 -> 45087394

Sheet Quarterly
A2: Year | B2: ='Financials Yearly'!C2 -> 2026 | F2: =SUM('Financials Yearly'!$C2 + 1) -> 2027 | J2: =F2+1 -> 2028 | N2: =J2+1 -> 2029 | R2: =N2+1 -> 2030 | V2: =R2+1 -> 2031 | Z2: =V2+1 -> 2032 | AD2: =Z2+1 -> 2033 | AH2: =AD2+1 -> 2034 | AL2: =AH2+1 -> 2035 | AP2: =AL2+1 -> 2036 | AT2: =AP2+1 -> 2037 | AX2: =AT2+1 -> 2038 | BB2: =AX2+1 -> 2039 | BF2: =BB2+1 -> 2040 | BJ2: =BF2+1 -> 2041 | BN2: =BJ2+1 -> 2042 | BR2: =BN2+1 -> 2043 | BV2: =BR2+1 -> 2044 | BZ2: =BV2+1 -> 2045 | CD2: =BZ2+1 -> 2046 | CH2: =CD2+1 -> 2047 | CL2: =CH2+1 -> 2048
A3: Quarter | B3: Jan - Mar | C3: Apr - Jun | D3: Jul - Sep | E3: Oct - Dec | F3: Jan - Mar | G3: Apr - Jun | H3: Jul - Sep | I3: Oct - Dec | J3: Jan - Mar | K3: Apr - Jun | L3: Jul - Sep | M3: Oct - Dec | N3: Jan - Mar | O3: Apr - Jun | P3: Jul - Sep | Q3: Oct - Dec | R3: Jan - Mar | S3: Apr - Jun | T3: Jul - Sep | U3: Oct - Dec | V3: Jan - Mar | W3: Apr - Jun | X3: Jul - Sep | Y3: Oct - Dec | Z3: Jan - Mar | AA3: Apr - Jun | AB3: Jul - Sep | AC3: Oct - Dec | AD3: Jan - Mar | AE3: Apr - Jun | AF3: Jul - Sep | AG3: Oct - Dec | AH3: Jan - Mar | AI3: Apr - Jun | AJ3: Jul - Sep | AK3: Oct - Dec | AL3: Jan - Mar | AM3: Apr - Jun | AN3: Jul - Sep | AO3: Oct - Dec | AP3: Jan - Mar | AQ3: Apr - Jun | AR3: Jul - Sep | AS3: Oct - Dec | AT3: Jan - Mar | AU3: Apr - Jun | AV3: Jul - Sep | AW3: Oct - Dec | AX3: Jan - Mar | AY3: Apr - Jun | AZ3: Jul - Sep | BA3: Oct - Dec | BB3: Jan - Mar | BC3: Apr - Jun | BD3: Jul - Sep | BE3: Oct - Dec | BF3: Jan - Mar | BG3: Apr - Jun | BH3: Jul - Sep | BI3: Oct - Dec | BJ3: Jan - Mar | BK3: Apr - Jun | BL3: Jul - Sep | BM3: Oct - Dec | BN3: Jan - Mar | BO3: Apr - Jun | BP3: Jul - Sep | BQ3: Oct - Dec | BR3: Jan - Mar | BS3: Apr - Jun | BT3: Jul - Sep | BU3: Oct - Dec | BV3: Jan - Mar | BW3: Apr - Jun | BX3: Jul - Sep | BY3: Oct - Dec | BZ3: Jan - Mar | CA3: Apr - Jun | CB3: Jul - Sep | CC3: Oct - Dec | CD3: Jan - Mar | CE3: Apr - Jun | CF3: Jul - Sep | CG3: Oct - Dec | CH3: Jan - Mar | CI3: Apr - Jun | CJ3: Jul - Sep | CK3: Oct - Dec | CL3: Jan - Mar | CM3: Apr - Jun | CN3: Jul - Sep | CO3: Oct - Dec
A4: =Financials!B11 -> Revenue Commodities
A5: =Financials!B12 -> Income Power | B5: =SUM(Financials!C12:E12) -> 0 | C5: =SUM(Financials!F12:H12) -> 0 | D5: =SUM(Financials!I12:K12) -> 0 | E5: =SUM(Financials!L12:N12) -> 0 | F5: =SUM(Financials!O12:Q12) -> 0 | G5: =SUM(Financials!R12:T12) -> 0 | H5: =SUM(Financials!U12:W12) -> 0 | I5: =SUM(Financials!X12:Z12) -> 0 | J5: =SUM(Financials!AA12:AC12) -> 0 | K5: =SUM(Financials!AD12:AF12) -> 5426570.3 | L5: =SUM(Financials!AG12:AI12) -> 5486202.9 | M5: =SUM(Financials!AJ12:AL12) -> 5486202.9 | N5: =SUM(Financials!AM12:AO12) -> 5366937.6 | O5: =SUM(Financials!AP12:AR12) -> 5426570.3 | P5: =SUM(Financials!AS12:AU12) -> 5486202.9 | Q5: =SUM(Financials!AV12:AX12) -> 5486202.9 | R5: =SUM(Financials!AY12:BA12) -> 5426570.3 | S5: =SUM(Financials!BB12:BD12) -> 5426570.3 | T5: =SUM(Financials!BE12:BG12) -> 5486202.9 | U5: =SUM(Financials!BH12:BJ12) -> 5486202.9 | V5: =SUM(Financials!BK12:BM12) -> 5366937.6 | W5: =SUM(Financials!BN12:BP12) -> 5426570.3 | X5: =SUM(Financials!BQ12:BS12) -> 5486202.9 | Y5: =SUM(Financials!BT12:BV12) -> 5486202.9 | Z5: =SUM(Financials!BW12:BY12) -> 5366937.6 | AA5: =SUM(Financials!BZ12:CB12) -> 5426570.3 | AB5: =SUM(Financials!CC12:CE12) -> 5486202.9 | AC5: =SUM(Financials!CF12:CH12) -> 5486202.9 | AD5: =SUM(Financials!CI12:CK12) -> 5366937.6 | AE5: =SUM(Financials!CL12:CN12) -> 5426570.3 | AF5: =SUM(Financials!CO12:CQ12) -> 5486202.9 | AG5: =SUM(Financials!CR12:CT12) -> 5486202.9 | AH5: =SUM(Financials!CU12:CW12) -> 5366937.6 | AI5: =SUM(Financials!CX12:CZ12) -> 5426570.3 | AJ5: =SUM(Financials!DA12:DC12) -> 5486202.9 | AK5: =SUM(Financials!DD12:DF12) -> 5486202.9 | AL5: =SUM(Financials!DG12:DI12) -> 5366937.6 | AM5: =SUM(Financials!DJ12:DL12) -> 5426570.3 | AN5: =SUM(Financials!DM12:DO12) -> 5486202.9 | AO5: =SUM(Financials!DP12:DR12) -> 5486202.9 | AP5: =SUM(Financials!DS12:DU12) -> 5366937.6 | AQ5: =SUM(Financials!DV12:DX12) -> 5426570.3 | AR5: =SUM(Financials!DY12:EA12) -> 5486202.9 | AS5: =SUM(Financials!EB12:ED12) -> 5486202.9 | AT5: =SUM(Financials!EE12:EG12) -> 5366937.6 | AU5: =SUM(Financials!EH12:EJ12) -> 5426570.3 | AV5: =SUM(Financials!EK12:EM12) -> 5486202.9 | AW5: =SUM(Financials!EN12:EP12) -> 5486202.9 | AX5: =SUM(Financials!EQ12:ES12) -> 5366937.6 | AY5: =SUM(Financials!ET12:EV12) -> 5426570.3 | AZ5: =SUM(Financials!EW12:EY12) -> 5486202.9 | BA5: =SUM(Financials!EZ12:FB12) -> 5486202.9 | BB5: =SUM(Financials!FC12:FE12) -> 5366937.6 | BC5: =SUM(Financials!FF12:FH12) -> 5426570.3 | BD5: =SUM(Financials!FI12:FK12) -> 5486202.9 | BE5: =SUM(Financials!FL12:FN12) -> 5486202.9 | BF5: =SUM(Financials!FO12:FQ12) -> 5366937.6 | BG5: =SUM(Financials!FR12:FT12) -> 5426570.3 | BH5: =SUM(Financials!FU12:FW12) -> 5486202.9 | BI5: =SUM(Financials!FX12:FZ12) -> 5486202.9 | BJ5: =SUM(Financials!GA12:GC12) -> 5366937.6 | BK5: =SUM(Financials!GD12:GF12) -> 5426570.3 | BL5: =SUM(Financials!GG12:GI12) -> 5486202.9 | BM5: =SUM(Financials!GJ12:GL12) -> 5486202.9 | BN5: =SUM(Financials!GM12:GO12) -> 5366937.6 | BO5: =SUM(Financials!GP12:GR12) -> 5426570.3 | BP5: =SUM(Financials!GS12:GU12) -> 5486202.9 | BQ5: =SUM(Financials!GV12:GX12) -> 5486202.9 | BR5: =SUM(Financials!GY12:HA12) -> 5366937.6 | BS5: =SUM(Financials!HB12:HD12) -> 5426570.3 | BT5: =SUM(Financials!HE12:HG12) -> 5486202.9 | BU5: =SUM(Financials!HH12:HJ12) -> 5486202.9 | BV5: =SUM(Financials!HK12:HM12) -> 5366937.6 | BW5: =SUM(Financials!HN12:HP12) -> 5426570.3 | BX5: =SUM(Financials!HQ12:HS12) -> 5486202.9 | BY5: =SUM(Financials!HT12:HV12) -> 5486202.9 | BZ5: =SUM(Financials!HW12:HY12) -> 5366937.6 | CA5: =SUM(Financials!HZ12:IB12) -> 5426570.3 | CB5: =SUM(Financials!IC12:IE12) -> 5486202.9 | CC5: =SUM(Financials!IF12:IH12) -> 5486202.9 | CD5: =SUM(Financials!II12:IK12) -> 5366937.6 | CE5: =SUM(Financials!IL12:IN12) -> 5426570.3 | CF5: =SUM(Financials!IO12:IQ12) -> 5486202.9 | CG5: =SUM(Financials!IR12:IT12) -> 5486202.9 | CH5: =SUM(Financials!IU12:IW12) -> 5366937.6 | CI5: =SUM(Financials!IX12:IZ12) -> 5426570.3 | CJ5: =SUM(Financials!JA12:JC12) -> 5486202.9 | CK5: =SUM(Financials!JD12:JF12) -> 5486202.9 | CL5: =SUM(Financials!JG12:JI12) -> 5366937.6 | CM5: =SUM(Financials!JJ12:JL12) -> 5426570.3 | CN5: =SUM(Financials!JM12:JO12) -> 5486202.9 | CO5: =SUM(Financials!JP12:JR12) -> 5486202.9
A6: =Financials!B13 -> RNG Sale price | B6: =SUM(Financials!C13:E13) -> 0 | C6: =SUM(Financials!F13:H13) -> 0 | D6: =SUM(Financials!I13:K13) -> 0 | E6: =SUM(Financials!L13:N13) -> 0 | F6: =SUM(Financials!O13:Q13) -> 0 | G6: =SUM(Financials!R13:T13) -> 0 | H6: =SUM(Financials!U13:W13) -> 0 | I6: =SUM(Financials!X13:Z13) -> 0 | J6: =SUM(Financials!AA13:AC13) -> 0 | K6: =SUM(Financials!AD13:AF13) -> 0 | L6: =SUM(Financials!AG13:AI13) -> 0 | M6: =SUM(Financials!AJ13:AL13) -> 0 | N6: =SUM(Financials!AM13:AO13) -> 0 | O6: =SUM(Financials!AP13:AR13) -> 0 | P6: =SUM(Financials!AS13:AU13) -> 0 | Q6: =SUM(Financials!AV13:AX13) -> 0 | R6: =SUM(Financials!AY13:BA13) -> 0 | S6: =SUM(Financials!BB13:BD13) -> 0 | T6: =SUM(Financials!BE13:BG13) -> 0 | U6: =SUM(Financials!BH13:BJ13) -> 0 | V6: =SUM(Financials!BK13:BM13) -> 0 | W6: =SUM(Financials!BN13:BP13) -> 0 | X6: =SUM(Financials!BQ13:BS13) -> 0 | Y6: =SUM(Financials!BT13:BV13) -> 0 | Z6: =SUM(Financials!BW13:BY13) -> 0 | AA6: =SUM(Financials!BZ13:CB13) -> 0 | AB6: =SUM(Financials!CC13:CE13) -> 0 | AC6: =SUM(Financials!CF13:CH13) -> 0 | AD6: =SUM(Financials!CI13:CK13) -> 0 | AE6: =SUM(Financials!CL13:CN13) -> 0 | AF6: =SUM(Financials!CO13:CQ13) -> 0 | AG6: =SUM(Financials!CR13:CT13) -> 0 | AH6: =SUM(Financials!CU13:CW13) -> 0 | AI6: =SUM(Financials!CX13:CZ13) -> 0 | AJ6: =SUM(Financials!DA13:DC13) -> 0 | AK6: =SUM(Financials!DD13:DF13) -> 0 | AL6: =SUM(Financials!DG13:DI13) -> 0 | AM6: =SUM(Financials!DJ13:DL13) -> 0 | AN6: =SUM(Financials!DM13:DO13) -> 0 | AO6: =SUM(Financials!DP13:DR13) -> 0 | AP6: =SUM(Financials!DS13:DU13) -> 0 | AQ6: =SUM(Financials!DV13:DX13) -> 0 | AR6: =SUM(Financials!DY13:EA13) -> 0 | AS6: =SUM(Financials!EB13:ED13) -> 0 | AT6: =SUM(Financials!EE13:EG13) -> 0 | AU6: =SUM(Financials!EH13:EJ13) -> 0 | AV6: =SUM(Financials!EK13:EM13) -> 0 | AW6: =SUM(Financials!EN13:EP13) -> 0 | AX6: =SUM(Financials!EQ13:ES13) -> 0 | AY6: =SUM(Financials!ET13:EV13) -> 0 | AZ6: =SUM(Financials!EW13:EY13) -> 0 | BA6: =SUM(Financials!EZ13:FB13) -> 0 | BB6: =SUM(Financials!FC13:FE13) -> 0 | BC6: =SUM(Financials!FF13:FH13) -> 0 | BD6: =SUM(Financials!FI13:FK13) -> 0 | BE6: =SUM(Financials!FL13:FN13) -> 0 | BF6: =SUM(Financials!FO13:FQ13) -> 0 | BG6: =SUM(Financials!FR13:FT13) -> 0 | BH6: =SUM(Financials!FU13:FW13) -> 0 | BI6: =SUM(Financials!FX13:FZ13) -> 0 | BJ6: =SUM(Financials!GA13:GC13) -> 0 | BK6: =SUM(Financials!GD13:GF13) -> 0 | BL6: =SUM(Financials!GG13:GI13) -> 0 | BM6: =SUM(Financials!GJ13:GL13) -> 0 | BN6: =SUM(Financials!GM13:GO13) -> 0 | BO6: =SUM(Financials!GP13:GR13) -> 0 | BP6: =SUM(Financials!GS13:GU13) -> 0 | BQ6: =SUM(Financials!GV13:GX13) -> 0 | BR6: =SUM(Financials!GY13:HA13) -> 0 | BS6: =SUM(Financials!HB13:HD13) -> 0 | BT6: =SUM(Financials!HE13:HG13) -> 0 | BU6: =SUM(Financials!HH13:HJ13) -> 0 | BV6: =SUM(Financials!HK13:HM13) -> 0 | BW6: =SUM(Financials!HN13:HP13) -> 0 | BX6: =SUM(Financials!HQ13:HS13) -> 0 | BY6: =SUM(Financials!HT13:HV13) -> 0 | BZ6: =SUM(Financials!HW13:HY13) -> 0 | CA6: =SUM(Financials!HZ13:IB13) -> 0 | CB6: =SUM(Financials!IC13:IE13) -> 0 | CC6: =SUM(Financials!IF13:IH13) -> 0 | CD6: =SUM(Financials!II13:IK13) -> 0 | CE6: =SUM(Financials!IL13:IN13) -> 0 | CF6: =SUM(Financials!IO13:IQ13) -> 0 | CG6: =SUM(Financials!IR13:IT13) -> 0 | CH6: =SUM(Financials!IU13:IW13) -> 0 | CI6: =SUM(Financials!IX13:IZ13) -> 0 | CJ6: =SUM(Financials!JA13:JC13) -> 0 | CK6: =SUM(Financials!JD13:JF13) -> 0 | CL6: =SUM(Financials!JG13:JI13) -> 0 | CM6: =SUM(Financials!JJ13:JL13) -> 0 | CN6: =SUM(Financials!JM13:JO13) -> 0 | CO6: =SUM(Financials!JP13:JR13) -> 0
A7: =Financials!B14 -> Activated Carbon Ash | B7: =SUM(Financials!C14:E14) -> 0 | C7: =SUM(Financials!F14:H14) -> 0 | D7: =SUM(Financials!I14:K14) -> 0 | E7: =SUM(Financials!L14:N14) -> 0 | F7: =SUM(Financials!O14:Q14) -> 0 | G7: =SUM(Financials!R14:T14) -> 3878791.3 | H7: =SUM(Financials!U14:W14) -> 3940983.8 | I7: =SUM(Financials!X14:Z14) -> 3960793.3 | J7: =SUM(Financials!AA14:AC14) -> 3894095 | K7: =SUM(Financials!AD14:AF14) -> 3957082.2 | L7: =SUM(Financials!AG14:AI14) -> 4020530 | M7: =SUM(Financials!AJ14:AL14) -> 4040739.4 | N7: =SUM(Financials!AM14:AO14) -> 3972694.8 | O7: =SUM(Financials!AP14:AR14) -> 4036953.3 | P7: =SUM(Financials!AS14:AU14) -> 4101681.8 | Q7: =SUM(Financials!AV14:AX14) -> 4122299.1 | R7: =SUM(Financials!AY14:BA14) -> 4097913 | S7: =SUM(Financials!BB14:BD14) -> 4118436.6 | T7: =SUM(Financials!BE14:BG14) -> 4184471.6 | U7: =SUM(Financials!BH14:BJ14) -> 4205505.1 | V7: =SUM(Financials!BK14:BM14) -> 4134685.9 | W7: =SUM(Financials!BN14:BP14) -> 4201564.6 | X7: =SUM(Financials!BQ14:BS14) -> 4268932.5 | Y7: =SUM(Financials!BT14:BV14) -> 4290390.5 | Z7: =SUM(Financials!BW14:BY14) -> 4218141.8 | AA7: =SUM(Financials!BZ14:CB14) -> 4286370.5 | AB7: =SUM(Financials!CC14:CE14) -> 4355098.2 | AC7: =SUM(Financials!CF14:CH14) -> 4376989.3 | AD7: =SUM(Financials!CI14:CK14) -> 4303282.3 | AE7: =SUM(Financials!CL14:CN14) -> 4372888.1 | AF7: =SUM(Financials!CO14:CQ14) -> 4443003 | AG7: =SUM(Financials!CR14:CT14) -> 4465336 | AH7: =SUM(Financials!CU14:CW14) -> 4390141.3 | AI7: =SUM(Financials!CX14:CZ14) -> 4461152.1 | AJ7: =SUM(Financials!DA14:DC14) -> 4532682.2 | AK7: =SUM(Financials!DD14:DF14) -> 4555465.9 | AL7: =SUM(Financials!DG14:DI14) -> 4478753.5 | AM7: =SUM(Financials!DJ14:DL14) -> 4551197.5 | AN7: =SUM(Financials!DM14:DO14) -> 4624171.4 | AO7: =SUM(Financials!DP14:DR14) -> 4647415 | AP7: =SUM(Financials!DS14:DU14) -> 4569154.2 | AQ7: =SUM(Financials!DV14:DX14) -> 4643060.5 | AR7: =SUM(Financials!DY14:EA14) -> 4717507.4 | AS7: =SUM(Financials!EB14:ED14) -> 4741220.1 | AT7: =SUM(Financials!EE14:EG14) -> 4661379.6 | AU7: =SUM(Financials!EH14:EJ14) -> 4736777.7 | AV7: =SUM(Financials!EK14:EM14) -> 4812727.2 | AW7: =SUM(Financials!EN14:EP14) -> 4836918.6 | AX7: =SUM(Financials!EQ14:ES14) -> 4755466.6 | AY7: =SUM(Financials!ET14:EV14) -> 4832386.5 | AZ7: =SUM(Financials!EW14:EY14) -> 4909869 | BA7: =SUM(Financials!EZ14:FB14) -> 4934548.7 | BB7: =SUM(Financials!FC14:FE14) -> 4851452.6 | BC7: =SUM(Financials!FF14:FH14) -> 4929925.1 | BD7: =SUM(Financials!FI14:FK14) -> 5008971.5 | BE7: =SUM(Financials!FL14:FN14) -> 5034149.4 | BF7: =SUM(Financials!FO14:FQ14) -> 4949376.1 | BG7: =SUM(Financials!FR14:FT14) -> 5029432.5 | BH7: =SUM(Financials!FU14:FW14) -> 5110074.4 | BI7: =SUM(Financials!FX14:FZ14) -> 5135760.4 | BJ7: =SUM(Financials!GA14:GC14) -> 5049276 | BK7: =SUM(Financials!GD14:GF14) -> 5130948.3 | BL7: =SUM(Financials!GG14:GI14) -> 5213218 | BM7: =SUM(Financials!GJ14:GL14) -> 5239422.4 | BN7: =SUM(Financials!GM14:GO14) -> 5151192.4 | BO7: =SUM(Financials!GP14:GR14) -> 5234513.2 | BP7: =SUM(Financials!GS14:GU14) -> 5318443.4 | BQ7: =SUM(Financials!GV14:GX14) -> 5345176.8 | BR7: =SUM(Financials!GY14:HA14) -> 5255165.9 | BS7: =SUM(Financials!HB14:HD14) -> 5340168.5 | BT7: =SUM(Financials!HE14:HG14) -> 5425792.8 | BU7: =SUM(Financials!HH14:HJ14) -> 5453065.8 | BV7: =SUM(Financials!HK14:HM14) -> 5361238 | BW7: =SUM(Financials!HN14:HP14) -> 5447956.4 | BX7: =SUM(Financials!HQ14:HS14) -> 5535308.9 | BY7: =SUM(Financials!HT14:HV14) -> 5563132.4 | BZ7: =SUM(Financials!HW14:HY14) -> 5469451.2 | CA7: =SUM(Financials!HZ14:IB14) -> 5557919.9 | CB7: =SUM(Financials!IC14:IE14) -> 5647035.5 | CC7: =SUM(Financials!IF14:IH14) -> 5675420.6 | CD7: =SUM(Financials!II14:IK14) -> 5579848.5 | CE7: =SUM(Financials!IL14:IN14) -> 5670102.9 | CF7: =SUM(Financials!IO14:IQ14) -> 5761017.3 | CG7: =SUM(Financials!IR14:IT14) -> 5789975.3 | CH7: =SUM(Financials!IU14:IW14) -> 5692474.2 | CI7: =SUM(Financials!IX14:IZ14) -> 5784550.3 | CJ7: =SUM(Financials!JA14:JC14) -> 5877299.7 | CK7: =SUM(Financials!JD14:JF14) -> 5906842.2 | CL7: =SUM(Financials!JG14:JI14) -> 5807373.1 | CM7: =SUM(Financials!JJ14:JL14) -> 5901307.7 | CN7: =SUM(Financials!JM14:JO14) -> 5995929.2 | CO7: =SUM(Financials!JP14:JR14) -> 6026068.1
A8: =Financials!B15 -> Aluminum | B8: =SUM(Financials!C15:E15) -> 0 | C8: =SUM(Financials!F15:H15) -> 0 | D8: =SUM(Financials!I15:K15) -> 0 | E8: =SUM(Financials!L15:N15) -> 0 | F8: =SUM(Financials!O15:Q15) -> 0 | G8: =SUM(Financials!R15:T15) -> 864952.63 | H8: =SUM(Financials!U15:W15) -> 878821.28 | I8: =SUM(Financials!X15:Z15) -> 883238.71 | J8: =SUM(Financials!AA15:AC15) -> 868365.28 | K8: =SUM(Financials!AD15:AF15) -> 882411.14 | L8: =SUM(Financials!AG15:AI15) -> 896559.72 | M8: =SUM(Financials!AJ15:AL15) -> 901066.32 | N8: =SUM(Financials!AM15:AO15) -> 885892.68 | O8: =SUM(Financials!AP15:AR15) -> 900222.04 | P8: =SUM(Financials!AS15:AU15) -> 914656.2 | Q8: =SUM(Financials!AV15:AX15) -> 919253.76 | R8: =SUM(Financials!AY15:BA15) -> 913815.77 | S8: =SUM(Financials!BB15:BD15) -> 918392.44 | T8: =SUM(Financials!BE15:BG15) -> 933117.95 | U8: =SUM(Financials!BH15:BJ15) -> 937808.31 | V8: =SUM(Financials!BK15:BM15) -> 922015.94 | W8: =SUM(Financials!BN15:BP15) -> 936929.6 | X8: =SUM(Financials!BQ15:BS15) -> 951952.33 | Y8: =SUM(Financials!BT15:BV15) -> 956737.36 | Z8: =SUM(Financials!BW15:BY15) -> 940626.24 | AA8: =SUM(Financials!BZ15:CB15) -> 955840.92 | AB8: =SUM(Financials!CC15:CE15) -> 971166.88 | AC8: =SUM(Financials!CF15:CH15) -> 976048.49 | AD8: =SUM(Financials!CI15:CK15) -> 959612.18 | AE8: =SUM(Financials!CL15:CN15) -> 975133.96 | AF8: =SUM(Financials!CO15:CQ15) -> 990769.25 | AG8: =SUM(Financials!CR15:CT15) -> 995749.4 | AH8: =SUM(Financials!CU15:CW15) -> 978981.33 | AI8: =SUM(Financials!CX15:CZ15) -> 994816.41 | AJ8: =SUM(Financials!DA15:DC15) -> 1010767.3 | AK8: =SUM(Financials!DD15:DF15) -> 1015848 | AL8: =SUM(Financials!DG15:DI15) -> 998741.44 | AM8: =SUM(Financials!DJ15:DL15) -> 1014896.1 | AN8: =SUM(Financials!DM15:DO15) -> 1031169 | AO8: =SUM(Financials!DP15:DR15) -> 1036352.2 | AP8: =SUM(Financials!DS15:DU15) -> 1018900.4 | AQ8: =SUM(Financials!DV15:DX15) -> 1035381.2 | AR8: =SUM(Financials!DY15:EA15) -> 1051982.5 | AS8: =SUM(Financials!EB15:ED15) -> 1057270.3 | AT8: =SUM(Financials!EE15:EG15) -> 1039466.2 | AU8: =SUM(Financials!EH15:EJ15) -> 1056279.7 | AV8: =SUM(Financials!EK15:EM15) -> 1073216 | AW8: =SUM(Financials!EN15:EP15) -> 1078610.6 | AX8: =SUM(Financials!EQ15:ES15) -> 1060447.2 | AY8: =SUM(Financials!ET15:EV15) -> 1077600 | AZ8: =SUM(Financials!EW15:EY15) -> 1094878.2 | BA8: =SUM(Financials!EZ15:FB15) -> 1100381.7 | BB8: =SUM(Financials!FC15:FE15) -> 1081851.6 | BC8: =SUM(Financials!FF15:FH15) -> 1099350.6 | BD8: =SUM(Financials!FI15:FK15) -> 1116977.6 | BE8: =SUM(Financials!FL15:FN15) -> 1122592.2 | BF8: =SUM(Financials!FO15:FQ15) -> 1103688.1 | BG8: =SUM(Financials!FR15:FT15) -> 1121540.3 | BH8: =SUM(Financials!FU15:FW15) -> 1139523.1 | BI8: =SUM(Financials!FX15:FZ15) -> 1145251 | BJ8: =SUM(Financials!GA15:GC15) -> 1125965.3 | BK8: =SUM(Financials!GD15:GF15) -> 1144177.9 | BL8: =SUM(Financials!GG15:GI15) -> 1162523.6 | BM8: =SUM(Financials!GJ15:GL15) -> 1168367.1 | BN8: =SUM(Financials!GM15:GO15) -> 1148692.2 | BO8: =SUM(Financials!GP15:GR15) -> 1167272.4 | BP8: =SUM(Financials!GS15:GU15) -> 1185988.4 | BQ8: =SUM(Financials!GV15:GX15) -> 1191949.9 | BR8: =SUM(Financials!GY15:HA15) -> 1171877.8 | BS8: =SUM(Financials!HB15:HD15) -> 1190833 | BT8: =SUM(Financials!HE15:HG15) -> 1209926.9 | BU8: =SUM(Financials!HH15:HJ15) -> 1216008.6 | BV8: =SUM(Financials!HK15:HM15) -> 1195531.4 | BW8: =SUM(Financials!HN15:HP15) -> 1214869.2 | BX8: =SUM(Financials!HQ15:HS15) -> 1234348.4 | BY8: =SUM(Financials!HT15:HV15) -> 1240553 | BZ8: =SUM(Financials!HW15:HY15) -> 1219662.5 | CA8: =SUM(Financials!HZ15:IB15) -> 1239390.6 | CB8: =SUM(Financials!IC15:IE15) -> 1259263 | CC8: =SUM(Financials!IF15:IH15) -> 1265592.7 | CD8: =SUM(Financials!II15:IK15) -> 1244280.6 | CE8: =SUM(Financials!IL15:IN15) -> 1264406.9 | CF8: =SUM(Financials!IO15:IQ15) -> 1284680.4 | CG8: =SUM(Financials!IR15:IT15) -> 1291137.9 | CH8: =SUM(Financials!IU15:IW15) -> 1269395.6 | CI8: =SUM(Financials!IX15:IZ15) -> 1289928.1 | CJ8: =SUM(Financials!JA15:JC15) -> 1310610.8 | CK8: =SUM(Financials!JD15:JF15) -> 1317198.7 | CL8: =SUM(Financials!JG15:JI15) -> 1295017.5 | CM8: =SUM(Financials!JJ15:JL15) -> 1315964.5 | CN8: =SUM(Financials!JM15:JO15) -> 1337064.7 | CO8: =SUM(Financials!JP15:JR15) -> 1343785.5
